Workbook
Name Запрос2: #REF!
Name ср_взв_квартал: #REF!
Name ср_взв_т: #REF!
Name срв_квартал_: 'Срв квартал'!$A$1:$C$15211
Name срв_мо_: 'Срв мо'!$A$1:$C$74

Sheet Объекты оценки
A1: Идентификатор | B1: Кадастровый номер | C1: Номер кадастрового квартала | D1: Площадь в квадратных метрах | E1: Категория земель | F1: Разрешенное использование участка Вид разрешенного использования по классификатору | G1: Вид использования участка по документу | H1: Разрешенное использование участка | I1: Разрешенное использование (текстовое описание) | J1: Кадастровая стоимость | K1: Дата определения кадастровой стоимости | L1: Удельный показатель кадастровой стоимости(руб/м2) | M1: Кадастровая стоимость (руб) | N1: Кадастровая стоимость описание вых | O1: Группа для XML | P1: Код населённого пункта | Q1: Код расчета вида использования | R1: Расшифровка расчетной подгруппы | S1: Сегмент | T1: Признак актуальности | U1: Номер заявления | V1: Тип заявления | W1: Статус заявления | X1: Дата пакета | Y1: Особый контроль | Z1: флажок | AA1: Дата комиссии | AB1: Решение комиссии | AC1: Статус расчета | AD1: НЕ Используется | AE1: Флаг ВРИ по документу | AF1: Флаг Местоположения (координат) | AG1: Флаг площади | AH1: Флаг ВРИ старый спр | AI1: Флаг ВРИ новый спр | AJ1: Флаг Категории ЗУ | AK1: Старый код НП | AL1: Флаг переопределения ФРИ | AM1: ВРИ по правилам | AN1: Правило | AO1: Новоя модель | AP1: Новый сегмент | AQ1: Суд | AR1: Дата заседания | AS1: Стоимость по суду | AW1: Specific_CadastralCost | AX1: CadastralCost | AY1: CadastralCostDesc | AZ1: id_group | BA1: loc_Factor_831 | BB1: CadastralNumber | BI1: ОПИСАНИЕ КС | BN1: Кадастровый номер | BO1: УПКС | BP1: Кадастровый номер | BQ1: Описание КС | BR1: Группа хмл | BS1: Средневзвш.упкс | BT1: Статус расчета | BU1: Сегмент | BV1: Код сегмента | BW1: ВРИ | BX1: Расшифровка расчетной подгруппы | BY1: Вид использования учтенный при ТЕКУЩЕМ расчете в рамках 16 статьи для загрузки в базу (в базе название колонки "ВРИ по документу старое") | BZ1: ИЗМЕНЕНИЕ КС | CA1: ИЗМЕНЕНИЕ, руб. | CB1: Новый/Старый | CF1: =IF(CF2="ОТСУТСТВУЮТ","-",CF2=ГОТОВО!N1) -> - | CG1: =IF(CG2="ОТСУТСТВУЮТ","-",CG2='ПЕРЕСЧЕТ НЕ ТРЕБУЕТСЯ'!I1) -> - | CH1: =IF(CH2="ОТСУТСТВУЮТ","-",CH2=СТОПЛИСТ!D1) -> -
A2: ID | B2: CadastralNumber | C2: CadastralBlock | D2: Area | E2: ParcelCategory | F2: Utilization | G2: UtilizationByDoc | H2: UtilizationLandUse | I2: UtilizationТхт | J2: CostValue | K2: CostDateValuation | L2: Specific_CadastralCost | M2: CadastralCost | N2: CadastralCostDesc | O2: ID_Group | P2: LocalityCode | Q2: loc_VICode | R2: loc_GroupName | S2: Segment | T2: act_sign | U2: Statement | V2: Type_Statement | W2: Status_Statement | X2: inputpacket_date | Y2: ControlSP | Z2: Sp_flag | AA2: Date_comm | AB2: Sol_comm | AC2: Status_kc | AD2: Flag_LocalityCode | AE2: Flag_VRI | AF2: Flag_Location | AG2: FlagParam | AH2: Flag_VRIoldspr | AI2: Flag_VRInewspr | AJ2: Flag_Category | AK2: OldLocalityCode | AL2: Flag_VRI_All | AM2: VRICode_NEW | AN2: PraviloVRI | AO2: New_id_group | AP2: New_Segment | AQ2: Court | AR2: Date_Court | AS2: Sol_Court | AT2: Код МО | AU2: СРДНВЗВШ ПО КВАРТАЛУ | AV2: СРДНВЗВШ ПО МО | AW2: УПКС СРДНВЗВШ, руб/м2 | AX2: КС, РУБ. | AY2: Описание КС | AZ2: Группа xml | BA2: УПКС | BB2: Кадастровый номер | BC2: Код расчета вида использования | BD2: Модель | BE2: Площадь | BF2: УПКС | BG2: КС | BH2: ОБЯЗАТЕЛЬНАЯ ПРОВЕРКА | BI2: Файл | BJ2: Модель | BK2: Дата | BL2: Ответственный | BM2: Графика | BN2: CadastralNumber | BO2: Specific_CadastralCost | BP2: CadastralCost | BQ2: CadastralCostDesc | BR2: id_group | BS2: loc_Factor_831 | BT2: Status_kc | BU2: Segment | BV2: loc_SgCode | BW2: loc_VICode | BX2: loc_GroupName | BY2: Old_Utlbydoc | CF2: =IF(AND(ГОТОВО!N1=1,COUNTIF(BT:BT,"ГОТОВ")=0),"ОТСУТСТВУЮТ",COUNTIF(BT:BT,"ГОТОВ")+1) -> ОТСУТСТВУЮТ | CG2: =IF(AND('ПЕРЕСЧЕТ НЕ ТРЕБУЕТСЯ'!I1=1,COUNTIF(BT:BT,"ПЕРЕСЧЕТ НЕ ТРЕБУЕТСЯ")=0),"ОТСУТСТВУЮТ",COUNTIF(BT:BT,"ПЕРЕСЧЕТ НЕ ТРЕБУЕТСЯ")+1) -> ОТСУТСТВУЮТ | CH2: =IF(AND(СТОПЛИСТ!D1=1,COUNTIF(BT:BT,"СТОПЛИСТ")=0),"ОТСУТСТВУЮТ",COUNTIF(BT:BT,"СТОПЛИСТ")+1) -> ОТСУТСТВУЮТ
A3: Parcels | B3: Parcels | C3: Parcels | D3: Parcels | E3: Parcels | F3: Parcels | G3: Parcels | H3: Parcels | I3: Parcels | J3: Parcels | K3: Parcels | L3: Parcels | M3: Parcels | N3: Parcels | O3: Parcels | P3: Parcels | Q3: Parcels | R3: Parcels | S3: Parcels | T3: Parcels | U3: Parcels | V3: Parcels | W3: Parcels | X3: Parcels | Y3: Parcels | Z3: Parcels | AA3: Parcels | AB3: Parcels | AC3: Parcels | AD3: Parcels | AE3: Parcels | AF3: Parcels | AG3: Parcels | AH3: Parcels | AI3: Parcels | AJ3: Parcels | AK3: Parcels | AL3: Parcels | AM3: Parcels | AN3: Parcels | AO3: Parcels | AP3: Parcels | AQ3: Parcels | AR3: Parcels | AS3: Parcels | AT3: =IF(B3="","",LEFT(P3,2)) -> Pa | AU3: =IF(B3="","",IFERROR(VLOOKUP(C3,'Срв квартал'!$A:$D,4,FALSE),"")) | AV3: =IF(B3="","",VLOOKUP(AT3,'Срв мо'!$A:$D,4,FALSE)) -> #N/A | AW3: =IF(B3="","",IF(OR(C3="0000000",AU3=""),AV3,AU3)) -> #N/A | AX3: =IF(B3="","",ROUND(AW3*D3,2)) -> #N/A | AY3: =IF(B3="","",CONCATENATE("СТ16_",BI3,"_",BJ3,"_",BK3,"_",BL3,"_",BM3,"_",CB3)) -> СТ16_Ф13_М10_25.05.2021_Фомин__Измененный | AZ3: =IF(B3="","",#REF!) -> #REF! | BA3: =IF(B3="","",AW3) -> #N/A | BB3: =IF(B3="","",B3) -> Parcels | BC3: =IF(B3="","",IF(MID(AM3,3,1)<>":","ОШИБКА В ФОРМАТЕ КОДА НП",IF(L3="","Отсутствуют предыдущие значения",AM3=Q3))) -> ОШИБКА В ФОРМАТЕ КОДА НП | BD3: =IF(B3="","",IF(L3="","Отсутствуют предыдущие значения",AO3=O3)) -> TRUE | BE3: =IF(B3="","",IF(L3="","Отсутствуют предыдущие значения",#REF!=D3)) -> #REF! | BF3: =IF(B3="","",IF(L3="","Отсутствуют предыдущие значения",AW3=L3)) -> #N/A | BG3: =IF(B3="","",IF(M3="","Отсутствуют предыдущие значения",AX3=M3)) -> #N/A | BH3: =IF(B3="","",IF(AB3<>"","ОСПАРИВАНИЕ",IF(U3="","",U3))) -> ОСПАРИВАНИЕ | BI3: ='реквизиты файла'!B$1 -> Ф13 | BJ3: ='реквизиты файла'!B$2 -> М10 | BK3: ='реквизиты файла'!B$3 -> 25.05.2021 | BL3: ='реквизиты файла'!B$4 -> Фомин | BN3: =IF(B3="","",B3) -> Parcels | BO3: =IF(B3="","",AW3) -> #N/A | BP3: =IF(B3="","",AX3) -> #N/A | BQ3: =IF(B3="","",AY3) -> СТ16_Ф13_М10_25.05.2021_Фомин__Измененный | BR3: ='реквизиты файла'!B5 -> 8010 | BS3: =IF(B3="","",BA3) -> #N/A | BT3: =IF(B3="","",IF(OR(Y3<>"",AB3<>"",BP3<0,AQ3<>""),"СТОПЛИСТ",IF(V3=21,"СТОПЛИСТ",IF(AND(BC3=TRUE,BE3=TRUE),"ПЕРЕСЧЕТ НЕ ТРЕБУЕТСЯ",IF(OR(BZ3="Отсутствует значения предыдущих расчетов",BZ3="Осуществлен пересчет"),"ГОТОВ","ПЕРЕСЧЕТ НЕ ТРЕБУЕТСЯ"))))) -> #N/A | BU3: =IF(B3="","",AP3) -> Parcels | BV3: =IF(B3="","",VLOOKUP(BU3,Справочник_ВРИ_Сегментов!$A:$D,4,)) -> #N/A | BW3: =IF(B3="","",AM3) -> Parcels | BX3: =IF(B3="","",VLOOKUP(BW3,Справочник_ВРИ_Сегментов!$B:$C,2,FALSE)) -> #N/A | BY3: =IF(B3="","",IF(OR(G3="",G3="-",G3="."),H3,G3)) -> Parcels | BZ3: =IF(B3="","",IF(M3="","Отсутствует значения предыдущих расчетов",IF(M3=AX3,"Значения КС не изменилось","Осуществлен пересчет"))) -> #N/A | CA3: =IF(B3="","-",M3-AX3) -> #VALUE! | CB3: =IF(B3="","",IF(L3="","Новый","Измененный")) -> Измененный
E4: spr | F4: spr | H4: spr | AT4: =IF(B4="","",LEFT(P4,2)) | AU4: =IF(B4="","",IFERROR(VLOOKUP(C4,'Срв квартал'!$A:$D,4,FALSE),"")) | AV4: =IF(B4="","",VLOOKUP(AT4,'Срв мо'!$A:$D,4,FALSE)) | AW4: =IF(B4="","",IF(OR(C4="0000000",AU4=""),AV4,AU4)) | AX4: =IF(B4="","",ROUND(AW4*D4,2)) | AY4: =IF(B4="","",CONCATENATE("СТ16_",BI4,"_",BJ4,"_",BK4,"_",BL4,"_",BM4,"_",CB4)) | AZ4: =IF(B4="","",#REF!) | BA4: =IF(B4="","",AW4) | BB4: =IF(B4="","",B4) | BC4: =IF(B4="","",IF(MID(AM4,3,1)<>":","ОШИБКА В ФОРМАТЕ КОДА НП",IF(L4="","Отсутствуют предыдущие значения",AM4=Q4))) | BD4: =IF(B4="","",IF(L4="","Отсутствуют предыдущие значения",AO4=O4)) | BE4: =IF(B4="","",IF(L4="","Отсутствуют предыдущие значения",#REF!=D4)) | BF4: =IF(B4="","",IF(L4="","Отсутствуют предыдущие значения",AW4=L4)) | BG4: =IF(B4="","",IF(M4="","Отсутствуют предыдущие значения",AX4=M4)) | BH4: =IF(B4="","",IF(AB4<>"","ОСПАРИВАНИЕ",IF(U4="","",U4))) | BI4: ='реквизиты файла'!B$1 -> Ф13 | BJ4: ='реквизиты файла'!B$2 -> М10 | BK4: ='реквизиты файла'!B$3 -> 25.05.2021 | BL4: ='реквизиты файла'!B$4 -> Фомин | BN4: =IF(B4="","",B4) | BO4: =IF(B4="","",AW4) | BP4: =IF(B4="","",AX4) | BQ4: =IF(B4="","",AY4) | BR4: =IF(B4="","",AZ4) | BS4: =IF(B4="","",BA4) | BT4: =IF(B4="","",IF(OR(Y4<>"",AB4<>"",BP4<0,AQ4<>""),"СТОПЛИСТ",IF(V4=21,"СТОПЛИСТ",IF(AND(BC4=TRUE,BE4=TRUE),"ПЕРЕСЧЕТ НЕ ТРЕБУЕТСЯ",IF(OR(BZ4="Отсутствует значения предыдущих расчетов",BZ4="Осуществлен пересчет"),"ГОТОВ","ПЕРЕСЧЕТ НЕ ТРЕБУЕТСЯ"))))) | BU4: =IF(B4="","",AP4) | BV4: =IF(B4="","",VLOOKUP(BU4,Справочник_ВРИ_Сегментов!$A:$D,4,)) | BW4: =IF(B4="","",AM4) | BX4: =IF(B4="","",VLOOKUP(BW4,Справочник_ВРИ_Сегментов!$B:$C,2,FALSE)) | BY4: =IF(B4="","",IF(OR(G4="",G4="-",G4="."),H4,G4)) | BZ4: =IF(B4="","",IF(M4="","Отсутствует значения предыдущих расчетов",IF(M4=AX4,"Значения КС не изменилось","Осуществлен пересчет"))) | CA4: =IF(B4="","-",M4-AX4) -> - | CB4: =IF(B4="","",IF(L4="","Новый","Измененный"))
AT5: =IF(B5="","",LEFT(P5,2)) | AU5: =IF(B5="","",IFERROR(VLOOKUP(C5,'Срв квартал'!$A:$D,4,FALSE),"")) | AV5: =IF(B5="","",VLOOKUP(AT5,'Срв мо'!$A:$D,4,FALSE)) | AW5: =IF(B5="","",IF(OR(C5="0000000",AU5=""),AV5,AU5)) | AX5: =IF(B5="","",ROUND(AW5*D5,2)) | AY5: =IF(B5="","",CONCATENATE("СТ16_",BI5,"_",BJ5,"_",BK5,"_",BL5,"_",BM5,"_",CB5)) | AZ5: =IF(B5="","",#REF!) | BA5: =IF(B5="","",AW5) | BB5: =IF(B5="","",B5) | BC5: =IF(B5="","",IF(MID(AM5,3,1)<>":","ОШИБКА В ФОРМАТЕ КОДА НП",IF(L5="","Отсутствуют предыдущие значения",AM5=Q5))) | BD5: =IF(B5="","",IF(L5="","Отсутствуют предыдущие значения",AO5=O5)) | BE5: =IF(B5="","",IF(L5="","Отсутствуют предыдущие значения",#REF!=D5)) | BF5: =IF(B5="","",IF(L5="","Отсутствуют предыдущие значения",AW5=L5)) | BG5: =IF(B5="","",IF(M5="","Отсутствуют предыдущие значения",AX5=M5)) | BH5: =IF(B5="","",IF(AB5<>"","ОСПАРИВАНИЕ",IF(U5="","",U5))) | BI5: ='реквизиты файла'!B$1 -> Ф13 | BJ5: ='реквизиты файла'!B$2 -> М10 | BK5: ='реквизиты файла'!B$3 -> 25.05.2021 | BL5: ='реквизиты файла'!B$4 -> Фомин | BN5: =IF(B5="","",B5) | BO5: =IF(B5="","",AW5) | BP5: =IF(B5="","",AX5) | BQ5: =IF(B5="","",AY5) | BR5: =IF(B5="","",AZ5) | BS5: =IF(B5="","",BA5) | BT5: =IF(B5="","",IF(OR(Y5<>"",AB5<>"",BP5<0,AQ5<>""),"СТОПЛИСТ",IF(V5=21,"СТОПЛИСТ",IF(AND(BC5=TRUE,BE5=TRUE),"ПЕРЕСЧЕТ НЕ ТРЕБУЕТСЯ",IF(OR(BZ5="Отсутствует значения предыдущих расчетов",BZ5="Осуществлен пересчет"),"ГОТОВ","ПЕРЕСЧЕТ НЕ ТРЕБУЕТСЯ"))))) | BU5: =IF(B5="","",AP5) | BV5: =IF(B5="","",VLOOKUP(BU5,Справочник_ВРИ_Сегментов!$A:$D,4,)) | BW5: =IF(B5="","",AM5) | BX5: =IF(B5="","",VLOOKUP(BW5,Справочник_ВРИ_Сегментов!$B:$C,2,FALSE)) | BY5: =IF(B5="","",IF(OR(G5="",G5="-",G5="."),H5,G5)) | BZ5: =IF(B5="","",IF(M5="","Отсутствует значения предыдущих расчетов",IF(M5=AX5,"Значения КС не изменилось","Осуществлен пересчет"))) | CA5: =IF(B5="","-",M5-AX5) -> - | CB5: =IF(B5="","",IF(L5="","Новый","Измененный"))
A6: Select ID,Source_ID,CadastralNumber,DateCreated,CadastralBlock,Name,ObjectType,Area,AreaUnit,AreaInaccuracy,LocationinBounds,LocationPlaced,ElaborationReferenceMark,ElaborationDistance,ElaborationDirection,AddressOrLocation,FIAS,OKATO,KLADR,OKTMO,PostalCode,AddressRF,Region,DistrictName,DistrictType,CityName,CityType,UrbanDistrictName,UrbanDistrictType,SovietVillageName,SovietVillageType,LocalityName,LocalityType,PlanningElementName,PlanningElementType,StreetName,StreetType,Level1Type,Level1Value,Level2Type,Level2Value,Level3Type,Level3Value,ApartmentType,ApartmentValue,AddressOther,AddressNote,ParcelCategory,Utilization,UtilizationByDoc,UtilizationLandUse,UtilizationТхт,CostValue,CostUnit,CostDateValuation,CostDateEntering,CostDateApproval,CostDocNumber,CostDocDate,CostApplicationDate,CostRevisalStatementDate,CostApplicationLastDate,CostDocName,FacilityKN,FacilityKNPurpose,SurveyProjectNum,DecisionCodeDocument,DecisionName,DecisionSeries,DecisionNumber,DecisionDate,DecisionIssueOrgan,DecisionDesc,HiredHouseUse,HouseActBuilding,HouseActDevelopment,BuildingContractName,DevelopContractName,OwnerDecision,SupportContractName,CodeDocument,DocHiredHouseName,DocHiredHouseSeries,DocHiredHouseNumber,DocHiredHouseDate,DocHiredHouseIssueOrgan,DocHiredHouseDesc,LimitedRightNumber,CREATEOPERATORNAME,CREATEDATE,OPERATORNAME,MODIFYDATE,MI_STYLE,Specific_CadastralCost,CadastralCost,CadastralCostDesc,MO_Name,ID_Group,LocalityCode,locTypeUse2,loc_VICode,loc_GroupName,loc_VRICode,Sourse_loc_VICode,locTypeUse,inputpacket_id,loc_SgCode,VIP_Sp,Quant_Kontur,Quant_Point,Sum_Square,Sum_Perim,Proc_Diff_Square,Pr_Diff,Source_Sum_Square,SourceLocalityCode,Upload_Scroll,Date_KC,Segment,FlagLocalityCode,DistanceToRoad,DistanceToCMO,СМО,PresenceGas,SourcePresenceGas,PresenceHeating,SourcePresenceHeating,PresencePower,SourcePresencePower,PresenceWaterDisposal,SourcePresenceWaterDisposal,PresenceWaterSupply,SourcePresenceWaterSupply,DistanceToEKB,DistanceToRoadEKB,CCoordX,CCoordY,DistanceToMetro,DistanceToStationEKB,CostZone,DistanceToRRStation,costzone2,Textloc_VICode,act_sign,MaxFloor,Enc_squre,Enc_proc,Adm_rn_EKB,forestry,InfluenceZone_IGS,loc_factor_801,loc_factor_802,loc_factor_803,loc_factor_804,loc_factor_806,loc_factor_807,loc_factor_8071,loc_factor_809,loc_factor_8091,loc_factor_810,loc_factor_8101,loc_factor_811,loc_factor_8111,loc_factor_812,loc_factor_8121,loc_factor_813,loc_factor_814,loc_factor_815,loc_factor_816,loc_factor_8161,loc_factor_817,loc_factor_818,loc_factor_819,loc_factor_820,loc_factor_8201,loc_factor_821,loc_factor_822,loc_factor_823,loc_factor_8231,loc_factor_824,loc_factor_825,loc_factor_826,loc_factor_827,loc_factor_828,loc_factor_829,loc_factor_830,loc_factor_831,loc_factor_832,loc_factor_833,loc_factor_8331,loc_factor_835,loc_factor_836,loc_factor_837,loc_factor_838,Statement,Type_Statement,Status_Statement,DistanceToVZC,VRI_IGS,Cot_name,DistanceToZTB,PowerLines,loc_factor_839,KodMO,loc_factor_840,loc_factor_841,presence_entrance,loc_factor_8371,ControlSP,Sp_flag,loc_VRICode540,Status_kc,Date_comm,Sol_comm,Flag_LocalityCode,Flag_VRI,Flag_Location,FlagParam,Flag_VRIoldspr,Flag_VRInewspr,Flag_Category,OldLocalityCode,Flag_VRI_All,VRICode_NEW,PraviloVRI,New_id_group,New_loc_SgCode,New_Segment,Old_Utlbydoc,VRICode_OLD,PraviloVRI_old,Court,Date_Court,Sol_Court,(select (case count(*) when 0 then 0 else 1 end) from GEO.docboxes b where b.obj_id=PARCELS.ID and b.table_id=265) Attachment,(select sign(Count(*)) from PARCELS g where (not GEOM_OBJ is null) and (PARCELS.ID = g.ID)) GeometryExists,((select DatePacket from inputpacket where id=Parcels.inputpacket_id) ) [inputpacket_date] From PARCELS where status_kc='НЕ ГОТОВ' AND CadastralCost is null AND New_id_group=8010 AND NEW_LOC_SGCODE = '6' | AT6: =IF(B6="","",LEFT(P6,2)) | AU6: =IF(B6="","",IFERROR(VLOOKUP(C6,'Срв квартал'!$A:$D,4,FALSE),"")) | AV6: =IF(B6="","",VLOOKUP(AT6,'Срв мо'!$A:$D,4,FALSE)) | AW6: =IF(B6="","",IF(OR(C6="0000000",AU6=""),AV6,AU6)) | AX6: =IF(B6="","",ROUND(AW6*D6,2)) | AY6: =IF(B6="","",CONCATENATE("СТ16_",BI6,"_",BJ6,"_",BK6,"_",BL6,"_",BM6,"_",CB6)) | AZ6: =IF(B6="","",#REF!) | BA6: =IF(B6="","",AW6) | BB6: =IF(B6="","",B6) | BC6: =IF(B6="","",IF(MID(AM6,3,1)<>":","ОШИБКА В ФОРМАТЕ КОДА НП",IF(L6="","Отсутствуют предыдущие значения",AM6=Q6))) | BD6: =IF(B6="","",IF(L6="","Отсутствуют предыдущие значения",AO6=O6)) | BE6: =IF(B6="","",IF(L6="","Отсутствуют предыдущие значения",#REF!=D6)) | BF6: =IF(B6="","",IF(L6="","Отсутствуют предыдущие значения",AW6=L6)) | BG6: =IF(B6="","",IF(M6="","Отсутствуют предыдущие значения",AX6=M6)) | BH6: =IF(B6="","",IF(AB6<>"","ОСПАРИВАНИЕ",IF(U6="","",U6))) | BI6: =IF(B6="","",#REF!) | BJ6: =IF(B6="","",#REF!) | BK6: =IF(B6="","",#REF!) | BL6: =IF(B6="","",#REF!) | BM6: =IF(B6="","",IF(L6="","Графика по ПКК","Графика на 01012020")) | BN6: =IF(B6="","",B6) | BO6: =IF(B6="","",AW6) | BP6: =IF(B6="","",AX6) | BQ6: =IF(B6="","",AY6) | BR6: =IF(B6="","",AZ6) | BS6: =IF(B6="","",BA6) | BT6: =IF(B6="","",IF(OR(Y6<>"",AB6<>"",BP6<0,AQ6<>""),"СТОПЛИСТ",IF(V6=21,"СТОПЛИСТ",IF(AND(BC6=TRUE,BE6=TRUE),"ПЕРЕСЧЕТ НЕ ТРЕБУЕТСЯ",IF(OR(BZ6="Отсутствует значения предыдущих расчетов",BZ6="Осуществлен пересчет"),"ГОТОВ","ПЕРЕСЧЕТ НЕ ТРЕБУЕТСЯ"))))) | BU6: =IF(B6="","",AP6) | BV6: =IF(B6="","",VLOOKUP(BU6,Справочник_ВРИ_Сегментов!$A:$D,4,)) | BW6: =IF(B6="","",AM6) | BX6: =IF(B6="","",VLOOKUP(BW6,Справочник_ВРИ_Сегментов!$B:$C,2,FALSE)) | BY6: =IF(B6="","",IF(OR(G6="",G6="-",G6="."),H6,G6)) | BZ6: =IF(B6="","",IF(M6="","Отсутствует значения предыдущих расчетов",IF(M6=AX6,"Значения КС не изменилось","Осуществлен пересчет"))) | CA6: =IF(B6="","-",M6-AX6) -> - | CB6: =IF(B6="","",IF(L6="","Новый","Измененный"))
AT7: =IF(B7="","",LEFT(P7,2)) | AU7: =IF(B7="","",IFERROR(VLOOKUP(C7,'Срв квартал'!$A:$D,4,FALSE),"")) | AV7: =IF(B7="","",VLOOKUP(AT7,'Срв мо'!$A:$D,4,FALSE)) | AW7: =IF(B7="","",IF(OR(C7="0000000",AU7=""),AV7,AU7)) | AX7: =IF(B7="","",ROUND(AW7*D7,2)) | AY7: =IF(B7="","",CONCATENATE("СТ16_",BI7,"_",BJ7,"_",BK7,"_",BL7,"_",BM7,"_",CB7)) | AZ7: =IF(B7="","",#REF!) | BA7: =IF(B7="","",AW7) | BB7: =IF(B7="","",B7) | BC7: =IF(B7="","",IF(MID(AM7,3,1)<>":","ОШИБКА В ФОРМАТЕ КОДА НП",IF(L7="","Отсутствуют предыдущие значения",AM7=Q7))) | BD7: =IF(B7="","",IF(L7="","Отсутствуют предыдущие значения",AO7=O7)) | BE7: =IF(B7="","",IF(L7="","Отсутствуют предыдущие значения",#REF!=D7)) | BF7: =IF(B7="","",IF(L7="","Отсутствуют предыдущие значения",AW7=L7)) | BG7: =IF(B7="","",IF(M7="","Отсутствуют предыдущие значения",AX7=M7)) | BH7: =IF(B7="","",IF(AB7<>"","ОСПАРИВАНИЕ",IF(U7="","",U7))) | BI7: =IF(B7="","",#REF!) | BJ7: =IF(B7="","",#REF!) | BK7: =IF(B7="","",#REF!) | BL7: =IF(B7="","",#REF!) | BM7: =IF(B7="","",IF(L7="","Графика по ПКК","Графика на 01012020")) | BN7: =IF(B7="","",B7) | BO7: =IF(B7="","",AW7) | BP7: =IF(B7="","",AX7) | BQ7: =IF(B7="","",AY7) | BR7: =IF(B7="","",AZ7) | BS7: =IF(B7="","",BA7) | BT7: =IF(B7="","",IF(OR(Y7<>"",AB7<>"",BP7<0,AQ7<>""),"СТОПЛИСТ",IF(V7=21,"СТОПЛИСТ",IF(AND(BC7=TRUE,BE7=TRUE),"ПЕРЕСЧЕТ НЕ ТРЕБУЕТСЯ",IF(OR(BZ7="Отсутствует значения предыдущих расчетов",BZ7="Осуществлен пересчет"),"ГОТОВ","ПЕРЕСЧЕТ НЕ ТРЕБУЕТСЯ"))))) | BU7: =IF(B7="","",AP7) | BV7: =IF(B7="","",VLOOKUP(BU7,Справочник_ВРИ_Сегментов!$A:$D,4,)) | BW7: =IF(B7="","",AM7) | BX7: =IF(B7="","",VLOOKUP(BW7,Справочник_ВРИ_Сегментов!$B:$C,2,FALSE)) | BY7: =IF(B7="","",IF(OR(G7="",G7="-",G7="."),H7,G7)) | BZ7: =IF(B7="","",IF(M7="","Отсутствует значения предыдущих расчетов",IF(M7=AX7,"Значения КС не изменилось","Осуществлен пересчет"))) | CA7: =IF(B7="","-",M7-AX7) -> - | CB7: =IF(B7="","",IF(L7="","Новый","Измененный"))
AT8: =IF(B8="","",LEFT(P8,2)) | AU8: =IF(B8="","",IFERROR(VLOOKUP(C8,'Срв квартал'!$A:$D,4,FALSE),"")) | AV8: =IF(B8="","",VLOOKUP(AT8,'Срв мо'!$A:$D,4,FALSE)) | AW8: =IF(B8="","",IF(OR(C8="0000000",AU8=""),AV8,AU8)) | AX8: =IF(B8="","",ROUND(AW8*D8,2)) | AY8: =IF(B8="","",CONCATENATE("СТ16_",BI8,"_",BJ8,"_",BK8,"_",BL8,"_",BM8,"_",CB8)) | AZ8: =IF(B8="","",#REF!) | BA8: =IF(B8="","",AW8) | BB8: =IF(B8="","",B8) | BC8: =IF(B8="","",IF(MID(AM8,3,1)<>":","ОШИБКА В ФОРМАТЕ КОДА НП",IF(L8="","Отсутствуют предыдущие значения",AM8=Q8))) | BD8: =IF(B8="","",IF(L8="","Отсутствуют предыдущие значения",AO8=O8)) | BE8: =IF(B8="","",IF(L8="","Отсутствуют предыдущие значения",#REF!=D8)) | BF8: =IF(B8="","",IF(L8="","Отсутствуют предыдущие значения",AW8=L8)) | BG8: =IF(B8="","",IF(M8="","Отсутствуют предыдущие значения",AX8=M8)) | BH8: =IF(B8="","",IF(AB8<>"","ОСПАРИВАНИЕ",IF(U8="","",U8))) | BI8: =IF(B8="","",#REF!) | BJ8: =IF(B8="","",#REF!) | BK8: =IF(B8="","",#REF!) | BL8: =IF(B8="","",#REF!) | BM8: =IF(B8="","",IF(L8="","Графика по ПКК","Графика на 01012020")) | BN8: =IF(B8="","",B8) | BO8: =IF(B8="","",AW8) | BP8: =IF(B8="","",AX8) | BQ8: =IF(B8="","",AY8) | BR8: =IF(B8="","",AZ8) | BS8: =IF(B8="","",BA8) | BT8: =IF(B8="","",IF(OR(Y8<>"",AB8<>"",BP8<0,AQ8<>""),"СТОПЛИСТ",IF(V8=21,"СТОПЛИСТ",IF(AND(BC8=TRUE,BE8=TRUE),"ПЕРЕСЧЕТ НЕ ТРЕБУЕТСЯ",IF(OR(BZ8="Отсутствует значения предыдущих расчетов",BZ8="Осуществлен пересчет"),"ГОТОВ","ПЕРЕСЧЕТ НЕ ТРЕБУЕТСЯ"))))) | BU8: =IF(B8="","",AP8) | BV8: =IF(B8="","",VLOOKUP(BU8,Справочник_ВРИ_Сегментов!$A:$D,4,)) | BW8: =IF(B8="","",AM8) | BX8: =IF(B8="","",VLOOKUP(BW8,Справочник_ВРИ_Сегментов!$B:$C,2,FALSE)) | BY8: =IF(B8="","",IF(OR(G8="",G8="-",G8="."),H8,G8)) | BZ8: =IF(B8="","",IF(M8="","Отсутствует значения предыдущих расчетов",IF(M8=AX8,"Значения КС не изменилось","Осуществлен пересчет"))) | CA8: =IF(B8="","-",M8-AX8) -> - | CB8: =IF(B8="","",IF(L8="","Новый","Измененный"))
AT9: =IF(B9="","",LEFT(P9,2)) | AU9: =IF(B9="","",IFERROR(VLOOKUP(C9,'Срв квартал'!$A:$D,4,FALSE),"")) | AV9: =IF(B9="","",VLOOKUP(AT9,'Срв мо'!$A:$D,4,FALSE)) | AW9: =IF(B9="","",IF(OR(C9="0000000",AU9=""),AV9,AU9)) | AX9: =IF(B9="","",ROUND(AW9*D9,2)) | AY9: =IF(B9="","",CONCATENATE("СТ16_",BI9,"_",BJ9,"_",BK9,"_",BL9,"_",BM9,"_",CB9)) | AZ9: =IF(B9="","",#REF!) | BA9: =IF(B9="","",AW9) | BB9: =IF(B9="","",B9) | BC9: =IF(B9="","",IF(MID(AM9,3,1)<>":","ОШИБКА В ФОРМАТЕ КОДА НП",IF(L9="","Отсутствуют предыдущие значения",AM9=Q9))) | BD9: =IF(B9="","",IF(L9="","Отсутствуют предыдущие значения",AO9=O9)) | BE9: =IF(B9="","",IF(L9="","Отсутствуют предыдущие значения",#REF!=D9)) | BF9: =IF(B9="","",IF(L9="","Отсутствуют предыдущие значения",AW9=L9)) | BG9: =IF(B9="","",IF(M9="","Отсутствуют предыдущие значения",AX9=M9)) | BH9: =IF(B9="","",IF(AB9<>"","ОСПАРИВАНИЕ",IF(U9="","",U9))) | BI9: =IF(B9="","",#REF!) | BJ9: =IF(B9="","",#REF!) | BK9: =IF(B9="","",#REF!) | BL9: =IF(B9="","",#REF!) | BM9: =IF(B9="","",IF(L9="","Графика по ПКК","Графика на 01012020")) | BN9: =IF(B9="","",B9) | BO9: =IF(B9="","",AW9) | BP9: =IF(B9="","",AX9) | BQ9: =IF(B9="","",AY9) | BR9: =IF(B9="","",AZ9) | BS9: =IF(B9="","",BA9) | BT9: =IF(B9="","",IF(OR(Y9<>"",AB9<>"",BP9<0,AQ9<>""),"СТОПЛИСТ",IF(V9=21,"СТОПЛИСТ",IF(AND(BC9=TRUE,BE9=TRUE),"ПЕРЕСЧЕТ НЕ ТРЕБУЕТСЯ",IF(OR(BZ9="Отсутствует значения предыдущих расчетов",BZ9="Осуществлен пересчет"),"ГОТОВ","ПЕРЕСЧЕТ НЕ ТРЕБУЕТСЯ"))))) | BU9: =IF(B9="","",AP9) | BV9: =IF(B9="","",VLOOKUP(BU9,Справочник_ВРИ_Сегментов!$A:$D,4,)) | BW9: =IF(B9="","",AM9) | BX9: =IF(B9="","",VLOOKUP(BW9,Справочник_ВРИ_Сегментов!$B:$C,2,FALSE)) | BY9: =IF(B9="","",IF(OR(G9="",G9="-",G9="."),H9,G9)) | BZ9: =IF(B9="","",IF(M9="","Отсутствует значения предыдущих расчетов",IF(M9=AX9,"Значения КС не изменилось","Осуществлен пересчет"))) | CA9: =IF(B9="","-",M9-AX9) -> - | CB9: =IF(B9="","",IF(L9="","Новый","Измененный"))
AT10: =IF(B10="","",LEFT(P10,2)) | AU10: =IF(B10="","",IFERROR(VLOOKUP(C10,'Срв квартал'!$A:$D,4,FALSE),"")) | AV10: =IF(B10="","",VLOOKUP(AT10,'Срв мо'!$A:$D,4,FALSE)) | AW10: =IF(B10="","",IF(OR(C10="0000000",AU10=""),AV10,AU10)) | AX10: =IF(B10="","",ROUND(AW10*D10,2)) | AY10: =IF(B10="","",CONCATENATE("СТ16_",BI10,"_",BJ10,"_",BK10,"_",BL10,"_",BM10,"_",CB10)) | AZ10: =IF(B10="","",#REF!) | BA10: =IF(B10="","",AW10) | BB10: =IF(B10="","",B10) | BC10: =IF(B10="","",IF(MID(AM10,3,1)<>":","ОШИБКА В ФОРМАТЕ КОДА НП",IF(L10="","Отсутствуют предыдущие значения",AM10=Q10))) | BD10: =IF(B10="","",IF(L10="","Отсутствуют предыдущие значения",AO10=O10)) | BE10: =IF(B10="","",IF(L10="","Отсутствуют предыдущие значения",#REF!=D10)) | BF10: =IF(B10="","",IF(L10="","Отсутствуют предыдущие значения",AW10=L10)) | BG10: =IF(B10="","",IF(M10="","Отсутствуют предыдущие значения",AX10=M10)) | BH10: =IF(B10="","",IF(AB10<>"","ОСПАРИВАНИЕ",IF(U10="","",U10))) | BI10: =IF(B10="","",#REF!) | BJ10: =IF(B10="","",#REF!) | BK10: =IF(B10="","",#REF!) | BL10: =IF(B10="","",#REF!) | BM10: =IF(B10="","",IF(L10="","Графика по ПКК","Графика на 01012020")) | BN10: =IF(B10="","",B10) | BO10: =IF(B10="","",AW10) | BP10: =IF(B10="","",AX10) | BQ10: =IF(B10="","",AY10) | BR10: =IF(B10="","",AZ10) | BS10: =IF(B10="","",BA10) | BT10: =IF(B10="","",IF(OR(Y10<>"",AB10<>"",BP10<0,AQ10<>""),"СТОПЛИСТ",IF(V10=21,"СТОПЛИСТ",IF(AND(BC10=TRUE,BE10=TRUE),"ПЕРЕСЧЕТ НЕ ТРЕБУЕТСЯ",IF(OR(BZ10="Отсутствует значения предыдущих расчетов",BZ10="Осуществлен пересчет"),"ГОТОВ","ПЕРЕСЧЕТ НЕ ТРЕБУЕТСЯ"))))) | BU10: =IF(B10="","",AP10) | BV10: =IF(B10="","",VLOOKUP(BU10,Справочник_ВРИ_Сегментов!$A:$D,4,)) | BW10: =IF(B10="","",AM10) | BX10: =IF(B10="","",VLOOKUP(BW10,Справочник_ВРИ_Сегментов!$B:$C,2,FALSE)) | BY10: =IF(B10="","",IF(OR(G10="",G10="-",G10="."),H10,G10)) | BZ10: =IF(B10="","",IF(M10="","Отсутствует значения предыдущих расчетов",IF(M10=AX10,"Значения КС не изменилось","Осуществлен пересчет"))) | CA10: =IF(B10="","-",M10-AX10) -> - | CB10: =IF(B10="","",IF(L10="","Новый","Измененный"))
AT11: =IF(B11="","",LEFT(P11,2)) | AU11: =IF(B11="","",IFERROR(VLOOKUP(C11,'Срв квартал'!$A:$D,4,FALSE),"")) | AV11: =IF(B11="","",VLOOKUP(AT11,'Срв мо'!$A:$D,4,FALSE)) | AW11: =IF(B11="","",IF(OR(C11="0000000",AU11=""),AV11,AU11)) | AX11: =IF(B11="","",ROUND(AW11*D11,2)) | AY11: =IF(B11="","",CONCATENATE("СТ16_",BI11,"_",BJ11,"_",BK11,"_",BL11,"_",BM11,"_",CB11)) | AZ11: =IF(B11="","",#REF!) | BA11: =IF(B11="","",AW11) | BB11: =IF(B11="","",B11) | BC11: =IF(B11="","",IF(MID(AM11,3,1)<>":","ОШИБКА В ФОРМАТЕ КОДА НП",IF(L11="","Отсутствуют предыдущие значения",AM11=Q11))) | BD11: =IF(B11="","",IF(L11="","Отсутствуют предыдущие значения",AO11=O11)) | BE11: =IF(B11="","",IF(L11="","Отсутствуют предыдущие значения",#REF!=D11)) | BF11: =IF(B11="","",IF(L11="","Отсутствуют предыдущие значения",AW11=L11)) | BG11: =IF(B11="","",IF(M11="","Отсутствуют предыдущие значения",AX11=M11)) | BH11: =IF(B11="","",IF(AB11<>"","ОСПАРИВАНИЕ",IF(U11="","",U11))) | BI11: =IF(B11="","",#REF!) | BJ11: =IF(B11="","",#REF!) | BK11: =IF(B11="","",#REF!) | BL11: =IF(B11="","",#REF!) | BM11: =IF(B11="","",IF(L11="","Графика по ПКК","Графика на 01012020")) | BN11: =IF(B11="","",B11) | BO11: =IF(B11="","",AW11) | BP11: =IF(B11="","",AX11) | BQ11: =IF(B11="","",AY11) | BR11: =IF(B11="","",AZ11) | BS11: =IF(B11="","",BA11) | BT11: =IF(B11="","",IF(OR(Y11<>"",AB11<>"",BP11<0,AQ11<>""),"СТОПЛИСТ",IF(V11=21,"СТОПЛИСТ",IF(AND(BC11=TRUE,BE11=TRUE),"ПЕРЕСЧЕТ НЕ ТРЕБУЕТСЯ",IF(OR(BZ11="Отсутствует значения предыдущих расчетов",BZ11="Осуществлен пересчет"),"ГОТОВ","ПЕРЕСЧЕТ НЕ ТРЕБУЕТСЯ"))))) | BU11: =IF(B11="","",AP11) | BV11: =IF(B11="","",VLOOKUP(BU11,Справочник_ВРИ_Сегментов!$A:$D,4,)) | BW11: =IF(B11="","",AM11) | BX11: =IF(B11="","",VLOOKUP(BW11,Справочник_ВРИ_Сегментов!$B:$C,2,FALSE)) | BY11: =IF(B11="","",IF(OR(G11="",G11="-",G11="."),H11,G11)) | BZ11: =IF(B11="","",IF(M11="","Отсутствует значения предыдущих расчетов",IF(M11=AX11,"Значения КС не изменилось","Осуществлен пересчет"))) | CA11: =IF(B11="","-",M11-AX11) -> - | CB11: =IF(B11="","",IF(L11="","Новый","Измененный"))
AT12: =IF(B12="","",LEFT(P12,2)) | AU12: =IF(B12="","",IFERROR(VLOOKUP(C12,'Срв квартал'!$A:$D,4,FALSE),"")) | AV12: =IF(B12="","",VLOOKUP(AT12,'Срв мо'!$A:$D,4,FALSE)) | AW12: =IF(B12="","",IF(OR(C12="0000000",AU12=""),AV12,AU12)) | AX12: =IF(B12="","",ROUND(AW12*D12,2)) | AY12: =IF(B12="","",CONCATENATE("СТ16_",BI12,"_",BJ12,"_",BK12,"_",BL12,"_",BM12,"_",CB12)) | AZ12: =IF(B12="","",#REF!) | BA12: =IF(B12="","",AW12) | BB12: =IF(B12="","",B12) | BC12: =IF(B12="","",IF(MID(AM12,3,1)<>":","ОШИБКА В ФОРМАТЕ КОДА НП",IF(L12="","Отсутствуют предыдущие значения",AM12=Q12))) | BD12: =IF(B12="","",IF(L12="","Отсутствуют предыдущие значения",AO12=O12)) | BE12: =IF(B12="","",IF(L12="","Отсутствуют предыдущие значения",#REF!=D12)) | BF12: =IF(B12="","",IF(L12="","Отсутствуют предыдущие значения",AW12=L12)) | BG12: =IF(B12="","",IF(M12="","Отсутствуют предыдущие значения",AX12=M12)) | BH12: =IF(B12="","",IF(AB12<>"","ОСПАРИВАНИЕ",IF(U12="","",U12))) | BI12: =IF(B12="","",#REF!) | BJ12: =IF(B12="","",#REF!) | BK12: =IF(B12="","",#REF!) | BL12: =IF(B12="","",#REF!) | BM12: =IF(B12="","",IF(L12="","Графика по ПКК","Графика на 01012020")) | BN12: =IF(B12="","",B12) | BO12: =IF(B12="","",AW12) | BP12: =IF(B12="","",AX12) | BQ12: =IF(B12="","",AY12) | BR12: =IF(B12="","",AZ12) | BS12: =IF(B12="","",BA12) | BT12: =IF(B12="","",IF(OR(Y12<>"",AB12<>"",BP12<0,AQ12<>""),"СТОПЛИСТ",IF(V12=21,"СТОПЛИСТ",IF(AND(BC12=TRUE,BE12=TRUE),"ПЕРЕСЧЕТ НЕ ТРЕБУЕТСЯ",IF(OR(BZ12="Отсутствует значения предыдущих расчетов",BZ12="Осуществлен пересчет"),"ГОТОВ","ПЕРЕСЧЕТ НЕ ТРЕБУЕТСЯ"))))) | BU12: =IF(B12="","",AP12) | BV12: =IF(B12="","",VLOOKUP(BU12,Справочник_ВРИ_Сегментов!$A:$D,4,)) | BW12: =IF(B12="","",AM12) | BX12: =IF(B12="","",VLOOKUP(BW12,Справочник_ВРИ_Сегментов!$B:$C,2,FALSE)) | BY12: =IF(B12="","",IF(OR(G12="",G12="-",G12="."),H12,G12)) | BZ12: =IF(B12="","",IF(M12="","Отсутствует значения предыдущих расчетов",IF(M12=AX12,"Значения КС не изменилось","Осуществлен пересчет"))) | CA12: =IF(B12="","-",M12-AX12) -> - | CB12: =IF(B12="","",IF(L12="","Новый","Измененный"))
AT13: =IF(B13="","",LEFT(P13,2)) | AU13: =IF(B13="","",IFERROR(VLOOKUP(C13,'Срв квартал'!$A:$D,4,FALSE),"")) | AV13: =IF(B13="","",VLOOKUP(AT13,'Срв мо'!$A:$D,4,FALSE)) | AW13: =IF(B13="","",IF(OR(C13="0000000",AU13=""),AV13,AU13)) | AX13: =IF(B13="","",ROUND(AW13*D13,2)) | AY13: =IF(B13="","",CONCATENATE("СТ16_",BI13,"_",BJ13,"_",BK13,"_",BL13,"_",BM13,"_",CB13)) | AZ13: =IF(B13="","",#REF!) | BA13: =IF(B13="","",AW13) | BB13: =IF(B13="","",B13) | BC13: =IF(B13="","",IF(MID(AM13,3,1)<>":","ОШИБКА В ФОРМАТЕ КОДА НП",IF(L13="","Отсутствуют предыдущие значения",AM13=Q13))) | BD13: =IF(B13="","",IF(L13="","Отсутствуют предыдущие значения",AO13=O13)) | BE13: =IF(B13="","",IF(L13="","Отсутствуют предыдущие значения",#REF!=D13)) | BF13: =IF(B13="","",IF(L13="","Отсутствуют предыдущие значения",AW13=L13)) | BG13: =IF(B13="","",IF(M13="","Отсутствуют предыдущие значения",AX13=M13)) | BH13: =IF(B13="","",IF(AB13<>"","ОСПАРИВАНИЕ",IF(U13="","",U13))) | BI13: =IF(B13="","",#REF!) | BJ13: =IF(B13="","",#REF!) | BK13: =IF(B13="","",#REF!) | BL13: =IF(B13="","",#REF!) | BM13: =IF(B13="","",IF(L13="","Графика по ПКК","Графика на 01012020")) | BN13: =IF(B13="","",B13) | BO13: =IF(B13="","",AW13) | BP13: =IF(B13="","",AX13) | BQ13: =IF(B13="","",AY13) | BR13: =IF(B13="","",AZ13) | BS13: =IF(B13="","",BA13) | BT13: =IF(B13="","",IF(OR(Y13<>"",AB13<>"",BP13<0,AQ13<>""),"СТОПЛИСТ",IF(V13=21,"СТОПЛИСТ",IF(AND(BC13=TRUE,BE13=TRUE),"ПЕРЕСЧЕТ НЕ ТРЕБУЕТСЯ",IF(OR(BZ13="Отсутствует значения предыдущих расчетов",BZ13="Осуществлен пересчет"),"ГОТОВ","ПЕРЕСЧЕТ НЕ ТРЕБУЕТСЯ"))))) | BU13: =IF(B13="","",AP13) | BV13: =IF(B13="","",VLOOKUP(BU13,Справочник_ВРИ_Сегментов!$A:$D,4,)) | BW13: =IF(B13="","",AM13) | BX13: =IF(B13="","",VLOOKUP(BW13,Справочник_ВРИ_Сегментов!$B:$C,2,FALSE)) | BY13: =IF(B13="","",IF(OR(G13="",G13="-",G13="."),H13,G13)) | BZ13: =IF(B13="","",IF(M13="","Отсутствует значения предыдущих расчетов",IF(M13=AX13,"Значения КС не изменилось","Осуществлен пересчет"))) | CA13: =IF(B13="","-",M13-AX13) -> - | CB13: =IF(B13="","",IF(L13="","Новый","Измененный"))
AT14: =IF(B14="","",LEFT(P14,2)) | AU14: =IF(B14="","",IFERROR(VLOOKUP(C14,'Срв квартал'!$A:$D,4,FALSE),"")) | AV14: =IF(B14="","",VLOOKUP(AT14,'Срв мо'!$A:$D,4,FALSE)) | AW14: =IF(B14="","",IF(OR(C14="0000000",AU14=""),AV14,AU14)) | AX14: =IF(B14="","",ROUND(AW14*D14,2)) | AY14: =IF(B14="","",CONCATENATE("СТ16_",BI14,"_",BJ14,"_",BK14,"_",BL14,"_",BM14,"_",CB14)) | AZ14: =IF(B14="","",#REF!) | BA14: =IF(B14="","",AW14) | BB14: =IF(B14="","",B14) | BC14: =IF(B14="","",IF(MID(AM14,3,1)<>":","ОШИБКА В ФОРМАТЕ КОДА НП",IF(L14="","Отсутствуют предыдущие значения",AM14=Q14))) | BD14: =IF(B14="","",IF(L14="","Отсутствуют предыдущие значения",AO14=O14)) | BE14: =IF(B14="","",IF(L14="","Отсутствуют предыдущие значения",#REF!=D14)) | BF14: =IF(B14="","",IF(L14="","Отсутствуют предыдущие значения",AW14=L14)) | BG14: =IF(B14="","",IF(M14="","Отсутствуют предыдущие значения",AX14=M14)) | BH14: =IF(B14="","",IF(AB14<>"","ОСПАРИВАНИЕ",IF(U14="","",U14))) | BI14: =IF(B14="","",#REF!) | BJ14: =IF(B14="","",#REF!) | BK14: =IF(B14="","",#REF!) | BL14: =IF(B14="","",#REF!) | BM14: =IF(B14="","",IF(L14="","Графика по ПКК","Графика на 01012020")) | BN14: =IF(B14="","",B14) | BO14: =IF(B14="","",AW14) | BP14: =IF(B14="","",AX14) | BQ14: =IF(B14="","",AY14) | BR14: =IF(B14="","",AZ14) | BS14: =IF(B14="","",BA14) | BT14: =IF(B14="","",IF(OR(Y14<>"",AB14<>"",BP14<0,AQ14<>""),"СТОПЛИСТ",IF(V14=21,"СТОПЛИСТ",IF(AND(BC14=TRUE,BE14=TRUE),"ПЕРЕСЧЕТ НЕ ТРЕБУЕТСЯ",IF(OR(BZ14="Отсутствует значения предыдущих расчетов",BZ14="Осуществлен пересчет"),"ГОТОВ","ПЕРЕСЧЕТ НЕ ТРЕБУЕТСЯ"))))) | BU14: =IF(B14="","",AP14) | BV14: =IF(B14="","",VLOOKUP(BU14,Справочник_ВРИ_Сегментов!$A:$D,4,)) | BW14: =IF(B14="","",AM14) | BX14: =IF(B14="","",VLOOKUP(BW14,Справочник_ВРИ_Сегментов!$B:$C,2,FALSE)) | BY14: =IF(B14="","",IF(OR(G14="",G14="-",G14="."),H14,G14)) | BZ14: =IF(B14="","",IF(M14="","Отсутствует значения предыдущих расчетов",IF(M14=AX14,"Значения КС не изменилось","Осуществлен пересчет"))) | CA14: =IF(B14="","-",M14-AX14) -> - | CB14: =IF(B14="","",IF(L14="","Новый","Измененный"))
AT15: =IF(B15="","",LEFT(P15,2)) | AU15: =IF(B15="","",IFERROR(VLOOKUP(C15,'Срв квартал'!$A:$D,4,FALSE),"")) | AV15: =IF(B15="","",VLOOKUP(AT15,'Срв мо'!$A:$D,4,FALSE)) | AW15: =IF(B15="","",IF(OR(C15="0000000",AU15=""),AV15,AU15)) | AX15: =IF(B15="","",ROUND(AW15*D15,2)) | AY15: =IF(B15="","",CONCATENATE("СТ16_",BI15,"_",BJ15,"_",BK15,"_",BL15,"_",BM15,"_",CB15)) | AZ15: =IF(B15="","",#REF!) | BA15: =IF(B15="","",AW15) | BB15: =IF(B15="","",B15) | BC15: =IF(B15="","",IF(MID(AM15,3,1)<>":","ОШИБКА В ФОРМАТЕ КОДА НП",IF(L15="","Отсутствуют предыдущие значения",AM15=Q15))) | BD15: =IF(B15="","",IF(L15="","Отсутствуют предыдущие значения",AO15=O15)) | BE15: =IF(B15="","",IF(L15="","Отсутствуют предыдущие значения",#REF!=D15)) | BF15: =IF(B15="","",IF(L15="","Отсутствуют предыдущие значения",AW15=L15)) | BG15: =IF(B15="","",IF(M15="","Отсутствуют предыдущие значения",AX15=M15)) | BH15: =IF(B15="","",IF(AB15<>"","ОСПАРИВАНИЕ",IF(U15="","",U15))) | BI15: =IF(B15="","",#REF!) | BJ15: =IF(B15="","",#REF!) | BK15: =IF(B15="","",#REF!) | BL15: =IF(B15="","",#REF!) | BM15: =IF(B15="","",IF(L15="","Графика по ПКК","Графика на 01012020")) | BN15: =IF(B15="","",B15) | BO15: =IF(B15="","",AW15) | BP15: =IF(B15="","",AX15) | BQ15: =IF(B15="","",AY15) | BR15: =IF(B15="","",AZ15) | BS15: =IF(B15="","",BA15) | BT15: =IF(B15="","",IF(OR(Y15<>"",AB15<>"",BP15<0,AQ15<>""),"СТОПЛИСТ",IF(V15=21,"СТОПЛИСТ",IF(AND(BC15=TRUE,BE15=TRUE),"ПЕРЕСЧЕТ НЕ ТРЕБУЕТСЯ",IF(OR(BZ15="Отсутствует значения предыдущих расчетов",BZ15="Осуществлен пересчет"),"ГОТОВ","ПЕРЕСЧЕТ НЕ ТРЕБУЕТСЯ"))))) | BU15: =IF(B15="","",AP15) | BV15: =IF(B15="","",VLOOKUP(BU15,Справочник_ВРИ_Сегментов!$A:$D,4,)) | BW15: =IF(B15="","",AM15) | BX15: =IF(B15="","",VLOOKUP(BW15,Справочник_ВРИ_Сегментов!$B:$C,2,FALSE)) | BY15: =IF(B15="","",IF(OR(G15="",G15="-",G15="."),H15,G15)) | BZ15: =IF(B15="","",IF(M15="","Отсутствует значения предыдущих расчетов",IF(M15=AX15,"Значения КС не изменилось","Осуществлен пересчет"))) | CA15: =IF(B15="","-",M15-AX15) -> - | CB15: =IF(B15="","",IF(L15="","Новый","Измененный"))
AT16: =IF(B16="","",LEFT(P16,2)) | AU16: =IF(B16="","",IFERROR(VLOOKUP(C16,'Срв квартал'!$A:$D,4,FALSE),"")) | AV16: =IF(B16="","",VLOOKUP(AT16,'Срв мо'!$A:$D,4,FALSE)) | AW16: =IF(B16="","",IF(OR(C16="0000000",AU16=""),AV16,AU16)) | AX16: =IF(B16="","",ROUND(AW16*D16,2)) | AY16: =IF(B16="","",CONCATENATE("СТ16_",BI16,"_",BJ16,"_",BK16,"_",BL16,"_",BM16,"_",CB16)) | AZ16: =IF(B16="","",#REF!) | BA16: =IF(B16="","",AW16) | BB16: =IF(B16="","",B16) | BC16: =IF(B16="","",IF(MID(AM16,3,1)<>":","ОШИБКА В ФОРМАТЕ КОДА НП",IF(L16="","Отсутствуют предыдущие значения",AM16=Q16))) | BD16: =IF(B16="","",IF(L16="","Отсутствуют предыдущие значения",AO16=O16)) | BE16: =IF(B16="","",IF(L16="","Отсутствуют предыдущие значения",#REF!=D16)) | BF16: =IF(B16="","",IF(L16="","Отсутствуют предыдущие значения",AW16=L16)) | BG16: =IF(B16="","",IF(M16="","Отсутствуют предыдущие значения",AX16=M16)) | BH16: =IF(B16="","",IF(AB16<>"","ОСПАРИВАНИЕ",IF(U16="","",U16))) | BI16: =IF(B16="","",#REF!) | BJ16: =IF(B16="","",#REF!) | BK16: =IF(B16="","",#REF!) | BL16: =IF(B16="","",#REF!) | BM16: =IF(B16="","",IF(L16="","Графика по ПКК","Графика на 01012020")) | BN16: =IF(B16="","",B16) | BO16: =IF(B16="","",AW16) | BP16: =IF(B16="","",AX16) | BQ16: =IF(B16="","",AY16) | BR16: =IF(B16="","",AZ16) | BS16: =IF(B16="","",BA16) | BT16: =IF(B16="","",IF(OR(Y16<>"",AB16<>"",BP16<0,AQ16<>""),"СТОПЛИСТ",IF(V16=21,"СТОПЛИСТ",IF(AND(BC16=TRUE,BE16=TRUE),"ПЕРЕСЧЕТ НЕ ТРЕБУЕТСЯ",IF(OR(BZ16="Отсутствует значения предыдущих расчетов",BZ16="Осуществлен пересчет"),"ГОТОВ","ПЕРЕСЧЕТ НЕ ТРЕБУЕТСЯ"))))) | BU16: =IF(B16="","",AP16) | BV16: =IF(B16="","",VLOOKUP(BU16,Справочник_ВРИ_Сегментов!$A:$D,4,)) | BW16: =IF(B16="","",AM16) | BX16: =IF(B16="","",VLOOKUP(BW16,Справочник_ВРИ_Сегментов!$B:$C,2,FALSE)) | BY16: =IF(B16="","",IF(OR(G16="",G16="-",G16="."),H16,G16)) | BZ16: =IF(B16="","",IF(M16="","Отсутствует значения предыдущих расчетов",IF(M16=AX16,"Значения КС не изменилось","Осуществлен пересчет"))) | CA16: =IF(B16="","-",M16-AX16) -> - | CB16: =IF(B16="","",IF(L16="","Новый","Измененный"))
AT17: =IF(B17="","",LEFT(P17,2)) | AU17: =IF(B17="","",IFERROR(VLOOKUP(C17,'Срв квартал'!$A:$D,4,FALSE),"")) | AV17: =IF(B17="","",VLOOKUP(AT17,'Срв мо'!$A:$D,4,FALSE)) | AW17: =IF(B17="","",IF(OR(C17="0000000",AU17=""),AV17,AU17)) | AX17: =IF(B17="","",ROUND(AW17*D17,2)) | AY17: =IF(B17="","",CONCATENATE("СТ16_",BI17,"_",BJ17,"_",BK17,"_",BL17,"_",BM17,"_",CB17)) | AZ17: =IF(B17="","",#REF!) | BA17: =IF(B17="","",AW17) | BB17: =IF(B17="","",B17) | BC17: =IF(B17="","",IF(MID(AM17,3,1)<>":","ОШИБКА В ФОРМАТЕ КОДА НП",IF(L17="","Отсутствуют предыдущие значения",AM17=Q17))) | BD17: =IF(B17="","",IF(L17="","Отсутствуют предыдущие значения",AO17=O17)) | BE17: =IF(B17="","",IF(L17="","Отсутствуют предыдущие значения",#REF!=D17)) | BF17: =IF(B17="","",IF(L17="","Отсутствуют предыдущие значения",AW17=L17)) | BG17: =IF(B17="","",IF(M17="","Отсутствуют предыдущие значения",AX17=M17)) | BH17: =IF(B17="","",IF(AB17<>"","ОСПАРИВАНИЕ",IF(U17="","",U17))) | BI17: =IF(B17="","",#REF!) | BJ17: =IF(B17="","",#REF!) | BK17: =IF(B17="","",#REF!) | BL17: =IF(B17="","",#REF!) | BM17: =IF(B17="","",IF(L17="","Графика по ПКК","Графика на 01012020")) | BN17: =IF(B17="","",B17) | BO17: =IF(B17="","",AW17) | BP17: =IF(B17="","",AX17) | BQ17: =IF(B17="","",AY17) | BR17: =IF(B17="","",AZ17) | BS17: =IF(B17="","",BA17) | BT17: =IF(B17="","",IF(OR(Y17<>"",AB17<>"",BP17<0,AQ17<>""),"СТОПЛИСТ",IF(V17=21,"СТОПЛИСТ",IF(AND(BC17=TRUE,BE17=TRUE),"ПЕРЕСЧЕТ НЕ ТРЕБУЕТСЯ",IF(OR(BZ17="Отсутствует значения предыдущих расчетов",BZ17="Осуществлен пересчет"),"ГОТОВ","ПЕРЕСЧЕТ НЕ ТРЕБУЕТСЯ"))))) | BU17: =IF(B17="","",AP17) | BV17: =IF(B17="","",VLOOKUP(BU17,Справочник_ВРИ_Сегментов!$A:$D,4,)) | BW17: =IF(B17="","",AM17) | BX17: =IF(B17="","",VLOOKUP(BW17,Справочник_ВРИ_Сегментов!$B:$C,2,FALSE)) | BY17: =IF(B17="","",IF(OR(G17="",G17="-",G17="."),H17,G17)) | BZ17: =IF(B17="","",IF(M17="","Отсутствует значения предыдущих расчетов",IF(M17=AX17,"Значения КС не изменилось","Осуществлен пересчет"))) | CA17: =IF(B17="","-",M17-AX17) -> - | CB17: =IF(B17="","",IF(L17="","Новый","Измененный"))
AT18: =IF(B18="","",LEFT(P18,2)) | AU18: =IF(B18="","",IFERROR(VLOOKUP(C18,'Срв квартал'!$A:$D,4,FALSE),"")) | AV18: =IF(B18="","",VLOOKUP(AT18,'Срв мо'!$A:$D,4,FALSE)) | AW18: =IF(B18="","",IF(OR(C18="0000000",AU18=""),AV18,AU18)) | AX18: =IF(B18="","",ROUND(AW18*D18,2)) | AY18: =IF(B18="","",CONCATENATE("СТ16_",BI18,"_",BJ18,"_",BK18,"_",BL18,"_",BM18,"_",CB18)) | AZ18: =IF(B18="","",#REF!) | BA18: =IF(B18="","",AW18) | BB18: =IF(B18="","",B18) | BC18: =IF(B18="","",IF(MID(AM18,3,1)<>":","ОШИБКА В ФОРМАТЕ КОДА НП",IF(L18="","Отсутствуют предыдущие значения",AM18=Q18))) | BD18: =IF(B18="","",IF(L18="","Отсутствуют предыдущие значения",AO18=O18)) | BE18: =IF(B18="","",IF(L18="","Отсутствуют предыдущие значения",#REF!=D18)) | BF18: =IF(B18="","",IF(L18="","Отсутствуют предыдущие значения",AW18=L18)) | BG18: =IF(B18="","",IF(M18="","Отсутствуют предыдущие значения",AX18=M18)) | BH18: =IF(B18="","",IF(AB18<>"","ОСПАРИВАНИЕ",IF(U18="","",U18))) | BI18: =IF(B18="","",#REF!) | BJ18: =IF(B18="","",#REF!) | BK18: =IF(B18="","",#REF!) | BL18: =IF(B18="","",#REF!) | BM18: =IF(B18="","",IF(L18="","Графика по ПКК","Графика на 01012020")) | BN18: =IF(B18="","",B18) | BO18: =IF(B18="","",AW18) | BP18: =IF(B18="","",AX18) | BQ18: =IF(B18="","",AY18) | BR18: =IF(B18="","",AZ18) | BS18: =IF(B18="","",BA18) | BT18: =IF(B18="","",IF(OR(Y18<>"",AB18<>"",BP18<0,AQ18<>""),"СТОПЛИСТ",IF(V18=21,"СТОПЛИСТ",IF(AND(BC18=TRUE,BE18=TRUE),"ПЕРЕСЧЕТ НЕ ТРЕБУЕТСЯ",IF(OR(BZ18="Отсутствует значения предыдущих расчетов",BZ18="Осуществлен пересчет"),"ГОТОВ","ПЕРЕСЧЕТ НЕ ТРЕБУЕТСЯ"))))) | BU18: =IF(B18="","",AP18) | BV18: =IF(B18="","",VLOOKUP(BU18,Справочник_ВРИ_Сегментов!$A:$D,4,)) | BW18: =IF(B18="","",AM18) | BX18: =IF(B18="","",VLOOKUP(BW18,Справочник_ВРИ_Сегментов!$B:$C,2,FALSE)) | BY18: =IF(B18="","",IF(OR(G18="",G18="-",G18="."),H18,G18)) | BZ18: =IF(B18="","",IF(M18="","Отсутствует значения предыдущих расчетов",IF(M18=AX18,"Значения КС не изменилось","Осуществлен пересчет"))) | CA18: =IF(B18="","-",M18-AX18) -> - | CB18: =IF(B18="","",IF(L18="","Новый","Измененный"))
... AT1999: =IF(B1999="","",LEFT(P1999,2)) | AU1999: =IF(B1999="","",IFERROR(VLOOKUP(C1999,'Срв квартал'!$A:$D,4,FALSE),"")) | AV1999: =IF(B1999="","",VLOOKUP(AT1999,'Срв мо'!$A:$D,4,FALSE)) | AW1999: =IF(B1999="","",IF(OR(C1999="0000000",AU1999=""),AV1999,AU1999)) | AX1999: =IF(B1999="","",ROUND(AW1999*D1999,2)) | AY1999: =IF(B1999="","",CONCATENATE("СТ16_",BI1999,"_",BJ1999,"_",BK1999,"_",BL1999,"_",BM1999,"_",CB1999)) | AZ1999: =IF(B1999="","",#REF!) | BA1999: =IF(B1999="","",AW1999) | BB1999: =IF(B1999="","",B1999) | BC1999: =IF(B1999="","",IF(MID(AM1999,3,1)<>":","ОШИБКА В ФОРМАТЕ КОДА НП",IF(L1999="","Отсутствуют предыдущие значения",AM1999=Q1999))) | BD1999: =IF(B1999="","",IF(L1999="","Отсутствуют предыдущие значения",AO1999=O1999)) | BE1999: =IF(B1999="","",IF(L1999="","Отсутствуют предыдущие значения",#REF!=D1999)) | BF1999: =IF(B1999="","",IF(L1999="","Отсутствуют предыдущие значения",AW1999=L1999)) | BG1999: =IF(B1999="","",IF(M1999="","Отсутствуют предыдущие значения",AX1999=M1999)) | BH1999: =IF(B1999="","",IF(AB1999<>"","ОСПАРИВАНИЕ",IF(U1999="","",U1999))) | BI1999: =IF(B1999="","",#REF!) | BJ1999: =IF(B1999="","",#REF!) | BK1999: =IF(B1999="","",#REF!) | BL1999: =IF(B1999="","",#REF!) | BM1999: =IF(B1999="","",IF(L1999="","Графика по ПКК","Графика на 01012020")) | BN1999: =IF(B1999="","",B1999) | BO1999: =IF(B1999="","",AW1999) | BP1999: =IF(B1999="","",AX1999) | BQ1999: =IF(B1999="","",AY1999) | BR1999: =IF(B1999="","",AZ1999) | BS1999: =IF(B1999="","",BA1999) | BT1999: =IF(B1999="","",IF(OR(Y1999<>"",AB1999<>"",BP1999<0,AQ1999<>""),"СТОПЛИСТ",IF(V1999=21,"СТОПЛИСТ",IF(AND(BC1999=TRUE,BE1999=TRUE),"ПЕРЕСЧЕТ НЕ ТРЕБУЕТСЯ",IF(OR(BZ1999="Отсутствует значения предыдущих расчетов",BZ1999="Осуществлен пересчет"),"ГОТОВ","ПЕРЕСЧЕТ НЕ ТРЕБУЕТСЯ"))))) | BU1999: =IF(B1999="","",AP1999) | BV1999: =IF(B1999="","",VLOOKUP(BU1999,Справочник_ВРИ_Сегментов!$A:$D,4,)) | BW1999: =IF(B1999="","",AM1999) | BX1999: =IF(B1999="","",VLOOKUP(BW1999,Справочник_ВРИ_Сегментов!$B:$C,2,FALSE)) | BY1999: =IF(B1999="","",IF(OR(G1999="",G1999="-",G1999="."),H1999,G1999)) | BZ1999: =IF(B1999="","",IF(M1999="","Отсутствует значения предыдущих расчетов",IF(M1999=AX1999,"Значения КС не изменилось","Осуществлен пересчет"))) | CA1999: =IF(B1999="","-",M1999-AX1999) -> - | CB1999: =IF(B1999="","",IF(L1999="","Новый","Измененный"))

Sheet реквизиты файла
A1: Файл | B1: Ф13
A2: Модель | B2: М10
A3: Дата | B3: 25.05.2021
A4: Ответственный | B4: Фомин
A5: код модели | B5: 8010

Sheet ГОТОВО
A1: CadastralNumber | B1: Specific_CadastralCost | C1: CadastralCost | D1: CadastralCostDesc | E1: id_group | F1: loc_Factor_831 | G1: Status_kc | H1: Segment | I1: loc_SgCode | J1: loc_VICode | K1: loc_GroupName | L1: Old_Utlbydoc | N1: =COUNTA(A:A) -> 1

Sheet ПЕРЕСЧЕТ НЕ ТРЕБУЕТСЯ
A1: CadastralNumber | B1: Status_kc | C1: Segment | D1: loc_SgCode | E1: loc_VICode | F1: loc_GroupName | G1: Old_Utlbydoc | I1: =COUNTA(A:A) -> 1

Sheet СТОПЛИСТ
A1: CadastralNumber | B1: Status_kc | D1: =COUNTA(A:A) -> 1

Sheet Инструкция
B1: Пошаговая инструкция расчета объектов в рамках статьи 16 для модели №10 сегмента 6 | C1: Ссылки на папки
A2: 1 | B2: Открываем рабочую область модели №10 сегмента 6 | C2: W:\ЦГКО\Отдел массовой оценки\19. 16 Статья\8. Земельные участки
A3: 2 | B3: В рабочей области стоят фильтры - новая модель 8010, статус расчета - не готов, сегмент - 6. Фильтры не трогаем
A4: 3 | B4: Выгружаем рабочую область через "Экспорт…", английские заголовки не нужны
A5: 4 | B5: Копируем объекты построчно без шапки, вставляем в данный файл на лист "объекты оценки". Должны быть заполнены ячейки от A3 до AR3 и ниже
A6: 5 | B6: Меняем формат вставленных данных в стилях ячеек на обычный
A7: 6 | B7: Все расчетные формулы работают автоматически, ячейки защищены и не редактируются (колонки AS - BA)
A8: 7 | B8: Анализируем колонки BB- BG, в случае, если значение не изменилось ячейка останется не закрашеной. Изменений в рамках расчета по 16 статье у объектов без графики быть не должно, за исключением смены модели, кода ВРИ, значения площади
A9: 8 | B9: Проверяем колонку "ОБЯЗАТЕЛЬНАЯ ПРОВЕРКА", в ней отражены наличия замечаний по объекту, обращений по статье 21, оспаривание
A10: 9 | B10: В случае наличия обращений по статье 21 или оспаривания ЗУ или особого контроля в колонке "статус расчета" будет указано СТОПЛИСТ | D10: уточню про стоплист
A11: 10 | B11: В случае наличия замечаний по объекту заходим в папку замечаний и проверяем корректно ли учтены данные при расчете по статье 16 | C11: W:\ЦГКО\Отдел по работе с обращениями\Замечания к ПОД-2020\ЗАМЕЧАНИЯ
A12: 11 | B12: Заполняем ячейки BH - BK ТОЛЬКО В ПЕРВОЙ СТРОКЕ. Пишем номер файла который указан в названии файла, номер модели - М10, дата - без точек, например 22012021 (формат ячейки с точками некорректно сцепляется), фамилия исполнителя, наличие графики - с графикой или без графики
A13: 12 | B13: Проверяем колонку "Статус расчета" и изменение КС. Если в колонке "Изменение, руб." значение меньше 1 руб. необходимо проверить расчеты
A14: 13 | B14: По колонке "статус расчета" BS разносим файлы по листам. Если "пересчет не требуется" то - кадастровый номер, ври, сегмент, статус расчета, если "стоплист" то только кадастровый номер и статус расчета, если "готов" то все данные на загрузку в базу. В шапке только английские заголовки!
A15: 14 | B15: ГОТОВО, отправляем на загрузку в базу
A16: 15 | B16: Важно: формулы растянуты на 2000 строк, если объектов оценки больше необходимо рассчитать их двумя файлами или растянуть ячейки
B18: Ячейки в строках 1-3 выделены цветом для удобства:
B19: Ячейки для заполнения
B20: Ячейки для анализа
B21: Ячейки не требующие редактирования

Sheet Справочник кодов НП
B1: Полное наименование МО | C1: Код МО | D1: Полное наименование МО
B2: Арамильский городской округ | C2: 01 | D2: Арамильский городской округ
B3: Артемовский городской округ | C3: 02 | D3: Артемовский городской округ
B4: Артинский городской округ | C4: 03 | D4: Артинский городской округ
B5: Асбестовский городской округ | C5: 04 | D5: Асбестовский городской округ
B6: Ачитский городской округ | C6: 05 | D6: Ачитский городской округ
B7: Байкаловский муниципальный район | C7: 06 | D7: Байкаловский муниципальный район
B8: Белоярский городской округ | C8: 07 | D8: Белоярский городской округ
B9: Березовский городской округ | C9: 08 | D9: Березовский городской округ
B10: Бисертский городской округ | C10: 09 | D10: Бисертский городской округ
B11: Верхнесалдинский городской округ | C11: 10 | D11: Верхнесалдинский городской округ
B12: Волчанский городской округ | C12: 11 | D12: Волчанский городской округ
... B74: Шалинский городской округ | C74: 73 | D74: Шалинский городской округ

Sheet Срв квартал
A1: CADASTRALBLOCK | B1: Sum-CADASTRALCOST | C1: Sum-AREA
A2: 66:01:0101001 | B2: 117477600 | C2: 1468470000 | D2: =ROUND(B2/C2,2) -> 0.08
A3: 66:01:0101002 | B3: 9319270.8 | C3: 93192708 | D3: =ROUND(B3/C3,2) -> 0.1
A4: 66:01:0201001 | B4: 8586664.1 | C4: 2583155 | D4: =ROUND(B4/C4,2) -> 3.32
A5: 66:01:0201002 | B5: 30695336 | C5: 657026 | D5: =ROUND(B5/C5,2) -> 46.72
A6: 66:01:0201003 | B6: 3182523.1 | C6: 23829 | D6: =ROUND(B6/C6,2) -> 133.56
A7: 66:01:0201004 | B7: 12215044 | C7: 81751.5 | D7: =ROUND(B7/C7,2) -> 149.42
A8: 66:01:0201005 | B8: 17462.83 | C8: 5132 | D8: =ROUND(B8/C8,2) -> 3.4
A9: 66:01:0201006 | B9: 3658000 | C9: 34500 | D9: =ROUND(B9/C9,2) -> 106.03
A10: 66:01:0201007 | B10: 3642444.6 | C10: 37693 | D10: =ROUND(B10/C10,2) -> 96.63
A11: 66:01:0201008 | B11: 2296772.9 | C11: 817486 | D11: =ROUND(B11/C11,2) -> 2.81
A12: 66:01:0201009 | B12: 635061.64 | C12: 9387 | D12: =ROUND(B12/C12,2) -> 67.65
A13: 66:01:0202001 | B13: 9094572.2 | C13: 72011.41 | D13: =ROUND(B13/C13,2) -> 126.29
... A15211: 66:73:0101006 | B15211: 15955199 | C15211: 96436 | D15211: =ROUND(B15211/C15211,2) -> 165.45

Sheet Срв мо
A1: KODMO | B1: Sum-CADASTRALCOST | C1: Sum-AREA
A2: 01 | B2: 1.0992053e+10 | C2: 16474386 | D2: =ROUND(B2/C2,2) -> 667.22
A3: 02 | B3: 1.4242436e+10 | C3: 1.8597321e+09 | D3: =ROUND(B3/C3,2) -> 7.66
A4: 03 | B4: 9.6519993e+09 | C4: 3.0977822e+09 | D4: =ROUND(B4/C4,2) -> 3.12
A5: 04 | B5: 2.8989855e+10 | C5: 8.3521917e+08 | D5: =ROUND(B5/C5,2) -> 34.71
A6: 05 | B6: 6.1688013e+09 | C6: 2.5815456e+09 | D6: =ROUND(B6/C6,2) -> 2.39
A7: 06 | B7: 8.5216626e+09 | C7: 2.6133052e+09 | D7: =ROUND(B7/C7,2) -> 3.26
A8: 07 | B8: 4.2072849e+10 | C8: 1.3610344e+09 | D8: =ROUND(B8/C8,2) -> 30.91
A9: 08 | B9: 6.2823652e+10 | C9: 1.0662232e+09 | D9: =ROUND(B9/C9,2) -> 58.92
A10: 09 | B10: 2.3063438e+09 | C10: 1.7151614e+08 | D10: =ROUND(B10/C10,2) -> 13.45
A11: 10 | B11: 1.4166667e+10 | C11: 1.6524453e+09 | D11: =ROUND(B11/C11,2) -> 8.57
A12: 11 | B12: 2.0785868e+09 | C12: 4.1584088e+08 | D12: =ROUND(B12/C12,2) -> 5
A13: 12 | B13: 3.1510315e+09 | C13: 1.6412676e+10 | D13: =ROUND(B13/C13,2) -> 0.19
... A74: 73 | B74: 5.5043863e+09 | C74: 5.207065e+09 | D74: =ROUND(B74/C74,2) -> 1.06

Sheet Справочник_ВРИ_Сегментов
A1: Segment | B1: loc_VICode | C1: loc_GroupName | D1: loc_SgCode
A2: Сегмент | B2: Код расчета вида использования | C2: Наименование вида использования | D2: Код сегмента | E2: Модель
A3: 1. СЕГМЕНТ "Сельскохозяйственное использование" | B3: 01:010 | C3: Растениеводство в целом. Включает коды расчета вида использования 01.020-01.060 | D3: 1.1 | E3: Модель № 1. Выращивание сельскохозяйственных культур
A4: 1. СЕГМЕНТ "Сельскохозяйственное использование" | B4: 01:020 | C4: Выращивание зерновых, бобовых, кормовых, технических, масличных, эфиромасличных и иных сельскохозяйственных культур | D4: 1.1 | E4: Модель № 1. Выращивание сельскохозяйственных культур
A5: 1. СЕГМЕНТ "Сельскохозяйственное использование" | B5: 01:030 | C5: Овощеводство в целом, связанное с производством картофеля, листовых, плодовых, луковичных и бахчевых сельскохозяйственных культур, в том числе с использованием теплиц | D5: 1.1 | E5: Модель № 1. Выращивание сельскохозяйственных культур
A6: 1. СЕГМЕНТ "Сельскохозяйственное использование" | B6: 01:031 | C6: Овощеводство в открытом грунте | D6: 1.1 | E6: Модель № 1. Выращивание сельскохозяйственных культур
A7: 1. СЕГМЕНТ "Сельскохозяйственное использование" | B7: 01:032 | C7: Овощеводство тепличное | D7: 1.1 | E7: Модель № 1. Выращивание сельскохозяйственных культур
A8: 1. СЕГМЕНТ "Сельскохозяйственное использование" | B8: 01:040 | C8: Выращивание тонизирующих, лекарственных, цветочных культур в целом | D8: 1.2 | E8: Модель №10. Метод УПКС
A9: 1. СЕГМЕНТ "Сельскохозяйственное использование" | B9: 01:041 | C9: Выращивание тонизирующих, лекарственных, цветочных культур. Травы | D9: 1.2 | E9: Модель №10. Метод УПКС
A10: 1. СЕГМЕНТ "Сельскохозяйственное использование" | B10: 01:042 | C10: Выращивание тонизирующих, лекарственных, цветочных культур. Кустарники | D10: 1.2 | E10: Модель №10. Метод УПКС
A11: 1. СЕГМЕНТ "Сельскохозяйственное использование" | B11: 01:050 | C11: Садоводство в целом - выращивание многолетних плодовых и ягодных культур, винограда и иных многолетних культур | D11: 1.1 | E11: Модель № 1. Выращивание сельскохозяйственных культур
A12: 1. СЕГМЕНТ "Сельскохозяйственное использование" | B12: 01:051 | C12: Садоводство плодовое | D12: 1.1 | E12: Модель № 1. Выращивание сельскохозяйственных культур
A13: 1. СЕГМЕНТ "Сельскохозяйственное использование" | B13: 01:052 | C13: Садоводство ягодно-кустарниковое | D13: 1.1 | E13: Модель № 1. Выращивание сельскохозяйственных культур
... A43: 1. СЕГМЕНТ "Сельскохозяйственное использование" | B43: 01:999 | C43: Иной вид использования в сегменте "Сельскохозяйственное использование" | D43: 1.1 | E43: Модель № 1. Выращивание сельскохозяйственных культур
A44: 2. СЕГМЕНТ "Жилая застройка (среднеэтажная и многоэтажная)" | B44: 02:000 | C44: Жилая застройка (среднеэтажная и многоэтажная без уточнения этажности) | D44: 2 | E44: Модель №2. Жилая застройка (среднеэтажная и многоэтажная)
A45: 2. СЕГМЕНТ "Жилая застройка (среднеэтажная и многоэтажная)" | B45: 02:050 | C45: Среднеэтажная жилая застройка в целом | D45: 2 | E45: Модель №2. Жилая застройка (среднеэтажная и многоэтажная)
A46: 2. СЕГМЕНТ "Жилая застройка (среднеэтажная и многоэтажная)" | B46: 02:051 | C46: Среднеэтажная жилая застройка. Размещение жилых домов, предназначенных для разделения на квартиры, каждая из которых пригодна для постоянного проживания (жилые дома высотой не выше восьми надземных этажей, разделенных на две и более квартиры), размещение встроенных в жилой дом подземных гаражей и автостоянок | D46: 2 | E46: Модель №2. Жилая застройка (среднеэтажная и многоэтажная)
A47: 2. СЕГМЕНТ "Жилая застройка (среднеэтажная и многоэтажная)" | B47: 02:060 | C47: Многоэтажная жилая застройка (высотная застройка) в целом | D47: 2 | E47: Модель №2. Жилая застройка (среднеэтажная и многоэтажная)
A48: 2. СЕГМЕНТ "Жилая застройка (среднеэтажная и многоэтажная)" | B48: 02:061 | C48: Многоэтажная жилая застройка. Размещение жилых домов, предназначенных для разделения на квартиры, каждая из которых пригодна для постоянного проживания (жилые дома высотой не выше восьми надземных этажей, разделенных на две и более квартиры), размещение встроенных в жилой дом подземных гаражей и автостоянок | D48: 2 | E48: Модель №2. Жилая застройка (среднеэтажная и многоэтажная)
A49: 2. СЕГМЕНТ "Жилая застройка (среднеэтажная и многоэтажная)" | B49: 02:999 | C49: Иной вид использования в сегменте "Жилая застройка (среднеэтажная и многоэтажная)" | D49: 2 | E49: Модель №2. Жилая застройка (среднеэтажная и многоэтажная)
A50: 3. СЕГМЕНТ "Общественное использование" | B50: 01:143 | C50: Научное обеспечение сельского хозяйства. Размещение зданий, сооружений, оборудования, необходимых для осуществления научного обеспечения сельского хозяйства, включая размещение коллекций генетических ресурсов растений | D50: 3 | E50: Модель №3. Общественное использование и Предпринимательство Екатеринбург Модель №4. Общественное использование и Предпринимательство Область
A51: 3. СЕГМЕНТ "Общественное использование" | B51: 03:010 | C51: Коммунальное обслуживание в целом | D51: 3 | E51: Модель №3. Общественное использование и Предпринимательство Екатеринбург Модель №4. Общественное использование и Предпринимательство Область
A52: 3. СЕГМЕНТ "Общественное использование" | B52: 03:013 | C52: Коммунальное обслуживание. Размещение ОКС в целях обеспечения физических и юридических лиц коммунальными услугами, в частности: зданий или помещений, предназначенных для приема физических и юридических лиц в связи с предоставлением им коммунальных услуг | D52: 3 | E52: Модель №3. Общественное использование и Предпринимательство Екатеринбург Модель №4. Общественное использование и Предпринимательство Область
A53: 3. СЕГМЕНТ "Общественное использование" | B53: 03:020 | C53: Социальное обслуживание в целом | D53: 3 | E53: Модель №3. Общественное использование и Предпринимательство Екатеринбург Модель №4. Общественное использование и Предпринимательство Область
A54: 3. СЕГМЕНТ "Общественное использование" | B54: 03:021 | C54: Социальное обслуживание. Размещение ОКС, предназначенных для оказания гражданам социальной помощи (службы занятости населения, дома престарелых, дома ребенка, детские дома, пункты питания малоимущих граждан, пункты ночлега для бездомных граждан, службы психологической и бесплатной юридической помощи, социальные, пенсионные и иные службы, в которых осуществляется прием граждан по вопросам оказания социальной помощи и назначения социальных или пенсионных выплат) | D54: 3 | E54: Модель №3. Общественное использование и Предпринимательство Екатеринбург Модель №4. Общественное использование и Предпринимательство Область
A55: 3. СЕГМЕНТ "Общественное использование" | B55: 03:022 | C55: Социальное обслуживание. Размещение ОКС для размещения отделений почты и телеграфа | D55: 3 | E55: Модель №3. Общественное использование и Предпринимательство Екатеринбург Модель №4. Общественное использование и Предпринимательство Область
... A271: 14. СЕГМЕНТ "Иное использование" | B271: 14:000 | C271: Иное использование | D271: 14 | E271: Модель №8. Затраты на межевание
