Workbook

Sheet Земельные участки
A1: Идентификатор | B1: Кадастровый номер | C1: Номер кадастрового квартала | D1: Площадь (ЦФ) | E1: Категория земель (ЦФ) | F1: Расстояние до административного центра МО (ЦФ) | G1: Вид разрешённого использования (ЦФ) | H1: Электроснабжение (ЦФ) | I1: Код МО (ЦФ) | J1: ЛЭП над участком (ЦФ) | K1: Удельный показатель кадастровой стоимости(руб/м2) | L1: Кадастровая стоимость (руб) | M1: Кадастровая стоимость описание вых | N1: Площадь в квадратных метрах | O1: Категория земель | P1: Расстояние до центра МО | Q1: Наличие электроснабжения | R1: Номер заявления | S1: Тип заявления | T1: Статус заявления | U1: Код Муниципального образования | V1: флажок | W1: Дата пакета | X1: Статус расчета | Y1: Дата комиссии | Z1: Решение комиссии | AA1: Флаг ВРИ по документу | AB1: Флаг площади | AC1: Флаг ВРИ старый спр | AD1: Флаг ВРИ новый спр | AE1: Флаг Категории ЗУ | AF1: Правило для ВРИ | AG1: Группа для XML | AH1: ВРИ по документу старое | AI1: Код расчета вида использования текущий (старый) | AJ1: ВРИ по документу новое | AK1: Код расчета вида использования новый | AL1: Новая модель | AM1: Особый контроль | AN1: Суд | AO1: Дата заседания | AP1: Повтор предыдущего расчета | BI1: loc_factor_804 | BK1: loc_factor_817 | BM1: loc_factor_812 | BN1: loc_factor_8121 | BO1: loc_factor_807 | BP1: loc_factor_8071 | BQ1: loc_factor_827 | BS1: loc_factor_829 | BU1: Specific_CadastralCost | BV1: CadastralCost | BW1: CadastralCostDesc | BX1: id_group | BY1: Status_kc | BZ1: loc_VICode | CA1: Segment | CB1: loc_SgCode | CC1: loc_GroupName | CD1: Old_Utlbydoc | CF1: Текущий диапазон УПКС от 4 руб. до 788 руб.
A2: ID | B2: CadastralNumber | C2: CadastralBlock | D2: loc_factor_807 | E2: loc_factor_817 | F2: loc_factor_812 | G2: loc_factor_825 | H2: loc_factor_804 | I2: loc_factor_830 | J2: loc_factor_829 | K2: Specific_CadastralCost | L2: CadastralCost | M2: CadastralCostDesc | N2: Area | O2: ParcelCategory | P2: DistanceToCMO | Q2: PresencePower | R2: Statement | S2: Type_Statement | T2: Status_Statement | U2: KodMO | V2: Sp_flag | W2: inputpacket_date | X2: Status_kc | Y2: Date_comm | Z2: Sol_comm | AA2: Flag_VRI | AB2: FlagParam | AC2: Flag_VRIoldspr | AD2: Flag_VRInewspr | AE2: Flag_Category | AF2: PraviloVRI | AG2: ID_Group | AH2: Old_Utlbydoc | AI2: loc_VICode | AJ2: UtilizationByDoc | AK2: VRICode_NEW | AL2: New_id_group | AM2: ControlSP | AN2: Court | AO2: Date_Court | AP2: Константа | AQ2: Электроснабжение | AR2: Поправка на электроснабжение | AS2: Категория земель | AT2: Поправка на категорию земель | AU2: Расстояние до центра МО | AV2: Поправка на расстояние до Нижнего Тагила | AW2: Поправка на площадь | AX2: Уторгование | AY2: Поправка на уторгование | AZ2: ЛЭП над участком | BA2: Поправка на ЛЭП над участком | BB2: УПС | BC2: Итоговая стоимость | BD2: id_group | BE2: Обязательная проверка | BG2: Кадастровый номер | BH2: Константа | BI2: Электроснабжение | BJ2: Поправка на электроснабжение | BK2: Категория земель | BL2: Поправка на категорию земель | BM2: Расстояние до центра МО | BN2: Поправка на расстояние до Нижнего Тагила | BO2: Площадь в квадратных метрах | BP2: Поправка на площадь | BQ2: Уторгование | BR2: Поправка на уторгование | BS2: ЛЭП над участком | BT2: Поправка на ЛЭП над участком | BU2: УПС | BV2: Итоговая стоимость | BW2: Идентификатор стоимости | BX2: Номер группы | BY2: Статус расчета | BZ2: ВРИ | CA2: Сегмент | CB2: Код сегмента | CC2: Расшифровка расчетной подгруппы | CD2: ВРИ по документу старое (формирование или обновление поля) | CE2: Сравнение расчета с предыдущим расчетом | CF2: Проверка отклонения УПКС от текущего диапазона и контроль значительного изменения КС | CG2: Код МО | CH2: Электроснабжение | CI2: Площадь | CJ2: Расстояние до административного центра МО | CK2: Изменение Кода расчета | CL2: ЛЭП над участком | CM2: Категория земель
A3: Parcels | B3: Parcels | C3: Parcels | D3: Parcels | E3: Parcels | F3: Parcels | G3: Parcels | H3: Parcels | I3: Parcels | J3: Parcels | K3: Parcels | L3: Parcels | M3: Parcels | N3: Parcels | O3: Parcels | P3: Parcels | Q3: Parcels | R3: Parcels | S3: Parcels | T3: Parcels | U3: Parcels | V3: Parcels | W3: Parcels | X3: Parcels | Y3: Parcels | Z3: Parcels | AA3: Parcels | AB3: Parcels | AC3: Parcels | AD3: Parcels | AE3: Parcels | AF3: Parcels | AG3: Parcels | AH3: Parcels | AI3: Parcels | AJ3: Parcels | AK3: Parcels | AL3: Parcels | AM3: Parcels | AN3: Parcels | AO3: Parcels | BE3: Вверно, если расходждение составляет 0,00 руб. Если расхождение составляет более 0,01 -ценовые факторы подобраны неверно. Требуется анализ | BF3: Участие объекта на комиссии, в заявлениях, в судах и прочее
O4: spr | AP4: =Лист1!$G$4 -> 603.1169 | AQ4: =H4 -> 0 | AR4: =VLOOKUP(AQ4,Лист1!$F$5:$G$6,2,0) -> #N/A | AS4: =E4 -> 0 | AT4: =VLOOKUP(AS4,Лист1!$F$7:$G$9,2,0) -> #N/A | AU4: =F4 -> 0 | AV4: =ROUND(EXP(0.77891374549679*(31.09574438-26.68403684*LN(IF(AU4<5.5,5.5,AU4))+9.02656927*LN(IF(AU4<5.5,5.5,AU4))^2-1.02030817*LN(IF(AU4<5.5,5.5,AU4))^3))/EXP(0.77891374549679*(31.09574438-26.68403684*LN(5.5)+9.02656927*LN(5.5)^2-1.02030817*LN(5.5)^3)),4) -> 1 | AW4: =ROUND(EXP(0.64000686795267*(9.03187218-0.61524404*LN(IF(D4<400,400,D4))))/EXP(0.64000686795267*(9.03187218-0.61524404*LN(1000))),4) -> 1.4345 | AX4: Наличие уторгования | AY4: =VLOOKUP(AX4,Лист1!$F$12:$G$13,2,0) -> 0.91 | AZ4: =J4 -> 0 | BA4: =VLOOKUP(AZ4,Лист1!$F$14:$G$15,2,0) -> #N/A | BB4: =ROUND(AP4*AR4*AT4*AV4*AW4*AY4*BA4,2) -> #N/A | BC4: =ROUND(BB4*D4,2) -> #N/A | BD4: =8016 -> 8016 | BE4: =IF(K4="","Новый объект",IF(AG4=AL4,BC4-L4,"Объект пришел из другой модели")) -> Новый объект | BF4: =IF(AM4="",IF(Y4<>"","ОСПАРИВАНИЕ",IF(AN4<>"","СУД",IF(R4="","",R4))),AM4) | BG4: =B4 -> 0 | BH4: =Лист1!$G$4 -> 603.1169 | BI4: =IF(K4="","Наличие электроснабжения",IF(H4="",IF(Q4="отсутствие","Отсутствие электроснабжения","Наличие электроснабжения"),H4)) -> Наличие электроснабжения | BJ4: =VLOOKUP(BI4,Лист1!$F$5:$G$6,2,0) -> 1 | BK4: =IF(O4="Земли населенных пунктов",Лист1!$F$7,Лист1!$F$8) -> Прочие | BL4: =VLOOKUP(BK4,Лист1!$F$7:$G$9,2,0) -> 0.9716 | BM4: =IF(F4="",IF(P4="",VLOOKUP(U4,Лист1!$G$17:$H$18,2,0),P4),F4) -> #N/A | BN4: =ROUND(EXP(0.77891374549679*(31.09574438-26.68403684*LN(IF(BM4<5.5,5.5,BM4))+9.02656927*LN(IF(BM4<5.5,5.5,BM4))^2-1.02030817*LN(IF(BM4<5.5,5.5,BM4))^3))/EXP(0.77891374549679*(31.09574438-26.68403684*LN(5.5)+9.02656927*LN(5.5)^2-1.02030817*LN(5.5)^3)),4) -> #N/A | BO4: =N4 -> 0 | BP4: =ROUND(EXP(0.64000686795267*(9.03187218-0.61524404*LN(IF(BO4<400,400,BO4))))/EXP(0.64000686795267*(9.03187218-0.61524404*LN(1000))),4) -> 1.4345 | BQ4: Наличие уторгования | BR4: =VLOOKUP(BQ4,Лист1!$F$12:$G$13,2,0) -> 0.91 | BS4: =IF(J4="","Отсутствие ЛЭП",IF(J4="Наличие ЛЭП","Наличие ЛЭП","Отсутствие ЛЭП")) -> Отсутствие ЛЭП | BT4: =VLOOKUP(BS4,Лист1!$F$14:$G$15,2,0) -> 1 | BU4: =ROUND(BH4*BJ4*BL4*BN4*BP4*BR4*BT4,2) -> #N/A | BV4: =ROUND(BU4*BO4,2) -> #N/A | BW4: СТ16_Ф1_М16_18052021_Бунаков | BX4: =8016 -> 8016 | BY4: =IF(OR(BV4=0,BV4<0),"ОТРИЦАТЕЛЬНАЯ СТОИМОСТЬ",IF(CE4=0,"Пересчет не требуется","Готов")) -> #N/A | BZ4: =AK4 -> 0 | CA4: 13. СЕГМЕНТ "Садоводство и огородничество, малоэтажная жилая застройка" | CB4: =13 -> 13 | CC4: =VLOOKUP(BZ4,'справочник ври'!$A$3:$B$271,2,0) -> #N/A | CD4: =AJ4 -> 0 | CE4: =IF(ISBLANK(K4),"Новый объект",IF(BX4=AG4,ABS(BV4-L4),"Объект из другой модели")) -> Новый объект | CF4: =IF(OR(CE4="Объект из другой модели",CE4="Новый объект"),IF(OR(BU4<4,BU4>788),"Отклонение УПКС","УПКС находится в допустимом интервале"),IF(CE4>1000000,"Внимение!Изменение более 1 млн","Изменение менее 1 млн")) -> #N/A | CG4: =IF(I4="","Новое значение",IF(I4=U4,"Осталось предыдущее значение ЦФ","ИЗМЕНЕНИЕ")) -> Новое значение | CH4: =IF(H4="","Новое значение",IF(H4=BI4,"Осталось предыдущее значение ЦФ","ИЗМЕНЕНИЕ")) -> Новое значение | CI4: =IF(K4="","Объект новый",IF(AB4="не готов","ИЗМЕНЕНИЕ","Осталось предыдущее значение ЦФ")) -> Объект новый | CJ4: =IF(F4="","Новое значение",IF(F4=BM4,"Осталось предыдущее значение ЦФ","ИЗМЕНЕНИЕ")) -> Новое значение | CK4: =IF(K4="","Объект новый",IF(AI4=AK4,"Осталось предыдущее значение ЦФ","ИЗМЕНЕНИЕ")) -> Объект новый | CL4: =IF(J4="","Новое значение",IF(J4=BS4,"Осталось предыдущее значение ЦФ","ИЗМЕНЕНИЕ")) -> Новое значение | CM4: =IF(E4="","Новое значение",IF(E4=BK4,"Осталось предыдущее значение ЦФ","ИЗМЕНЕНИЕ")) -> Новое значение
AP5: =Лист1!$G$4 -> 603.1169 | AQ5: =H5 -> 0 | AR5: =VLOOKUP(AQ5,Лист1!$F$5:$G$6,2,0) -> #N/A | AS5: =E5 -> 0 | AT5: =VLOOKUP(AS5,Лист1!$F$7:$G$9,2,0) -> #N/A | AU5: =F5 -> 0 | AV5: =ROUND(EXP(0.77891374549679*(31.09574438-26.68403684*LN(IF(AU5<5.5,5.5,AU5))+9.02656927*LN(IF(AU5<5.5,5.5,AU5))^2-1.02030817*LN(IF(AU5<5.5,5.5,AU5))^3))/EXP(0.77891374549679*(31.09574438-26.68403684*LN(5.5)+9.02656927*LN(5.5)^2-1.02030817*LN(5.5)^3)),4) -> 1 | AW5: =ROUND(EXP(0.64000686795267*(9.03187218-0.61524404*LN(IF(D5<400,400,D5))))/EXP(0.64000686795267*(9.03187218-0.61524404*LN(1000))),4) -> 1.4345 | AX5: Наличие уторгования | AY5: =VLOOKUP(AX5,Лист1!$F$12:$G$13,2,0) -> 0.91 | AZ5: =J5 -> 0 | BA5: =VLOOKUP(AZ5,Лист1!$F$14:$G$15,2,0) -> #N/A | BB5: =ROUND(AP5*AR5*AT5*AV5*AW5*AY5*BA5,2) -> #N/A | BC5: =ROUND(BB5*D5,2) -> #N/A | BD5: =8016 -> 8016 | BE5: =IF(K5="","Новый объект",IF(AG5=AL5,BC5-L5,"Объект пришел из другой модели")) -> Новый объект | BF5: =IF(AM5="",IF(Y5<>"","ОСПАРИВАНИЕ",IF(AN5<>"","СУД",IF(R5="","",R5))),AM5) | BG5: =B5 -> 0 | BH5: =Лист1!$G$4 -> 603.1169 | BI5: =IF(K5="","Наличие электроснабжения",IF(H5="",IF(Q5="отсутствие","Отсутствие электроснабжения","Наличие электроснабжения"),H5)) -> Наличие электроснабжения | BJ5: =VLOOKUP(BI5,Лист1!$F$5:$G$6,2,0) -> 1 | BK5: =IF(O5="Земли населенных пунктов",Лист1!$F$7,Лист1!$F$8) -> Прочие | BL5: =VLOOKUP(BK5,Лист1!$F$7:$G$9,2,0) -> 0.9716 | BM5: =IF(F5="",IF(P5="",VLOOKUP(U5,Лист1!$G$17:$H$18,2,0),P5),F5) -> #N/A | BN5: =ROUND(EXP(0.77891374549679*(31.09574438-26.68403684*LN(IF(BM5<5.5,5.5,BM5))+9.02656927*LN(IF(BM5<5.5,5.5,BM5))^2-1.02030817*LN(IF(BM5<5.5,5.5,BM5))^3))/EXP(0.77891374549679*(31.09574438-26.68403684*LN(5.5)+9.02656927*LN(5.5)^2-1.02030817*LN(5.5)^3)),4) -> #N/A | BO5: =N5 -> 0 | BP5: =ROUND(EXP(0.64000686795267*(9.03187218-0.61524404*LN(IF(BO5<400,400,BO5))))/EXP(0.64000686795267*(9.03187218-0.61524404*LN(1000))),4) -> 1.4345 | BQ5: Наличие уторгования | BR5: =VLOOKUP(BQ5,Лист1!$F$12:$G$13,2,0) -> 0.91 | BS5: =IF(J5="","Отсутствие ЛЭП",IF(J5="Наличие ЛЭП","Наличие ЛЭП","Отсутствие ЛЭП")) -> Отсутствие ЛЭП | BT5: =VLOOKUP(BS5,Лист1!$F$14:$G$15,2,0) -> 1 | BU5: =ROUND(BH5*BJ5*BL5*BN5*BP5*BR5*BT5,2) -> #N/A | BV5: =ROUND(BU5*BO5,2) -> #N/A | BW5: СТ16_Ф1_М16_18052021_Бунаков | BX5: =8016 -> 8016 | BY5: =IF(OR(BV5=0,BV5<0),"ОТРИЦАТЕЛЬНАЯ СТОИМОСТЬ",IF(CE5=0,"Пересчет не требуется","Готов")) -> #N/A | BZ5: =AK5 -> 0 | CA5: 13. СЕГМЕНТ "Садоводство и огородничество, малоэтажная жилая застройка" | CB5: =13 -> 13 | CC5: =VLOOKUP(BZ5,'справочник ври'!$A$3:$B$271,2,0) -> #N/A | CD5: =AJ5 -> 0 | CE5: =IF(ISBLANK(K5),"Новый объект",IF(BX5=AG5,ABS(BV5-L5),"Объект из другой модели")) -> Новый объект | CF5: =IF(OR(CE5="Объект из другой модели",CE5="Новый объект"),IF(OR(BU5<4,BU5>788),"Отклонение УПКС","УПКС находится в допустимом интервале"),IF(CE5>1000000,"Внимение!Изменение более 1 млн","Изменение менее 1 млн")) -> #N/A | CG5: =IF(I5="","Новое значение",IF(I5=U5,"Осталось предыдущее значение ЦФ","ИЗМЕНЕНИЕ")) -> Новое значение | CH5: =IF(H5="","Новое значение",IF(H5=BI5,"Осталось предыдущее значение ЦФ","ИЗМЕНЕНИЕ")) -> Новое значение | CI5: =IF(K5="","Объект новый",IF(AB5="не готов","ИЗМЕНЕНИЕ","Осталось предыдущее значение ЦФ")) -> Объект новый | CJ5: =IF(F5="","Новое значение",IF(F5=BM5,"Осталось предыдущее значение ЦФ","ИЗМЕНЕНИЕ")) -> Новое значение | CK5: =IF(K5="","Объект новый",IF(AI5=AK5,"Осталось предыдущее значение ЦФ","ИЗМЕНЕНИЕ")) -> Объект новый | CL5: =IF(J5="","Новое значение",IF(J5=BS5,"Осталось предыдущее значение ЦФ","ИЗМЕНЕНИЕ")) -> Новое значение | CM5: =IF(E5="","Новое значение",IF(E5=BK5,"Осталось предыдущее значение ЦФ","ИЗМЕНЕНИЕ")) -> Новое значение
A6: Select ID,Source_ID,CadastralNumber,DateCreated,CadastralBlock,Name,ObjectType,Area,AreaUnit,AreaInaccuracy,LocationinBounds,LocationPlaced,ElaborationReferenceMark,ElaborationDistance,ElaborationDirection,AddressOrLocation,FIAS,OKATO,KLADR,OKTMO,PostalCode,AddressRF,Region,DistrictName,DistrictType,CityName,CityType,UrbanDistrictName,UrbanDistrictType,SovietVillageName,SovietVillageType,LocalityName,LocalityType,PlanningElementName,PlanningElementType,StreetName,StreetType,Level1Type,Level1Value,Level2Type,Level2Value,Level3Type,Level3Value,ApartmentType,ApartmentValue,AddressOther,AddressNote,ParcelCategory,Utilization,UtilizationByDoc,UtilizationLandUse,UtilizationТхт,CostValue,CostUnit,CostDateValuation,CostDateEntering,CostDateApproval,CostDocNumber,CostDocDate,CostApplicationDate,CostRevisalStatementDate,CostApplicationLastDate,CostDocName,FacilityKN,FacilityKNPurpose,SurveyProjectNum,DecisionCodeDocument,DecisionName,DecisionSeries,DecisionNumber,DecisionDate,DecisionIssueOrgan,DecisionDesc,HiredHouseUse,HouseActBuilding,HouseActDevelopment,BuildingContractName,DevelopContractName,OwnerDecision,SupportContractName,CodeDocument,DocHiredHouseName,DocHiredHouseSeries,DocHiredHouseNumber,DocHiredHouseDate,DocHiredHouseIssueOrgan,DocHiredHouseDesc,LimitedRightNumber,CREATEOPERATORNAME,CREATEDATE,OPERATORNAME,MODIFYDATE,MI_STYLE,Specific_CadastralCost,CadastralCost,CadastralCostDesc,MO_Name,ID_Group,LocalityCode,locTypeUse2,loc_VICode,loc_GroupName,loc_VRICode,Sourse_loc_VICode,locTypeUse,inputpacket_id,loc_SgCode,VIP_Sp,Quant_Kontur,Quant_Point,Sum_Square,Sum_Perim,Proc_Diff_Square,Pr_Diff,Source_Sum_Square,SourceLocalityCode,Upload_Scroll,Date_KC,Segment,FlagLocalityCode,DistanceToRoad,DistanceToCMO,СМО,PresenceGas,SourcePresenceGas,PresenceHeating,SourcePresenceHeating,PresencePower,SourcePresencePower,PresenceWaterDisposal,SourcePresenceWaterDisposal,PresenceWaterSupply,SourcePresenceWaterSupply,DistanceToEKB,DistanceToRoadEKB,CCoordX,CCoordY,DistanceToMetro,DistanceToStationEKB,CostZone,DistanceToRRStation,costzone2,Textloc_VICode,act_sign,MaxFloor,Enc_squre,Enc_proc,Adm_rn_EKB,forestry,InfluenceZone_IGS,loc_factor_801,loc_factor_802,loc_factor_803,loc_factor_804,loc_factor_806,loc_factor_807,loc_factor_8071,loc_factor_809,loc_factor_8091,loc_factor_810,loc_factor_8101,loc_factor_811,loc_factor_8111,loc_factor_812,loc_factor_8121,loc_factor_813,loc_factor_814,loc_factor_815,loc_factor_816,loc_factor_8161,loc_factor_817,loc_factor_818,loc_factor_819,loc_factor_820,loc_factor_8201,loc_factor_821,loc_factor_822,loc_factor_823,loc_factor_8231,loc_factor_824,loc_factor_825,loc_factor_826,loc_factor_827,loc_factor_828,loc_factor_829,loc_factor_830,loc_factor_831,loc_factor_832,loc_factor_833,loc_factor_8331,loc_factor_835,loc_factor_836,loc_factor_837,loc_factor_838,Statement,Type_Statement,Status_Statement,DistanceToVZC,VRI_IGS,Cot_name,DistanceToZTB,PowerLines,loc_factor_839,KodMO,loc_factor_840,loc_factor_841,presence_entrance,loc_factor_8371,ControlSP,Sp_flag,loc_VRICode540,Status_kc,Date_comm,Sol_comm,Flag_LocalityCode,Flag_VRI,Flag_Location,FlagParam,Flag_VRIoldspr,Flag_VRInewspr,Flag_Category,OldLocalityCode,Flag_VRI_All,VRICode_NEW,PraviloVRI,New_id_group,New_loc_SgCode,New_Segment,Old_Utlbydoc,VRICode_OLD,PraviloVRI_old,Court,Date_Court,Sol_Court,(select (case count(*) when 0 then 0 else 1 end) from GEO.docboxes b where b.obj_id=PARCELS.ID and b.table_id=265) Attachment,(select sign(Count(*)) from PARCELS g where (not GEOM_OBJ is null) and (PARCELS.ID = g.ID)) GeometryExists,((select DatePacket from inputpacket where id=Parcels.inputpacket_id) ) [inputpacket_date] From PARCELS where status_kc='НЕ ГОТОВ' AND New_id_group=8016 | AP6: =Лист1!$G$4 -> 603.1169 | AQ6: =H6 -> 0 | AR6: =VLOOKUP(AQ6,Лист1!$F$5:$G$6,2,0) -> #N/A | AS6: =E6 -> 0 | AT6: =VLOOKUP(AS6,Лист1!$F$7:$G$9,2,0) -> #N/A | AU6: =F6 -> 0 | AV6: =ROUND(EXP(0.77891374549679*(31.09574438-26.68403684*LN(IF(AU6<5.5,5.5,AU6))+9.02656927*LN(IF(AU6<5.5,5.5,AU6))^2-1.02030817*LN(IF(AU6<5.5,5.5,AU6))^3))/EXP(0.77891374549679*(31.09574438-26.68403684*LN(5.5)+9.02656927*LN(5.5)^2-1.02030817*LN(5.5)^3)),4) -> 1 | AW6: =ROUND(EXP(0.64000686795267*(9.03187218-0.61524404*LN(IF(D6<400,400,D6))))/EXP(0.64000686795267*(9.03187218-0.61524404*LN(1000))),4) -> 1.4345 | AX6: Наличие уторгования | AY6: =VLOOKUP(AX6,Лист1!$F$12:$G$13,2,0) -> 0.91 | AZ6: =J6 -> 0 | BA6: =VLOOKUP(AZ6,Лист1!$F$14:$G$15,2,0) -> #N/A | BB6: =ROUND(AP6*AR6*AT6*AV6*AW6*AY6*BA6,2) -> #N/A | BC6: =ROUND(BB6*D6,2) -> #N/A | BD6: =8016 -> 8016 | BE6: =IF(K6="","Новый объект",IF(AG6=AL6,BC6-L6,"Объект пришел из другой модели")) -> Новый объект | BF6: =IF(AM6="",IF(Y6<>"","ОСПАРИВАНИЕ",IF(AN6<>"","СУД",IF(R6="","",R6))),AM6) | BG6: =B6 -> 0 | BH6: =Лист1!$G$4 -> 603.1169 | BI6: =IF(K6="","Наличие электроснабжения",IF(H6="",IF(Q6="отсутствие","Отсутствие электроснабжения","Наличие электроснабжения"),H6)) -> Наличие электроснабжения | BJ6: =VLOOKUP(BI6,Лист1!$F$5:$G$6,2,0) -> 1 | BK6: =IF(O6="Земли населенных пунктов",Лист1!$F$7,Лист1!$F$8) -> Прочие | BL6: =VLOOKUP(BK6,Лист1!$F$7:$G$9,2,0) -> 0.9716 | BM6: =IF(F6="",IF(P6="",VLOOKUP(U6,Лист1!$G$17:$H$18,2,0),P6),F6) -> #N/A | BN6: =ROUND(EXP(0.77891374549679*(31.09574438-26.68403684*LN(IF(BM6<5.5,5.5,BM6))+9.02656927*LN(IF(BM6<5.5,5.5,BM6))^2-1.02030817*LN(IF(BM6<5.5,5.5,BM6))^3))/EXP(0.77891374549679*(31.09574438-26.68403684*LN(5.5)+9.02656927*LN(5.5)^2-1.02030817*LN(5.5)^3)),4) -> #N/A | BO6: =N6 -> 0 | BP6: =ROUND(EXP(0.64000686795267*(9.03187218-0.61524404*LN(IF(BO6<400,400,BO6))))/EXP(0.64000686795267*(9.03187218-0.61524404*LN(1000))),4) -> 1.4345 | BQ6: Наличие уторгования | BR6: =VLOOKUP(BQ6,Лист1!$F$12:$G$13,2,0) -> 0.91 | BS6: =IF(J6="","Отсутствие ЛЭП",IF(J6="Наличие ЛЭП","Наличие ЛЭП","Отсутствие ЛЭП")) -> Отсутствие ЛЭП | BT6: =VLOOKUP(BS6,Лист1!$F$14:$G$15,2,0) -> 1 | BU6: =ROUND(BH6*BJ6*BL6*BN6*BP6*BR6*BT6,2) -> #N/A | BV6: =ROUND(BU6*BO6,2) -> #N/A | BW6: СТ16_Ф1_М16_18052021_Бунаков | BX6: =8016 -> 8016 | BY6: =IF(OR(BV6=0,BV6<0),"ОТРИЦАТЕЛЬНАЯ СТОИМОСТЬ",IF(CE6=0,"Пересчет не требуется","Готов")) -> #N/A | BZ6: =AK6 -> 0 | CA6: 13. СЕГМЕНТ "Садоводство и огородничество, малоэтажная жилая застройка" | CB6: =13 -> 13 | CC6: =VLOOKUP(BZ6,'справочник ври'!$A$3:$B$271,2,0) -> #N/A | CD6: =AJ6 -> 0 | CE6: =IF(ISBLANK(K6),"Новый объект",IF(BX6=AG6,ABS(BV6-L6),"Объект из другой модели")) -> Новый объект | CF6: =IF(OR(CE6="Объект из другой модели",CE6="Новый объект"),IF(OR(BU6<4,BU6>788),"Отклонение УПКС","УПКС находится в допустимом интервале"),IF(CE6>1000000,"Внимение!Изменение более 1 млн","Изменение менее 1 млн")) -> #N/A | CG6: =IF(I6="","Новое значение",IF(I6=U6,"Осталось предыдущее значение ЦФ","ИЗМЕНЕНИЕ")) -> Новое значение | CH6: =IF(H6="","Новое значение",IF(H6=BI6,"Осталось предыдущее значение ЦФ","ИЗМЕНЕНИЕ")) -> Новое значение | CI6: =IF(K6="","Объект новый",IF(AB6="не готов","ИЗМЕНЕНИЕ","Осталось предыдущее значение ЦФ")) -> Объект новый | CJ6: =IF(F6="","Новое значение",IF(F6=BM6,"Осталось предыдущее значение ЦФ","ИЗМЕНЕНИЕ")) -> Новое значение | CK6: =IF(K6="","Объект новый",IF(AI6=AK6,"Осталось предыдущее значение ЦФ","ИЗМЕНЕНИЕ")) -> Объект новый | CL6: =IF(J6="","Новое значение",IF(J6=BS6,"Осталось предыдущее значение ЦФ","ИЗМЕНЕНИЕ")) -> Новое значение | CM6: =IF(E6="","Новое значение",IF(E6=BK6,"Осталось предыдущее значение ЦФ","ИЗМЕНЕНИЕ")) -> Новое значение

Sheet справочник ври
A1: loc_VICode | B1: loc_GroupName
A2: Код расчета вида использования | B2: Наименование вида использования
A3: 01:010 | B3: Растениеводство в целом. Включает коды расчета вида использования 01.020-01.060
A4: 01:020 | B4: Выращивание зерновых, бобовых, кормовых, технических, масличных, эфиромасличных и иных сельскохозяйственных культур
A5: 01:030 | B5: Овощеводство в целом, связанное с производством картофеля, листовых, плодовых, луковичных и бахчевых сельскохозяйственных культур, в том числе с использованием теплиц
A6: 01:031 | B6: Овощеводство в открытом грунте
A7: 01:032 | B7: Овощеводство тепличное
A8: 01:040 | B8: Выращивание тонизирующих, лекарственных, цветочных культур в целом
A9: 01:041 | B9: Выращивание тонизирующих, лекарственных, цветочных культур. Травы
A10: 01:042 | B10: Выращивание тонизирующих, лекарственных, цветочных культур. Кустарники
A11: 01:050 | B11: Садоводство в целом - выращивание многолетних плодовых и ягодных культур, винограда и иных многолетних культур
A12: 01:051 | B12: Садоводство плодовое
... A271: 14:000 | B271: Иное использование

Sheet ГОТОВ
A1: CadastralNumber | C1: loc_factor_804 | E1: loc_factor_817 | G1: loc_factor_812 | H1: loc_factor_8121 | I1: loc_factor_807 | J1: loc_factor_8071 | K1: loc_factor_827 | M1: loc_factor_829 | O1: Specific_CadastralCost | P1: CadastralCost | Q1: CadastralCostDesc | R1: id_group | S1: Status_kc | T1: loc_VICode | U1: Segment | V1: loc_SgCode | W1: loc_GroupName | X1: Old_Utlbydoc

Sheet ПЕРЕСЧЕТ НЕ ТРЕБУЕТСЯ
A1: CadastralNumber | B1: Status_kc | C1: loc_VICode | D1: Segment | E1: loc_SgCode | F1: loc_GroupName | G1: Old_Utlbydoc
A2: Кадастровый номер | B2: Статус расчета | C2: ВРИ | D2: Сегмент | E2: Код сегмента | F2: Расшифровка расчетной подгруппы | G2: ВРИ по документу старое(обновление поля)

Sheet СТОПЛИСТ
A1: CadastralNumber | B1: ControlSP

Sheet Лист1
A1: Модель №16. Садоводческое, огородническое и дачное использование, малоэтажная жилая застройка. НТ_Сады
A2: Код МО (13и14). В других моделях это ценовой фактор | B2: Специально заводить в БД такое полев БД не нужно (Будем определять как два первых знака от кода НП)
A3: Фактор | B3: Обозначение фактора | C3: Номер модели | D3: Наименование поля БД | E3: Значение поля БД | F3: Градация (не хранится в БД как отдельное поле) | G3: Значение поправки | I3: Сравнение со старым расчетом | X3: y=574,28*V1*V2*V3*V4*V5 Где: y – удельный показатель; V1 – Поправочный коэффициент фактора "Наличие электричества"; V2 – Поправочный коэффициент фактора "Категория земель" V3 – Поправочный коэффициент фактора «Расстояние до центра г. Нижний Тагил». V4– Поправочный коэффициент фактора «Общая площадь»; V5 – Поправочный коэффициент фактора «Уторгование». V6 – Поправочный коэффициент фактора "ЛЭП над участком";
A4: Константа | B4: С0 | C4: 8016 | D4: НЕТ | E4: НЕТ | F4: Константа | G4: 603.1169 | I4: 574.28
A5: Электроснабжение | B5: V1 | C5: 8016 | D5: Электроснабжение | E5: наличие | F5: Наличие электроснабжения | G5: 1 | I5: 1
E6: отсутствие | F6: Отсутствие электроснабжения | G6: 0.7064 | I6: 0.7024
A7: Категория земель | B7: V2 | C7: 8016 | D7: Категория | E7: Земли населенных пунктов | F7: ЗНП | G7: 1 | I7: 1
E8: Земли сельскохозяйственного назначения | F8: Прочие | G8: 0.9716 | I8: 0.9579
E9: Иные категории, пусто
A10: Расстояние до Нижнего Тагила | B10: V3 | C10: 8016 | D10: Расстояние до центра МО | E10: 5.5 | F10: Количественный | G10: 5.5 | I10: =ROUND(EXP(0.75488519435606*(31.10548841-26.76360101*LN(IF(G10<5.5,5.5,G10))+9.08405661*LN(IF(G10<5.5,5.5,G10))^2-1.03071008*LN(IF(G10<5.5,5.5,G10))^3))/EXP(0.75488519435606*(31.10548841-26.76360101*LN(5.5)+9.08405661*LN(5.5)^2-1.03071008*LN(5.5)^3)),4) -> 1 | J10: Если в графЕ РАССТОЯНИЕ ПУСТО,ТО ДЛЯ 13 мо-11КМ,ДЛЯ 14мо-19
A11: Площадь | B11: V4 | C11: 8016 | D11: Площадь | E11: 1000 | F11: Количественный | G11: 1000 | I11: =ROUND(EXP(0.64404038005242*(13.2398016-4.3779567*LN(LN(IF(G11<400,400,G11)))))/EXP(0.64404038005242*(13.2398016-4.3779567*LN(LN(1000)))),4) -> 1
A12: Уторгование | B12: V5 | C12: 8016 | D12: НЕТ | E12: НЕТ | F12: Наличие уторгования | G12: 0.91 | I12: 0.91
E13: НЕТ | F13: Отсутствие уторгования | G13: 1 | I13: 1
A14: ЛЭП над участком | B14: V6 | C14: 8016 | D14: НЕТ | E14: НЕТ | F14: Наличие ЛЭП | G14: 0.7024 | I14: 0.7024
F15: Отсутствие ЛЭП | G15: 1 | I15: 1
G16: мо
G17: 13 | H17: 11
G18: 14 | H18: 19
