Workbook

Sheet расчеты
A1: Идентификатор | B1: Кадастровый номер | C1: Номер кадастрового квартала | D1: Площадь (ЦФ) | E1: Газоснабжение (ЦФ) | F1: Электроснабжение (ЦФ) | G1: Водоотведение (ЦФ) | H1: Теплоснабжение (ЦФ) | I1: Рыночная стоимость квартиры(ЦФ) | J1: Коэффициент плотности(ЦФ) | K1: Коэффициент типовых характеристик(ЦФ) | L1: Код населённого пункта | M1: Старый код НП | N1: Удельный показатель кадастровой стоимости(руб/м2) | O1: Кадастровая стоимость (руб) | P1: Кадастровая стоимость описание вых | Q1: Площадь в квадратных метрах | R1: Категория земель | S1: Наличие газоснабжения | T1: Наличие отопления | U1: Наличие электроснабжения | V1: Наличие водоотведения | W1: Номер заявления | X1: Тип заявления | Y1: Статус заявления | Z1: флажок | AA1: Дата пакета | AB1: Статус расчета | AC1: Дата комиссии | AD1: Решение комиссии | AE1: Флаг кода НП | AF1: Флаг ВРИ по документу | AG1: Флаг площади | AH1: Флаг ВРИ старый спр | AI1: Флаг ВРИ новый спр | AJ1: Флаг Категории ЗУ | AK1: Правило | AL1: Группа для XML | AM1: Особый контроль | AN1: Новоя модель | AO1: ВРИ по документу новое | AP1: Код расчета вида использования новый | AQ1: Код расчета вида использования текущий | AR1: ВРИ по документу старое | AS1: Суд | AT1: Дата заседания Суда | AU1: Повтор расчета по данным предудыщего расчета | BG1: Обязательная проверка | BK1: Расчет стоимости в рамках 16 статьи и факторы для загрузки в базу | CF1: Обновляем или формируем поле "Старое ВРИ" | CG1: Анализ | CQ1: 13. СЕГМЕНТ "Садоводство и огородничество, малоэтажная жилая застройка" | CR1: 2. СЕГМЕНТ "Жилая застройка (среднеэтажная и многоэтажная)"
A2: ID | B2: CadastralNumber | C2: CadastralBlock | D2: loc_factor_807 | E2: loc_factor_822 | F2: loc_factor_804 | G2: loc_factor_803 | H2: loc_factor_802 | I2: loc_factor_838 | J2: loc_factor_835 | K2: loc_factor_836 | L2: LocalityCode | M2: OldLocalityCode | N2: Specific_CadastralCost | O2: CadastralCost | P2: CadastralCostDesc | Q2: Area | R2: ParcelCategory | S2: PresenceGas | T2: PresenceHeating | U2: PresencePower | V2: PresenceWaterDisposal | W2: Statement | X2: Type_Statement | Y2: Status_Statement | Z2: Sp_flag | AA2: inputpacket_date | AB2: Status_kc | AC2: Date_comm | AD2: Sol_comm | AE2: FlagLocalityCode | AF2: Flag_VRI | AG2: FlagParam | AH2: Flag_VRIoldspr | AI2: Flag_VRInewspr | AJ2: Flag_Category | AK2: PraviloVRI | AL2: ID_Group | AM2: ControlSP | AN2: New_id_group | AO2: UtilizationByDoc | AP2: VRICode_NEW | AQ2: loc_VICode | AR2: Old_Utlbydoc | AS2: Court | AT2: Date_Court | BI2: CadastralNumber | BJ2: loc_factor_807 | BL2: loc_Factor_838 | BM2: loc_Factor_836 | BP2: loc_Factor_835 | BQ2: loc_Factor_802 | BS2: loc_Factor_804 | BU2: loc_Factor_803 | BW2: Specific_CadastralCost | BX2: CadastralCost | BY2: id_group | BZ2: CadastralCostDesc | CA2: Status_kc | CB2: loc_VICode | CC2: Segment | CD2: loc_SgCode | CE2: loc_GroupName | CF2: Old_Utlbydoc | CI2: Контроль текущего диапазона УПКС от 866 руб. до 17 260 руб. за 1 кв. м и значительного изменения стоимости (50 млн. руб) | CM2: Площадь не является ценообразующим фактором,но при ее изменении объект может попасть на перегруппировку | CQ2: 13 | CR2: 2
A3: Parcels | B3: Parcels | C3: Parcels | D3: Parcels | E3: Parcels | F3: Parcels | G3: Parcels | H3: Parcels | I3: Parcels | J3: Parcels | K3: Parcels | L3: Parcels | M3: Parcels | N3: Parcels | O3: Parcels | P3: Parcels | Q3: Parcels | R3: Parcels | S3: Parcels | T3: Parcels | U3: Parcels | V3: Parcels | W3: Parcels | X3: Parcels | Y3: Parcels | Z3: Parcels | AA3: Parcels | AB3: Parcels | AC3: Parcels | AD3: Parcels | AE3: Parcels | AF3: Parcels | AG3: Parcels | AH3: Parcels | AI3: Parcels | AJ3: Parcels | AK3: Parcels | AL3: Parcels | AM3: Parcels | AN3: Parcels | AO3: Parcels | AP3: Parcels | AQ3: Parcels | AR3: Parcels | AS3: Parcels | AT3: Parcels | AU3: УПКС рыночной стоимости квартиры | AV3: Коэффициент типовых характеристик | AW3: Поправка на Коэффициент типовых характеристик | AX3: Коэффициент плотности | AY3: Теплоснабжение | AZ3: Теплоснабжение | BA3: Электроснабжение | BB3: Электроснабжение | BC3: Водоотведение | BD3: Водоотведение | BE3: УПКС, руб. за 1 кв. М | BF3: КС, рублей | BG3: Верно, если расходждение менее 1,00 руб. Если расхождение более 1,00 -ценовые факторы подобраны неверно. Требуется анализ | BH3: Участие объекта на комиссии, в заявлениях, в судах и прочее | BI3: Кадастровый номер | BJ3: Площадь | BK3: Район,исходя из которого считается УПКС | BL3: УПКС рыночной стоимости квартиры | BM3: Коэффициент типовых характеристик | BN3: Поправка на Коэффициент типовых характеристик | BO3: Этажность в расчет (если ЦФ "Коэ-т плотности" не сформирован ранее) | BP3: Коэффициент плотности | BQ3: Теплоснабжение | BR3: Теплоснабжение | BS3: Электроснабжение | BT3: Электроснабжение | BU3: Водоотведение | BV3: Водоотведение | BW3: УПКС, руб. за 1 кв. М | BX3: КС, рублей | CA3: Статус расчета | CB3: ВРИ | CC3: Сегмент | CD3: Код сегмента | CE3: Расшифровка расчетной подгруппы | CF3: Ври по документу старое | CG3: Сравнение текущей стоимости от предыдущего расчета | CH3: Сравнение УПКС от предыдущего расчета | CI3: Проверка отклонения УПКС от текущего диапазона и контроль значительного изменения КС | CJ3: УПКС рыночной стоимости квартиры | CK3: Электроснабжение | CL3: Теплоснабжение | CM3: Площадь | CN3: Коэффициент плотности | CO3: Коэффициент типовых характеристик | CP3: Вид разрешенного использования | CQ3: Переход от РС квартиры к району (ВНИМАНИЕ, есть совпадения по РС квартиры!) | CR3: Проверка района
AU4: =I4 -> 0 | AV4: =K4 -> 0 | AW4: =VLOOKUP(AV4,коэф.модели!$F$6:$G$11,2,0) -> #N/A | AX4: =J4 -> 0 | AY4: =H4 -> 0 | AZ4: =IF(AY4="","ОШИБКА",VLOOKUP(AY4,коэф.модели!$F$12:$G$17,2,0)) -> #N/A | BA4: =F4 -> 0 | BB4: =IF(BA4="","ОШИБКА",VLOOKUP(BA4,коэф.модели!$F$12:$G$17,2,0)) -> #N/A | BC4: =G4 -> 0 | BD4: =IF(BC4="","ОШИБКА",VLOOKUP(BC4,коэф.модели!$F$12:$G$17,2,0)) -> #N/A | BE4: =ROUND(PRODUCT(AU4,AW4,AX4,AZ4,BD4,BB4),2) -> #N/A | BF4: =MROUND(BE4*D4,2) -> #N/A | BG4: =IF(N4="","Новый объект",IF(AN4=AL4,BF4-O4,"Объект пришел из другой модели")) -> Новый объект | BH4: =IF(AM4="",IF(AC4<>"","ОСПАРИВАНИЕ",IF(AS4<>"","СУД",IF(W4="","",W4))),AM4) | BI4: =B4 -> 0 | BJ4: =Q4 -> 0 | BK4: =IFERROR(IF(AP4="02:060",VLOOKUP(C4,'КК и удельник'!$A$3:$E$6521,2,0),IF(расчеты!AP4="02:050",VLOOKUP(расчеты!C4,'КК и удельник'!$A$3:$E$6521,2,0),IF(расчеты!AP4="02:014",VLOOKUP(расчеты!C4,'КК и удельник'!$A$3:$E$6521,2,0)))),IF(AP4="02:060",IF(M4="",VLOOKUP(L4,'КК и удельник'!$AG$3:$AK$1928,2,0),VLOOKUP(M4,'КК и удельник'!$AG$3:$AK$1928,2,0)),IF(расчеты!AP4="02:050",IF(M4="",VLOOKUP(расчеты!L4,'КК и удельник'!$AG$3:$AK$1928,2,0),VLOOKUP(расчеты!M4,'КК и удельник'!$AG$3:$AK$1928,2,0)),IF(расчеты!AP4="02:014",IF(M4="",VLOOKUP(расчеты!L4,'КК и удельник'!$AG$3:$AK$1928,2,0),VLOOKUP(расчеты!M4,'КК и удельник'!$AG$3:$AK$1928,2,0)),"ОШИБКА")))) -> FALSE | BL4: =IF(AQ4=AP4,I4,IFERROR(IF(AP4="02:060",VLOOKUP(C4,'КК и удельник'!$A$3:$E$6521,4,0),IF(расчеты!AP4="02:050",VLOOKUP(расчеты!C4,'КК и удельник'!$A$3:$E$6521,3,0),IF(расчеты!AP4="02:014",VLOOKUP(расчеты!C4,'КК и удельник'!$A$3:$E$6521,5,0)))),IF(AP4="02:060",IF(M4="",VLOOKUP(L4,'КК и удельник'!$AG$3:$AK$1928,4,0),VLOOKUP(M4,'КК и удельник'!$AG$3:$AK$1928,4,0)),IF(расчеты!AP4="02:050",IF(M4="",VLOOKUP(расчеты!L4,'КК и удельник'!$AG$3:$AK$1928,3,0),VLOOKUP(расчеты!M4,'КК и удельник'!$AG$3:$AK$1928,3,0)),IF(расчеты!AP4="02:014",IF(M4="",VLOOKUP(расчеты!L4,'КК и удельник'!$AG$3:$AK$1928,5,0),VLOOKUP(расчеты!M4,'КК и удельник'!$AG$3:$AK$1928,5,0))))))) -> 0 | BM4: =VLOOKUP(AP4,коэф.модели!$J$5:$K$7,2,0) -> #N/A | BN4: =VLOOKUP(BM4,коэф.модели!$F$6:$G$11,2,0) -> #N/A | BO4: =IF(M4="",IF(L4="47:004:1:1:1",IF(BM4="многоэтажный",9,VLOOKUP(BM4,коэф.модели!$K$5:$L$7,2,0)),VLOOKUP(BM4,коэф.модели!$K$5:$L$7,2,0)),IF(M4="47:004:1:1:1",IF(BM4="многоэтажный",9,VLOOKUP(BM4,коэф.модели!$K$5:$L$7,2,0)),VLOOKUP(BM4,коэф.модели!$K$5:$L$7,2,0))) -> #N/A | BP4: =IF(AQ4=AP4,J4,ROUND(0.6329*LN(BO4)+0.0442,4)) -> 0 | BQ4: =IF(AN4=AL4,IF(H4="отсутствие теплоснабжения","отсутствие теплоснабжения","наличие теплоснабжения"),"наличие теплоснабжения") -> наличие теплоснабжения | BR4: =VLOOKUP(BQ4,коэф.модели!$F$12:$G$17,2,0) -> 1 | BS4: =IF(AN4=AL4,IF(F4="отсутствие электроснабжения","отсутствие электроснабжения","наличие электроснабжения"),"наличие электроснабжения") -> наличие электроснабжения | BT4: =VLOOKUP(BS4,коэф.модели!$F$12:$G$17,2,0) -> 1 | BU4: =IF(AN4=AL4,IF(G4="отсутствие водоотведения","отсутствие водоотведения","наличие водоотведения"),"наличие водоотведения") -> наличие водоотведения | BV4: =VLOOKUP(BU4,коэф.модели!$F$12:$G$17,2,0) -> 1 | BW4: =ROUND(PRODUCT(BL4,BN4,BP4,BR4,BT4,BV4),2) -> #N/A | BX4: =ROUND(BW4*Q4,2) -> #N/A | BY4: =8002 -> 8002 | BZ4: СТ16_Ф1_М2_18052021_Бунаков | CA4: =IF(OR(BX4<0,BX4=0),"ОТРИЦАТЕЛЬНОЕ ЗНАЧЕНИЕ",IF(OR(CG4=0,CG4<1),"Пересчет не требуется","Готов")) -> #N/A | CB4: =AP4 -> 0 | CC4: =IF(CB4="02:014",$CQ$1,$CR$1) -> 2. СЕГМЕНТ "Жилая застройка (среднеэтажная и многоэтажная)" | CD4: =IF(CB4="02:014",$CQ$2,$CR$2) -> 2 | CE4: =VLOOKUP(CB4,'справочник ВРИ'!$A$3:$B$271,2,0) -> #N/A | CF4: =AO4 -> 0 | CG4: =IF(ISBLANK(N4),"Новый объект",IF(AL4=AN4,ABS(BX4-O4),"Объект из другой модели")) -> Новый объект | CH4: =IF(AN4=AL4,BW4-N4,IF(OR(BW4<866,BW4>17260),"Отклонение УПКС","УПКС объекта в допустимом интервале")) -> #N/A | CI4: =IF(CG4="Объект из другой модели",CG4,IF(CG4="Новый объект",CG4,IF(CG4>50000000,"Внимание!Изменение стоимости","Изменение менее 50 млн"))) -> Новый объект | CJ4: =IF(I4="","Новое значение",IF(I4=BL4,"Осталось предыдущее значение ЦФ","ИЗМЕНЕНИЕ")) -> Новое значение | CK4: =IF(F4="","Новое значение",IF(BS4=F4,"Осталось предыдущее значение ЦФ","ИЗМЕНЕНИЕ")) -> Новое значение | CL4: =IF(H4="","Новое значение",IF(BQ4=H4,"Осталось предыдущее значение ЦФ","ИЗМЕНЕНИЕ")) -> Новое значение | CM4: =IF(N4="","Объект новый",IF(AG4="не готов","ИЗМЕНЕНИЕ","Осталось предыдущее значение ЦФ")) -> Объект новый | CN4: =IF(J4="","Новое значение",IF(BP4=J4,"Осталось предыдущее значение ЦФ","ИЗМЕНЕНИЕ")) -> Новое значение | CO4: =IF(K4="","Новое значение",IF(BM4=K4,"Осталось предыдущее значение ЦФ","ИЗМЕНЕНИЕ")) -> Новое значение | CP4: =IF(AP4=AQ4,"Осталось предыдущее значение ЦФ","ИЗМЕНЕНИЕ") -> Осталось предыдущее значение ЦФ | CQ4: =IFERROR(IFERROR(IFERROR(VLOOKUP(BL4,'КК и удельник'!$E$3:$G$6521,3,0),VLOOKUP(BL4,'КК и удельник'!$D$3:$G$6521,4,0)),VLOOKUP(BL4,'КК и удельник'!$AI$3:$AL$1928,4,0)),VLOOKUP(BL4,'КК и удельник'!$AK$3:$AL$1928,2,0)) -> #N/A | CR4: =CQ4=BK4 -> #N/A
A5: 1644014 | B5: 66:41:0704041:7 | C5: 66:41:0000000 | D5: 4191 | F5: наличие электроснабжения | G5: наличие водоотведения | H5: наличие теплоснабжения | I5: 77071.443 | J5: 1.0628 | K5: среднеэтажный | L5: 47:004:1:1:1 | N5: 6806.85 | O5: 28527508 | P5: ППЗ_M2_Осипов | Q5: 3296 | R5: Земли населенных пунктов | S5: наличие | T5: наличие | U5: наличие | V5: наличие | Z5: 10 | AA5: 12.05.2021 | AB5: НЕ ГОТОВ | AE5: не готов | AF5: ГОТОВ | AG5: не готов | AH5: ГОТОВ | AI5: ГОТОВ | AJ5: ГОТОВ | AK5: Правило6 | AL5: 8002 | AN5: 8002 | AO5: земли жилой застройки (для жилищных нужд) | AP5: 02:050 | AQ5: 02:050 | AR5: земли жилой застройки (для жилищных нужд) | AU5: =I5 -> 77071.443 | AV5: =K5 -> среднеэтажный | AW5: =VLOOKUP(AV5,коэф.модели!$F$6:$G$11,2,0) -> 0.0831 | AX5: =J5 -> 1.0628 | AY5: =H5 -> наличие теплоснабжения | AZ5: =IF(AY5="","ОШИБКА",VLOOKUP(AY5,коэф.модели!$F$12:$G$17,2,0)) -> 1 | BA5: =F5 -> наличие электроснабжения | BB5: =IF(BA5="","ОШИБКА",VLOOKUP(BA5,коэф.модели!$F$12:$G$17,2,0)) -> 1 | BC5: =G5 -> наличие водоотведения | BD5: =IF(BC5="","ОШИБКА",VLOOKUP(BC5,коэф.модели!$F$12:$G$17,2,0)) -> 1 | BE5: =ROUND(PRODUCT(AU5,AW5,AX5,AZ5,BD5,BB5),2) -> 6806.85 | BF5: =MROUND(BE5*D5,2) -> 28527508 | BG5: =IF(N5="","Новый объект",IF(AN5=AL5,BF5-O5,"Объект пришел из другой модели")) -> 0 | BH5: =IF(AM5="",IF(AC5<>"","ОСПАРИВАНИЕ",IF(AS5<>"","СУД",IF(W5="","",W5))),AM5) | BI5: =B5 -> 66:41:0704041:7 | BJ5: =Q5 -> 3296 | BK5: =IFERROR(IF(AP5="02:060",VLOOKUP(C5,'КК и удельник'!$A$3:$E$6521,2,0),IF(расчеты!AP5="02:050",VLOOKUP(расчеты!C5,'КК и удельник'!$A$3:$E$6521,2,0),IF(расчеты!AP5="02:014",VLOOKUP(расчеты!C5,'КК и удельник'!$A$3:$E$6521,2,0)))),IF(AP5="02:060",IF(M5="",VLOOKUP(L5,'КК и удельник'!$AG$3:$AK$1928,2,0),VLOOKUP(M5,'КК и удельник'!$AG$3:$AK$1928,2,0)),IF(расчеты!AP5="02:050",IF(M5="",VLOOKUP(расчеты!L5,'КК и удельник'!$AG$3:$AK$1928,2,0),VLOOKUP(расчеты!M5,'КК и удельник'!$AG$3:$AK$1928,2,0)),IF(расчеты!AP5="02:014",IF(M5="",VLOOKUP(расчеты!L5,'КК и удельник'!$AG$3:$AK$1928,2,0),VLOOKUP(расчеты!M5,'КК и удельник'!$AG$3:$AK$1928,2,0)),"ОШИБКА")))) -> АКАДЕМИЧЕСКИЙ | BL5: =IF(AQ5=AP5,I5,IFERROR(IF(AP5="02:060",VLOOKUP(C5,'КК и удельник'!$A$3:$E$6521,4,0),IF(расчеты!AP5="02:050",VLOOKUP(расчеты!C5,'КК и удельник'!$A$3:$E$6521,3,0),IF(расчеты!AP5="02:014",VLOOKUP(расчеты!C5,'КК и удельник'!$A$3:$E$6521,5,0)))),IF(AP5="02:060",IF(M5="",VLOOKUP(L5,'КК и удельник'!$AG$3:$AK$1928,4,0),VLOOKUP(M5,'КК и удельник'!$AG$3:$AK$1928,4,0)),IF(расчеты!AP5="02:050",IF(M5="",VLOOKUP(расчеты!L5,'КК и удельник'!$AG$3:$AK$1928,3,0),VLOOKUP(расчеты!M5,'КК и удельник'!$AG$3:$AK$1928,3,0)),IF(расчеты!AP5="02:014",IF(M5="",VLOOKUP(расчеты!L5,'КК и удельник'!$AG$3:$AK$1928,5,0),VLOOKUP(расчеты!M5,'КК и удельник'!$AG$3:$AK$1928,5,0))))))) -> 77071.443 | BM5: =VLOOKUP(AP5,коэф.модели!$J$5:$K$7,2,0) -> среднеэтажный | BN5: =VLOOKUP(BM5,коэф.модели!$F$6:$G$11,2,0) -> 0.0831 | BO5: =IF(M5="",IF(L5="47:004:1:1:1",IF(BM5="многоэтажный",9,VLOOKUP(BM5,коэф.модели!$K$5:$L$7,2,0)),VLOOKUP(BM5,коэф.модели!$K$5:$L$7,2,0)),IF(M5="47:004:1:1:1",IF(BM5="многоэтажный",9,VLOOKUP(BM5,коэф.модели!$K$5:$L$7,2,0)),VLOOKUP(BM5,коэф.модели!$K$5:$L$7,2,0))) -> 5 | BP5: =IF(AQ5=AP5,J5,ROUND(0.6329*LN(BO5)+0.0442,4)) -> 1.0628 | BQ5: =IF(AN5=AL5,IF(H5="отсутствие теплоснабжения","отсутствие теплоснабжения","наличие теплоснабжения"),"наличие теплоснабжения") -> наличие теплоснабжения | BR5: =VLOOKUP(BQ5,коэф.модели!$F$12:$G$17,2,0) -> 1 | BS5: =IF(AN5=AL5,IF(F5="отсутствие электроснабжения","отсутствие электроснабжения","наличие электроснабжения"),"наличие электроснабжения") -> наличие электроснабжения | BT5: =VLOOKUP(BS5,коэф.модели!$F$12:$G$17,2,0) -> 1 | BU5: =IF(AN5=AL5,IF(G5="отсутствие водоотведения","отсутствие водоотведения","наличие водоотведения"),"наличие водоотведения") -> наличие водоотведения | BV5: =VLOOKUP(BU5,коэф.модели!$F$12:$G$17,2,0) -> 1 | BW5: =ROUND(PRODUCT(BL5,BN5,BP5,BR5,BT5,BV5),2) -> 6806.85 | BX5: =ROUND(BW5*Q5,2) -> 22435378 | BY5: =8002 -> 8002 | BZ5: СТ16_Ф1_М2_18052021_Бунаков | CA5: =IF(OR(BX5<0,BX5=0),"ОТРИЦАТЕЛЬНОЕ ЗНАЧЕНИЕ",IF(OR(CG5=0,CG5<1),"Пересчет не требуется","Готов")) -> Готов | CB5: =AP5 -> 02:050 | CC5: =IF(CB5="02:014",$CQ$1,$CR$1) -> 2. СЕГМЕНТ "Жилая застройка (среднеэтажная и многоэтажная)" | CD5: =IF(CB5="02:014",$CQ$2,$CR$2) -> 2 | CE5: =VLOOKUP(CB5,'справочник ВРИ'!$A$3:$B$271,2,0) -> Среднеэтажная жилая застройка в целом | CF5: =AO5 -> земли жилой застройки (для жилищных нужд) | CG5: =IF(ISBLANK(N5),"Новый объект",IF(AL5=AN5,ABS(BX5-O5),"Объект из другой модели")) -> 6092130.4 | CH5: =IF(AN5=AL5,BW5-N5,IF(OR(BW5<866,BW5>17260),"Отклонение УПКС","УПКС объекта в допустимом интервале")) -> 0 | CI5: =IF(CG5="Объект из другой модели",CG5,IF(CG5="Новый объект",CG5,IF(CG5>50000000,"Внимание!Изменение стоимости","Изменение менее 50 млн"))) -> Изменение менее 50 млн | CJ5: =IF(I5="","Новое значение",IF(I5=BL5,"Осталось предыдущее значение ЦФ","ИЗМЕНЕНИЕ")) -> Осталось предыдущее значение ЦФ | CK5: =IF(F5="","Новое значение",IF(BS5=F5,"Осталось предыдущее значение ЦФ","ИЗМЕНЕНИЕ")) -> Осталось предыдущее значение ЦФ | CL5: =IF(H5="","Новое значение",IF(BQ5=H5,"Осталось предыдущее значение ЦФ","ИЗМЕНЕНИЕ")) -> Осталось предыдущее значение ЦФ | CM5: =IF(N5="","Объект новый",IF(AG5="не готов","ИЗМЕНЕНИЕ","Осталось предыдущее значение ЦФ")) -> ИЗМЕНЕНИЕ | CN5: =IF(J5="","Новое значение",IF(BP5=J5,"Осталось предыдущее значение ЦФ","ИЗМЕНЕНИЕ")) -> Осталось предыдущее значение ЦФ | CO5: =IF(K5="","Новое значение",IF(BM5=K5,"Осталось предыдущее значение ЦФ","ИЗМЕНЕНИЕ")) -> Осталось предыдущее значение ЦФ | CP5: =IF(AP5=AQ5,"Осталось предыдущее значение ЦФ","ИЗМЕНЕНИЕ") -> Осталось предыдущее значение ЦФ | CQ5: =IFERROR(IFERROR(IFERROR(VLOOKUP(BL5,'КК и удельник'!$E$3:$G$6521,3,0),VLOOKUP(BL5,'КК и удельник'!$D$3:$G$6521,4,0)),VLOOKUP(BL5,'КК и удельник'!$AI$3:$AL$1928,4,0)),VLOOKUP(BL5,'КК и удельник'!$AK$3:$AL$1928,2,0)) -> ВТУЗГОРОДОК | CR5: =CQ5=BK5 -> FALSE
A6: Select ID,Source_ID,CadastralNumber,DateCreated,CadastralBlock,Name,ObjectType,Area,AreaUnit,AreaInaccuracy,LocationinBounds,LocationPlaced,ElaborationReferenceMark,ElaborationDistance,ElaborationDirection,AddressOrLocation,FIAS,OKATO,KLADR,OKTMO,PostalCode,AddressRF,Region,DistrictName,DistrictType,CityName,CityType,UrbanDistrictName,UrbanDistrictType,SovietVillageName,SovietVillageType,LocalityName,LocalityType,PlanningElementName,PlanningElementType,StreetName,StreetType,Level1Type,Level1Value,Level2Type,Level2Value,Level3Type,Level3Value,ApartmentType,ApartmentValue,AddressOther,AddressNote,ParcelCategory,Utilization,UtilizationByDoc,UtilizationLandUse,UtilizationТхт,CostValue,CostUnit,CostDateValuation,CostDateEntering,CostDateApproval,CostDocNumber,CostDocDate,CostApplicationDate,CostRevisalStatementDate,CostApplicationLastDate,CostDocName,FacilityKN,FacilityKNPurpose,SurveyProjectNum,DecisionCodeDocument,DecisionName,DecisionSeries,DecisionNumber,DecisionDate,DecisionIssueOrgan,DecisionDesc,HiredHouseUse,HouseActBuilding,HouseActDevelopment,BuildingContractName,DevelopContractName,OwnerDecision,SupportContractName,CodeDocument,DocHiredHouseName,DocHiredHouseSeries,DocHiredHouseNumber,DocHiredHouseDate,DocHiredHouseIssueOrgan,DocHiredHouseDesc,LimitedRightNumber,CREATEOPERATORNAME,CREATEDATE,OPERATORNAME,MODIFYDATE,MI_STYLE,Specific_CadastralCost,CadastralCost,CadastralCostDesc,MO_Name,ID_Group,LocalityCode,locTypeUse2,loc_VICode,loc_GroupName,loc_VRICode,Sourse_loc_VICode,locTypeUse,inputpacket_id,loc_SgCode,VIP_Sp,Quant_Kontur,Quant_Point,Sum_Square,Sum_Perim,Proc_Diff_Square,Pr_Diff,Source_Sum_Square,SourceLocalityCode,Upload_Scroll,Date_KC,Segment,FlagLocalityCode,DistanceToRoad,DistanceToCMO,СМО,PresenceGas,SourcePresenceGas,PresenceHeating,SourcePresenceHeating,PresencePower,SourcePresencePower,PresenceWaterDisposal,SourcePresenceWaterDisposal,PresenceWaterSupply,SourcePresenceWaterSupply,DistanceToEKB,DistanceToRoadEKB,CCoordX,CCoordY,DistanceToMetro,DistanceToStationEKB,CostZone,DistanceToRRStation,costzone2,Textloc_VICode,act_sign,MaxFloor,Enc_squre,Enc_proc,Adm_rn_EKB,forestry,InfluenceZone_IGS,loc_factor_801,loc_factor_802,loc_factor_803,loc_factor_804,loc_factor_806,loc_factor_807,loc_factor_8071,loc_factor_809,loc_factor_8091,loc_factor_810,loc_factor_8101,loc_factor_811,loc_factor_8111,loc_factor_812,loc_factor_8121,loc_factor_813,loc_factor_814,loc_factor_815,loc_factor_816,loc_factor_8161,loc_factor_817,loc_factor_818,loc_factor_819,loc_factor_820,loc_factor_8201,loc_factor_821,loc_factor_822,loc_factor_823,loc_factor_8231,loc_factor_824,loc_factor_825,loc_factor_826,loc_factor_827,loc_factor_828,loc_factor_829,loc_factor_830,loc_factor_831,loc_factor_832,loc_factor_833,loc_factor_8331,loc_factor_835,loc_factor_836,loc_factor_837,loc_factor_838,Statement,Type_Statement,Status_Statement,DistanceToVZC,VRI_IGS,Cot_name,DistanceToZTB,PowerLines,loc_factor_839,KodMO,loc_factor_840,loc_factor_841,presence_entrance,loc_factor_8371,ControlSP,Sp_flag,loc_VRICode540,Status_kc,Date_comm,Sol_comm,Flag_LocalityCode,Flag_VRI,Flag_Location,FlagParam,Flag_VRIoldspr,Flag_VRInewspr,Flag_Category,OldLocalityCode,Flag_VRI_All,VRICode_NEW,PraviloVRI,New_id_group,New_loc_SgCode,New_Segment,Old_Utlbydoc,VRICode_OLD,PraviloVRI_old,Court,Date_Court,Sol_Court,(select (case count(*) when 0 then 0 else 1 end) from GEO.docboxes b where b.obj_id=PARCELS.ID and b.table_id=265) Attachment,(select sign(Count(*)) from PARCELS g where (not GEOM_OBJ is null) and (PARCELS.ID = g.ID)) GeometryExists,((select DatePacket from inputpacket where id=Parcels.inputpacket_id) ) [inputpacket_date] From PARCELS WHERE status_kc = 'НЕ ГОТОВ' AND New_id_group=8002 | AU6: =I6 -> 0 | AV6: =K6 -> 0 | AW6: =VLOOKUP(AV6,коэф.модели!$F$6:$G$11,2,0) -> #N/A | AX6: =J6 -> 0 | AY6: =H6 -> 0 | AZ6: =IF(AY6="","ОШИБКА",VLOOKUP(AY6,коэф.модели!$F$12:$G$17,2,0)) -> #N/A | BA6: =F6 -> 0 | BB6: =IF(BA6="","ОШИБКА",VLOOKUP(BA6,коэф.модели!$F$12:$G$17,2,0)) -> #N/A | BC6: =G6 -> 0 | BD6: =IF(BC6="","ОШИБКА",VLOOKUP(BC6,коэф.модели!$F$12:$G$17,2,0)) -> #N/A | BE6: =ROUND(PRODUCT(AU6,AW6,AX6,AZ6,BD6,BB6),2) -> #N/A | BF6: =MROUND(BE6*D6,2) -> #N/A | BG6: =IF(N6="","Новый объект",IF(AN6=AL6,BF6-O6,"Объект пришел из другой модели")) -> Новый объект | BH6: =IF(AM6="",IF(AC6<>"","ОСПАРИВАНИЕ",IF(AS6<>"","СУД",IF(W6="","",W6))),AM6) | BI6: =B6 -> 0 | BJ6: =Q6 -> 0 | BK6: =IFERROR(IF(AP6="02:060",VLOOKUP(C6,'КК и удельник'!$A$3:$E$6521,2,0),IF(расчеты!AP6="02:050",VLOOKUP(расчеты!C6,'КК и удельник'!$A$3:$E$6521,2,0),IF(расчеты!AP6="02:014",VLOOKUP(расчеты!C6,'КК и удельник'!$A$3:$E$6521,2,0)))),IF(AP6="02:060",IF(M6="",VLOOKUP(L6,'КК и удельник'!$AG$3:$AK$1928,2,0),VLOOKUP(M6,'КК и удельник'!$AG$3:$AK$1928,2,0)),IF(расчеты!AP6="02:050",IF(M6="",VLOOKUP(расчеты!L6,'КК и удельник'!$AG$3:$AK$1928,2,0),VLOOKUP(расчеты!M6,'КК и удельник'!$AG$3:$AK$1928,2,0)),IF(расчеты!AP6="02:014",IF(M6="",VLOOKUP(расчеты!L6,'КК и удельник'!$AG$3:$AK$1928,2,0),VLOOKUP(расчеты!M6,'КК и удельник'!$AG$3:$AK$1928,2,0)),"ОШИБКА")))) -> FALSE | BL6: =IF(AQ6=AP6,I6,IFERROR(IF(AP6="02:060",VLOOKUP(C6,'КК и удельник'!$A$3:$E$6521,4,0),IF(расчеты!AP6="02:050",VLOOKUP(расчеты!C6,'КК и удельник'!$A$3:$E$6521,3,0),IF(расчеты!AP6="02:014",VLOOKUP(расчеты!C6,'КК и удельник'!$A$3:$E$6521,5,0)))),IF(AP6="02:060",IF(M6="",VLOOKUP(L6,'КК и удельник'!$AG$3:$AK$1928,4,0),VLOOKUP(M6,'КК и удельник'!$AG$3:$AK$1928,4,0)),IF(расчеты!AP6="02:050",IF(M6="",VLOOKUP(расчеты!L6,'КК и удельник'!$AG$3:$AK$1928,3,0),VLOOKUP(расчеты!M6,'КК и удельник'!$AG$3:$AK$1928,3,0)),IF(расчеты!AP6="02:014",IF(M6="",VLOOKUP(расчеты!L6,'КК и удельник'!$AG$3:$AK$1928,5,0),VLOOKUP(расчеты!M6,'КК и удельник'!$AG$3:$AK$1928,5,0))))))) -> 0 | BM6: =VLOOKUP(AP6,коэф.модели!$J$5:$K$7,2,0) -> #N/A | BN6: =VLOOKUP(BM6,коэф.модели!$F$6:$G$11,2,0) -> #N/A | BO6: =IF(M6="",IF(L6="47:004:1:1:1",IF(BM6="многоэтажный",9,VLOOKUP(BM6,коэф.модели!$K$5:$L$7,2,0)),VLOOKUP(BM6,коэф.модели!$K$5:$L$7,2,0)),IF(M6="47:004:1:1:1",IF(BM6="многоэтажный",9,VLOOKUP(BM6,коэф.модели!$K$5:$L$7,2,0)),VLOOKUP(BM6,коэф.модели!$K$5:$L$7,2,0))) -> #N/A | BP6: =IF(AQ6=AP6,J6,ROUND(0.6329*LN(BO6)+0.0442,4)) -> 0 | BQ6: =IF(AN6=AL6,IF(H6="отсутствие теплоснабжения","отсутствие теплоснабжения","наличие теплоснабжения"),"наличие теплоснабжения") -> наличие теплоснабжения | BR6: =VLOOKUP(BQ6,коэф.модели!$F$12:$G$17,2,0) -> 1 | BS6: =IF(AN6=AL6,IF(F6="отсутствие электроснабжения","отсутствие электроснабжения","наличие электроснабжения"),"наличие электроснабжения") -> наличие электроснабжения | BT6: =VLOOKUP(BS6,коэф.модели!$F$12:$G$17,2,0) -> 1 | BU6: =IF(AN6=AL6,IF(G6="отсутствие водоотведения","отсутствие водоотведения","наличие водоотведения"),"наличие водоотведения") -> наличие водоотведения | BV6: =VLOOKUP(BU6,коэф.модели!$F$12:$G$17,2,0) -> 1 | BW6: =ROUND(PRODUCT(BL6,BN6,BP6,BR6,BT6,BV6),2) -> #N/A | BX6: =ROUND(BW6*Q6,2) -> #N/A | BY6: =8002 -> 8002 | BZ6: СТ16_Ф1_М2_18052021_Бунаков | CA6: =IF(OR(BX6<0,BX6=0),"ОТРИЦАТЕЛЬНОЕ ЗНАЧЕНИЕ",IF(OR(CG6=0,CG6<1),"Пересчет не требуется","Готов")) -> #N/A | CB6: =AP6 -> 0 | CC6: =IF(CB6="02:014",$CQ$1,$CR$1) -> 2. СЕГМЕНТ "Жилая застройка (среднеэтажная и многоэтажная)" | CD6: =IF(CB6="02:014",$CQ$2,$CR$2) -> 2 | CE6: =VLOOKUP(CB6,'справочник ВРИ'!$A$3:$B$271,2,0) -> #N/A | CF6: =AO6 -> 0 | CG6: =IF(ISBLANK(N6),"Новый объект",IF(AL6=AN6,ABS(BX6-O6),"Объект из другой модели")) -> Новый объект | CH6: =IF(AN6=AL6,BW6-N6,IF(OR(BW6<866,BW6>17260),"Отклонение УПКС","УПКС объекта в допустимом интервале")) -> #N/A | CI6: =IF(CG6="Объект из другой модели",CG6,IF(CG6="Новый объект",CG6,IF(CG6>50000000,"Внимание!Изменение стоимости","Изменение менее 50 млн"))) -> Новый объект | CJ6: =IF(I6="","Новое значение",IF(I6=BL6,"Осталось предыдущее значение ЦФ","ИЗМЕНЕНИЕ")) -> Новое значение | CK6: =IF(F6="","Новое значение",IF(BS6=F6,"Осталось предыдущее значение ЦФ","ИЗМЕНЕНИЕ")) -> Новое значение | CL6: =IF(H6="","Новое значение",IF(BQ6=H6,"Осталось предыдущее значение ЦФ","ИЗМЕНЕНИЕ")) -> Новое значение | CM6: =IF(N6="","Объект новый",IF(AG6="не готов","ИЗМЕНЕНИЕ","Осталось предыдущее значение ЦФ")) -> Объект новый | CN6: =IF(J6="","Новое значение",IF(BP6=J6,"Осталось предыдущее значение ЦФ","ИЗМЕНЕНИЕ")) -> Новое значение | CO6: =IF(K6="","Новое значение",IF(BM6=K6,"Осталось предыдущее значение ЦФ","ИЗМЕНЕНИЕ")) -> Новое значение | CP6: =IF(AP6=AQ6,"Осталось предыдущее значение ЦФ","ИЗМЕНЕНИЕ") -> Осталось предыдущее значение ЦФ | CQ6: =IFERROR(IFERROR(IFERROR(VLOOKUP(BL6,'КК и удельник'!$E$3:$G$6521,3,0),VLOOKUP(BL6,'КК и удельник'!$D$3:$G$6521,4,0)),VLOOKUP(BL6,'КК и удельник'!$AI$3:$AL$1928,4,0)),VLOOKUP(BL6,'КК и удельник'!$AK$3:$AL$1928,2,0)) -> #N/A | CR6: =CQ6=BK6 -> #N/A
AU7: =I7 -> 0 | AV7: =K7 -> 0 | AW7: =VLOOKUP(AV7,коэф.модели!$F$6:$G$11,2,0) -> #N/A | AX7: =J7 -> 0 | AY7: =H7 -> 0 | AZ7: =IF(AY7="","ОШИБКА",VLOOKUP(AY7,коэф.модели!$F$12:$G$17,2,0)) -> #N/A | BA7: =F7 -> 0 | BB7: =IF(BA7="","ОШИБКА",VLOOKUP(BA7,коэф.модели!$F$12:$G$17,2,0)) -> #N/A | BC7: =G7 -> 0 | BD7: =IF(BC7="","ОШИБКА",VLOOKUP(BC7,коэф.модели!$F$12:$G$17,2,0)) -> #N/A | BE7: =ROUND(PRODUCT(AU7,AW7,AX7,AZ7,BD7,BB7),2) -> #N/A | BF7: =MROUND(BE7*D7,2) -> #N/A | BG7: =IF(N7="","Новый объект",IF(AN7=AL7,BF7-O7,"Объект пришел из другой модели")) -> Новый объект | BH7: =IF(AM7="",IF(AC7<>"","ОСПАРИВАНИЕ",IF(AS7<>"","СУД",IF(W7="","",W7))),AM7) | BI7: =B7 -> 0 | BJ7: =Q7 -> 0 | BK7: =IFERROR(IF(AP7="02:060",VLOOKUP(C7,'КК и удельник'!$A$3:$E$6521,2,0),IF(расчеты!AP7="02:050",VLOOKUP(расчеты!C7,'КК и удельник'!$A$3:$E$6521,2,0),IF(расчеты!AP7="02:014",VLOOKUP(расчеты!C7,'КК и удельник'!$A$3:$E$6521,2,0)))),IF(AP7="02:060",IF(M7="",VLOOKUP(L7,'КК и удельник'!$AG$3:$AK$1928,2,0),VLOOKUP(M7,'КК и удельник'!$AG$3:$AK$1928,2,0)),IF(расчеты!AP7="02:050",IF(M7="",VLOOKUP(расчеты!L7,'КК и удельник'!$AG$3:$AK$1928,2,0),VLOOKUP(расчеты!M7,'КК и удельник'!$AG$3:$AK$1928,2,0)),IF(расчеты!AP7="02:014",IF(M7="",VLOOKUP(расчеты!L7,'КК и удельник'!$AG$3:$AK$1928,2,0),VLOOKUP(расчеты!M7,'КК и удельник'!$AG$3:$AK$1928,2,0)),"ОШИБКА")))) -> FALSE | BL7: =IF(AQ7=AP7,I7,IFERROR(IF(AP7="02:060",VLOOKUP(C7,'КК и удельник'!$A$3:$E$6521,4,0),IF(расчеты!AP7="02:050",VLOOKUP(расчеты!C7,'КК и удельник'!$A$3:$E$6521,3,0),IF(расчеты!AP7="02:014",VLOOKUP(расчеты!C7,'КК и удельник'!$A$3:$E$6521,5,0)))),IF(AP7="02:060",IF(M7="",VLOOKUP(L7,'КК и удельник'!$AG$3:$AK$1928,4,0),VLOOKUP(M7,'КК и удельник'!$AG$3:$AK$1928,4,0)),IF(расчеты!AP7="02:050",IF(M7="",VLOOKUP(расчеты!L7,'КК и удельник'!$AG$3:$AK$1928,3,0),VLOOKUP(расчеты!M7,'КК и удельник'!$AG$3:$AK$1928,3,0)),IF(расчеты!AP7="02:014",IF(M7="",VLOOKUP(расчеты!L7,'КК и удельник'!$AG$3:$AK$1928,5,0),VLOOKUP(расчеты!M7,'КК и удельник'!$AG$3:$AK$1928,5,0))))))) -> 0 | BM7: =VLOOKUP(AP7,коэф.модели!$J$5:$K$7,2,0) -> #N/A | BN7: =VLOOKUP(BM7,коэф.модели!$F$6:$G$11,2,0) -> #N/A | BO7: =IF(M7="",IF(L7="47:004:1:1:1",IF(BM7="многоэтажный",9,VLOOKUP(BM7,коэф.модели!$K$5:$L$7,2,0)),VLOOKUP(BM7,коэф.модели!$K$5:$L$7,2,0)),IF(M7="47:004:1:1:1",IF(BM7="многоэтажный",9,VLOOKUP(BM7,коэф.модели!$K$5:$L$7,2,0)),VLOOKUP(BM7,коэф.модели!$K$5:$L$7,2,0))) -> #N/A | BP7: =IF(AQ7=AP7,J7,ROUND(0.6329*LN(BO7)+0.0442,4)) -> 0 | BQ7: =IF(AN7=AL7,IF(H7="отсутствие теплоснабжения","отсутствие теплоснабжения","наличие теплоснабжения"),"наличие теплоснабжения") -> наличие теплоснабжения | BR7: =VLOOKUP(BQ7,коэф.модели!$F$12:$G$17,2,0) -> 1 | BS7: =IF(AN7=AL7,IF(F7="отсутствие электроснабжения","отсутствие электроснабжения","наличие электроснабжения"),"наличие электроснабжения") -> наличие электроснабжения | BT7: =VLOOKUP(BS7,коэф.модели!$F$12:$G$17,2,0) -> 1 | BU7: =IF(AN7=AL7,IF(G7="отсутствие водоотведения","отсутствие водоотведения","наличие водоотведения"),"наличие водоотведения") -> наличие водоотведения | BV7: =VLOOKUP(BU7,коэф.модели!$F$12:$G$17,2,0) -> 1 | BW7: =ROUND(PRODUCT(BL7,BN7,BP7,BR7,BT7,BV7),2) -> #N/A | BX7: =ROUND(BW7*Q7,2) -> #N/A | BY7: =8002 -> 8002 | BZ7: СТ16_Ф1_М2_18052021_Бунаков | CA7: =IF(OR(BX7<0,BX7=0),"ОТРИЦАТЕЛЬНОЕ ЗНАЧЕНИЕ",IF(OR(CG7=0,CG7<1),"Пересчет не требуется","Готов")) -> #N/A | CB7: =AP7 -> 0 | CC7: =IF(CB7="02:014",$CQ$1,$CR$1) -> 2. СЕГМЕНТ "Жилая застройка (среднеэтажная и многоэтажная)" | CD7: =IF(CB7="02:014",$CQ$2,$CR$2) -> 2 | CE7: =VLOOKUP(CB7,'справочник ВРИ'!$A$3:$B$271,2,0) -> #N/A | CF7: =AO7 -> 0 | CG7: =IF(ISBLANK(N7),"Новый объект",IF(AL7=AN7,ABS(BX7-O7),"Объект из другой модели")) -> Новый объект | CH7: =IF(AN7=AL7,BW7-N7,IF(OR(BW7<866,BW7>17260),"Отклонение УПКС","УПКС объекта в допустимом интервале")) -> #N/A | CI7: =IF(CG7="Объект из другой модели",CG7,IF(CG7="Новый объект",CG7,IF(CG7>50000000,"Внимание!Изменение стоимости","Изменение менее 50 млн"))) -> Новый объект | CJ7: =IF(I7="","Новое значение",IF(I7=BL7,"Осталось предыдущее значение ЦФ","ИЗМЕНЕНИЕ")) -> Новое значение | CK7: =IF(F7="","Новое значение",IF(BS7=F7,"Осталось предыдущее значение ЦФ","ИЗМЕНЕНИЕ")) -> Новое значение | CL7: =IF(H7="","Новое значение",IF(BQ7=H7,"Осталось предыдущее значение ЦФ","ИЗМЕНЕНИЕ")) -> Новое значение | CM7: =IF(N7="","Объект новый",IF(AG7="не готов","ИЗМЕНЕНИЕ","Осталось предыдущее значение ЦФ")) -> Объект новый | CN7: =IF(J7="","Новое значение",IF(BP7=J7,"Осталось предыдущее значение ЦФ","ИЗМЕНЕНИЕ")) -> Новое значение | CO7: =IF(K7="","Новое значение",IF(BM7=K7,"Осталось предыдущее значение ЦФ","ИЗМЕНЕНИЕ")) -> Новое значение | CP7: =IF(AP7=AQ7,"Осталось предыдущее значение ЦФ","ИЗМЕНЕНИЕ") -> Осталось предыдущее значение ЦФ | CQ7: =IFERROR(IFERROR(IFERROR(VLOOKUP(BL7,'КК и удельник'!$E$3:$G$6521,3,0),VLOOKUP(BL7,'КК и удельник'!$D$3:$G$6521,4,0)),VLOOKUP(BL7,'КК и удельник'!$AI$3:$AL$1928,4,0)),VLOOKUP(BL7,'КК и удельник'!$AK$3:$AL$1928,2,0)) -> #N/A | CR7: =CQ7=BK7 -> #N/A
AU8: =I8 -> 0 | AV8: =K8 -> 0 | AW8: =VLOOKUP(AV8,коэф.модели!$F$6:$G$11,2,0) -> #N/A | AX8: =J8 -> 0 | AY8: =H8 -> 0 | AZ8: =IF(AY8="","ОШИБКА",VLOOKUP(AY8,коэф.модели!$F$12:$G$17,2,0)) -> #N/A | BA8: =F8 -> 0 | BB8: =IF(BA8="","ОШИБКА",VLOOKUP(BA8,коэф.модели!$F$12:$G$17,2,0)) -> #N/A | BC8: =G8 -> 0 | BD8: =IF(BC8="","ОШИБКА",VLOOKUP(BC8,коэф.модели!$F$12:$G$17,2,0)) -> #N/A | BE8: =ROUND(PRODUCT(AU8,AW8,AX8,AZ8,BD8,BB8),2) -> #N/A | BF8: =MROUND(BE8*D8,2) -> #N/A | BG8: =IF(N8="","Новый объект",IF(AN8=AL8,BF8-O8,"Объект пришел из другой модели")) -> Новый объект | BH8: =IF(AM8="",IF(AC8<>"","ОСПАРИВАНИЕ",IF(AS8<>"","СУД",IF(W8="","",W8))),AM8) | BI8: =B8 -> 0 | BJ8: =Q8 -> 0 | BK8: =IFERROR(IF(AP8="02:060",VLOOKUP(C8,'КК и удельник'!$A$3:$E$6521,2,0),IF(расчеты!AP8="02:050",VLOOKUP(расчеты!C8,'КК и удельник'!$A$3:$E$6521,2,0),IF(расчеты!AP8="02:014",VLOOKUP(расчеты!C8,'КК и удельник'!$A$3:$E$6521,2,0)))),IF(AP8="02:060",IF(M8="",VLOOKUP(L8,'КК и удельник'!$AG$3:$AK$1928,2,0),VLOOKUP(M8,'КК и удельник'!$AG$3:$AK$1928,2,0)),IF(расчеты!AP8="02:050",IF(M8="",VLOOKUP(расчеты!L8,'КК и удельник'!$AG$3:$AK$1928,2,0),VLOOKUP(расчеты!M8,'КК и удельник'!$AG$3:$AK$1928,2,0)),IF(расчеты!AP8="02:014",IF(M8="",VLOOKUP(расчеты!L8,'КК и удельник'!$AG$3:$AK$1928,2,0),VLOOKUP(расчеты!M8,'КК и удельник'!$AG$3:$AK$1928,2,0)),"ОШИБКА")))) -> FALSE | BL8: =IF(AQ8=AP8,I8,IFERROR(IF(AP8="02:060",VLOOKUP(C8,'КК и удельник'!$A$3:$E$6521,4,0),IF(расчеты!AP8="02:050",VLOOKUP(расчеты!C8,'КК и удельник'!$A$3:$E$6521,3,0),IF(расчеты!AP8="02:014",VLOOKUP(расчеты!C8,'КК и удельник'!$A$3:$E$6521,5,0)))),IF(AP8="02:060",IF(M8="",VLOOKUP(L8,'КК и удельник'!$AG$3:$AK$1928,4,0),VLOOKUP(M8,'КК и удельник'!$AG$3:$AK$1928,4,0)),IF(расчеты!AP8="02:050",IF(M8="",VLOOKUP(расчеты!L8,'КК и удельник'!$AG$3:$AK$1928,3,0),VLOOKUP(расчеты!M8,'КК и удельник'!$AG$3:$AK$1928,3,0)),IF(расчеты!AP8="02:014",IF(M8="",VLOOKUP(расчеты!L8,'КК и удельник'!$AG$3:$AK$1928,5,0),VLOOKUP(расчеты!M8,'КК и удельник'!$AG$3:$AK$1928,5,0))))))) -> 0 | BM8: =VLOOKUP(AP8,коэф.модели!$J$5:$K$7,2,0) -> #N/A | BN8: =VLOOKUP(BM8,коэф.модели!$F$6:$G$11,2,0) -> #N/A | BO8: =IF(M8="",IF(L8="47:004:1:1:1",IF(BM8="многоэтажный",9,VLOOKUP(BM8,коэф.модели!$K$5:$L$7,2,0)),VLOOKUP(BM8,коэф.модели!$K$5:$L$7,2,0)),IF(M8="47:004:1:1:1",IF(BM8="многоэтажный",9,VLOOKUP(BM8,коэф.модели!$K$5:$L$7,2,0)),VLOOKUP(BM8,коэф.модели!$K$5:$L$7,2,0))) -> #N/A | BP8: =IF(AQ8=AP8,J8,ROUND(0.6329*LN(BO8)+0.0442,4)) -> 0 | BQ8: =IF(AN8=AL8,IF(H8="отсутствие теплоснабжения","отсутствие теплоснабжения","наличие теплоснабжения"),"наличие теплоснабжения") -> наличие теплоснабжения | BR8: =VLOOKUP(BQ8,коэф.модели!$F$12:$G$17,2,0) -> 1 | BS8: =IF(AN8=AL8,IF(F8="отсутствие электроснабжения","отсутствие электроснабжения","наличие электроснабжения"),"наличие электроснабжения") -> наличие электроснабжения | BT8: =VLOOKUP(BS8,коэф.модели!$F$12:$G$17,2,0) -> 1 | BU8: =IF(AN8=AL8,IF(G8="отсутствие водоотведения","отсутствие водоотведения","наличие водоотведения"),"наличие водоотведения") -> наличие водоотведения | BV8: =VLOOKUP(BU8,коэф.модели!$F$12:$G$17,2,0) -> 1 | BW8: =ROUND(PRODUCT(BL8,BN8,BP8,BR8,BT8,BV8),2) -> #N/A | BX8: =ROUND(BW8*Q8,2) -> #N/A | BY8: =8002 -> 8002 | BZ8: СТ16_Ф1_М2_18052021_Бунаков | CA8: =IF(OR(BX8<0,BX8=0),"ОТРИЦАТЕЛЬНОЕ ЗНАЧЕНИЕ",IF(OR(CG8=0,CG8<1),"Пересчет не требуется","Готов")) -> #N/A | CB8: =AP8 -> 0 | CC8: =IF(CB8="02:014",$CQ$1,$CR$1) -> 2. СЕГМЕНТ "Жилая застройка (среднеэтажная и многоэтажная)" | CD8: =IF(CB8="02:014",$CQ$2,$CR$2) -> 2 | CE8: =VLOOKUP(CB8,'справочник ВРИ'!$A$3:$B$271,2,0) -> #N/A | CF8: =AO8 -> 0 | CG8: =IF(ISBLANK(N8),"Новый объект",IF(AL8=AN8,ABS(BX8-O8),"Объект из другой модели")) -> Новый объект | CH8: =IF(AN8=AL8,BW8-N8,IF(OR(BW8<866,BW8>17260),"Отклонение УПКС","УПКС объекта в допустимом интервале")) -> #N/A | CI8: =IF(CG8="Объект из другой модели",CG8,IF(CG8="Новый объект",CG8,IF(CG8>50000000,"Внимание!Изменение стоимости","Изменение менее 50 млн"))) -> Новый объект | CJ8: =IF(I8="","Новое значение",IF(I8=BL8,"Осталось предыдущее значение ЦФ","ИЗМЕНЕНИЕ")) -> Новое значение | CK8: =IF(F8="","Новое значение",IF(BS8=F8,"Осталось предыдущее значение ЦФ","ИЗМЕНЕНИЕ")) -> Новое значение | CL8: =IF(H8="","Новое значение",IF(BQ8=H8,"Осталось предыдущее значение ЦФ","ИЗМЕНЕНИЕ")) -> Новое значение | CM8: =IF(N8="","Объект новый",IF(AG8="не готов","ИЗМЕНЕНИЕ","Осталось предыдущее значение ЦФ")) -> Объект новый | CN8: =IF(J8="","Новое значение",IF(BP8=J8,"Осталось предыдущее значение ЦФ","ИЗМЕНЕНИЕ")) -> Новое значение | CO8: =IF(K8="","Новое значение",IF(BM8=K8,"Осталось предыдущее значение ЦФ","ИЗМЕНЕНИЕ")) -> Новое значение | CP8: =IF(AP8=AQ8,"Осталось предыдущее значение ЦФ","ИЗМЕНЕНИЕ") -> Осталось предыдущее значение ЦФ | CQ8: =IFERROR(IFERROR(IFERROR(VLOOKUP(BL8,'КК и удельник'!$E$3:$G$6521,3,0),VLOOKUP(BL8,'КК и удельник'!$D$3:$G$6521,4,0)),VLOOKUP(BL8,'КК и удельник'!$AI$3:$AL$1928,4,0)),VLOOKUP(BL8,'КК и удельник'!$AK$3:$AL$1928,2,0)) -> #N/A | CR8: =CQ8=BK8 -> #N/A
AU9: =I9 -> 0 | AV9: =K9 -> 0 | AW9: =VLOOKUP(AV9,коэф.модели!$F$6:$G$11,2,0) -> #N/A | AX9: =J9 -> 0 | AY9: =H9 -> 0 | AZ9: =IF(AY9="","ОШИБКА",VLOOKUP(AY9,коэф.модели!$F$12:$G$17,2,0)) -> #N/A | BA9: =F9 -> 0 | BB9: =IF(BA9="","ОШИБКА",VLOOKUP(BA9,коэф.модели!$F$12:$G$17,2,0)) -> #N/A | BC9: =G9 -> 0 | BD9: =IF(BC9="","ОШИБКА",VLOOKUP(BC9,коэф.модели!$F$12:$G$17,2,0)) -> #N/A | BE9: =ROUND(PRODUCT(AU9,AW9,AX9,AZ9,BD9,BB9),2) -> #N/A | BF9: =MROUND(BE9*D9,2) -> #N/A | BG9: =IF(N9="","Новый объект",IF(AN9=AL9,BF9-O9,"Объект пришел из другой модели")) -> Новый объект | BH9: =IF(AM9="",IF(AC9<>"","ОСПАРИВАНИЕ",IF(AS9<>"","СУД",IF(W9="","",W9))),AM9) | BI9: =B9 -> 0 | BJ9: =Q9 -> 0 | BK9: =IFERROR(IF(AP9="02:060",VLOOKUP(C9,'КК и удельник'!$A$3:$E$6521,2,0),IF(расчеты!AP9="02:050",VLOOKUP(расчеты!C9,'КК и удельник'!$A$3:$E$6521,2,0),IF(расчеты!AP9="02:014",VLOOKUP(расчеты!C9,'КК и удельник'!$A$3:$E$6521,2,0)))),IF(AP9="02:060",IF(M9="",VLOOKUP(L9,'КК и удельник'!$AG$3:$AK$1928,2,0),VLOOKUP(M9,'КК и удельник'!$AG$3:$AK$1928,2,0)),IF(расчеты!AP9="02:050",IF(M9="",VLOOKUP(расчеты!L9,'КК и удельник'!$AG$3:$AK$1928,2,0),VLOOKUP(расчеты!M9,'КК и удельник'!$AG$3:$AK$1928,2,0)),IF(расчеты!AP9="02:014",IF(M9="",VLOOKUP(расчеты!L9,'КК и удельник'!$AG$3:$AK$1928,2,0),VLOOKUP(расчеты!M9,'КК и удельник'!$AG$3:$AK$1928,2,0)),"ОШИБКА")))) -> FALSE | BL9: =IF(AQ9=AP9,I9,IFERROR(IF(AP9="02:060",VLOOKUP(C9,'КК и удельник'!$A$3:$E$6521,4,0),IF(расчеты!AP9="02:050",VLOOKUP(расчеты!C9,'КК и удельник'!$A$3:$E$6521,3,0),IF(расчеты!AP9="02:014",VLOOKUP(расчеты!C9,'КК и удельник'!$A$3:$E$6521,5,0)))),IF(AP9="02:060",IF(M9="",VLOOKUP(L9,'КК и удельник'!$AG$3:$AK$1928,4,0),VLOOKUP(M9,'КК и удельник'!$AG$3:$AK$1928,4,0)),IF(расчеты!AP9="02:050",IF(M9="",VLOOKUP(расчеты!L9,'КК и удельник'!$AG$3:$AK$1928,3,0),VLOOKUP(расчеты!M9,'КК и удельник'!$AG$3:$AK$1928,3,0)),IF(расчеты!AP9="02:014",IF(M9="",VLOOKUP(расчеты!L9,'КК и удельник'!$AG$3:$AK$1928,5,0),VLOOKUP(расчеты!M9,'КК и удельник'!$AG$3:$AK$1928,5,0))))))) -> 0 | BM9: =VLOOKUP(AP9,коэф.модели!$J$5:$K$7,2,0) -> #N/A | BN9: =VLOOKUP(BM9,коэф.модели!$F$6:$G$11,2,0) -> #N/A | BO9: =IF(M9="",IF(L9="47:004:1:1:1",IF(BM9="многоэтажный",9,VLOOKUP(BM9,коэф.модели!$K$5:$L$7,2,0)),VLOOKUP(BM9,коэф.модели!$K$5:$L$7,2,0)),IF(M9="47:004:1:1:1",IF(BM9="многоэтажный",9,VLOOKUP(BM9,коэф.модели!$K$5:$L$7,2,0)),VLOOKUP(BM9,коэф.модели!$K$5:$L$7,2,0))) -> #N/A | BP9: =IF(AQ9=AP9,J9,ROUND(0.6329*LN(BO9)+0.0442,4)) -> 0 | BQ9: =IF(AN9=AL9,IF(H9="отсутствие теплоснабжения","отсутствие теплоснабжения","наличие теплоснабжения"),"наличие теплоснабжения") -> наличие теплоснабжения | BR9: =VLOOKUP(BQ9,коэф.модели!$F$12:$G$17,2,0) -> 1 | BS9: =IF(AN9=AL9,IF(F9="отсутствие электроснабжения","отсутствие электроснабжения","наличие электроснабжения"),"наличие электроснабжения") -> наличие электроснабжения | BT9: =VLOOKUP(BS9,коэф.модели!$F$12:$G$17,2,0) -> 1 | BU9: =IF(AN9=AL9,IF(G9="отсутствие водоотведения","отсутствие водоотведения","наличие водоотведения"),"наличие водоотведения") -> наличие водоотведения | BV9: =VLOOKUP(BU9,коэф.модели!$F$12:$G$17,2,0) -> 1 | BW9: =ROUND(PRODUCT(BL9,BN9,BP9,BR9,BT9,BV9),2) -> #N/A | BX9: =ROUND(BW9*Q9,2) -> #N/A | BY9: =8002 -> 8002 | BZ9: СТ16_Ф1_М2_18052021_Бунаков | CA9: =IF(OR(BX9<0,BX9=0),"ОТРИЦАТЕЛЬНОЕ ЗНАЧЕНИЕ",IF(OR(CG9=0,CG9<1),"Пересчет не требуется","Готов")) -> #N/A | CB9: =AP9 -> 0 | CC9: =IF(CB9="02:014",$CQ$1,$CR$1) -> 2. СЕГМЕНТ "Жилая застройка (среднеэтажная и многоэтажная)" | CD9: =IF(CB9="02:014",$CQ$2,$CR$2) -> 2 | CE9: =VLOOKUP(CB9,'справочник ВРИ'!$A$3:$B$271,2,0) -> #N/A | CF9: =AO9 -> 0 | CG9: =IF(ISBLANK(N9),"Новый объект",IF(AL9=AN9,ABS(BX9-O9),"Объект из другой модели")) -> Новый объект | CH9: =IF(AN9=AL9,BW9-N9,IF(OR(BW9<866,BW9>17260),"Отклонение УПКС","УПКС объекта в допустимом интервале")) -> #N/A | CI9: =IF(CG9="Объект из другой модели",CG9,IF(CG9="Новый объект",CG9,IF(CG9>50000000,"Внимание!Изменение стоимости","Изменение менее 50 млн"))) -> Новый объект | CJ9: =IF(I9="","Новое значение",IF(I9=BL9,"Осталось предыдущее значение ЦФ","ИЗМЕНЕНИЕ")) -> Новое значение | CK9: =IF(F9="","Новое значение",IF(BS9=F9,"Осталось предыдущее значение ЦФ","ИЗМЕНЕНИЕ")) -> Новое значение | CL9: =IF(H9="","Новое значение",IF(BQ9=H9,"Осталось предыдущее значение ЦФ","ИЗМЕНЕНИЕ")) -> Новое значение | CM9: =IF(N9="","Объект новый",IF(AG9="не готов","ИЗМЕНЕНИЕ","Осталось предыдущее значение ЦФ")) -> Объект новый | CN9: =IF(J9="","Новое значение",IF(BP9=J9,"Осталось предыдущее значение ЦФ","ИЗМЕНЕНИЕ")) -> Новое значение | CO9: =IF(K9="","Новое значение",IF(BM9=K9,"Осталось предыдущее значение ЦФ","ИЗМЕНЕНИЕ")) -> Новое значение | CP9: =IF(AP9=AQ9,"Осталось предыдущее значение ЦФ","ИЗМЕНЕНИЕ") -> Осталось предыдущее значение ЦФ | CQ9: =IFERROR(IFERROR(IFERROR(VLOOKUP(BL9,'КК и удельник'!$E$3:$G$6521,3,0),VLOOKUP(BL9,'КК и удельник'!$D$3:$G$6521,4,0)),VLOOKUP(BL9,'КК и удельник'!$AI$3:$AL$1928,4,0)),VLOOKUP(BL9,'КК и удельник'!$AK$3:$AL$1928,2,0)) -> #N/A | CR9: =CQ9=BK9 -> #N/A
AU10: =I10 -> 0 | AV10: =K10 -> 0 | AW10: =VLOOKUP(AV10,коэф.модели!$F$6:$G$11,2,0) -> #N/A | AX10: =J10 -> 0 | AY10: =H10 -> 0 | AZ10: =IF(AY10="","ОШИБКА",VLOOKUP(AY10,коэф.модели!$F$12:$G$17,2,0)) -> #N/A | BA10: =F10 -> 0 | BB10: =IF(BA10="","ОШИБКА",VLOOKUP(BA10,коэф.модели!$F$12:$G$17,2,0)) -> #N/A | BC10: =G10 -> 0 | BD10: =IF(BC10="","ОШИБКА",VLOOKUP(BC10,коэф.модели!$F$12:$G$17,2,0)) -> #N/A | BE10: =ROUND(PRODUCT(AU10,AW10,AX10,AZ10,BD10,BB10),2) -> #N/A | BF10: =MROUND(BE10*D10,2) -> #N/A | BG10: =IF(N10="","Новый объект",IF(AN10=AL10,BF10-O10,"Объект пришел из другой модели")) -> Новый объект | BH10: =IF(AM10="",IF(AC10<>"","ОСПАРИВАНИЕ",IF(AS10<>"","СУД",IF(W10="","",W10))),AM10) | BI10: =B10 -> 0 | BJ10: =Q10 -> 0 | BK10: =IFERROR(IF(AP10="02:060",VLOOKUP(C10,'КК и удельник'!$A$3:$E$6521,2,0),IF(расчеты!AP10="02:050",VLOOKUP(расчеты!C10,'КК и удельник'!$A$3:$E$6521,2,0),IF(расчеты!AP10="02:014",VLOOKUP(расчеты!C10,'КК и удельник'!$A$3:$E$6521,2,0)))),IF(AP10="02:060",IF(M10="",VLOOKUP(L10,'КК и удельник'!$AG$3:$AK$1928,2,0),VLOOKUP(M10,'КК и удельник'!$AG$3:$AK$1928,2,0)),IF(расчеты!AP10="02:050",IF(M10="",VLOOKUP(расчеты!L10,'КК и удельник'!$AG$3:$AK$1928,2,0),VLOOKUP(расчеты!M10,'КК и удельник'!$AG$3:$AK$1928,2,0)),IF(расчеты!AP10="02:014",IF(M10="",VLOOKUP(расчеты!L10,'КК и удельник'!$AG$3:$AK$1928,2,0),VLOOKUP(расчеты!M10,'КК и удельник'!$AG$3:$AK$1928,2,0)),"ОШИБКА")))) -> FALSE | BL10: =IF(AQ10=AP10,I10,IFERROR(IF(AP10="02:060",VLOOKUP(C10,'КК и удельник'!$A$3:$E$6521,4,0),IF(расчеты!AP10="02:050",VLOOKUP(расчеты!C10,'КК и удельник'!$A$3:$E$6521,3,0),IF(расчеты!AP10="02:014",VLOOKUP(расчеты!C10,'КК и удельник'!$A$3:$E$6521,5,0)))),IF(AP10="02:060",IF(M10="",VLOOKUP(L10,'КК и удельник'!$AG$3:$AK$1928,4,0),VLOOKUP(M10,'КК и удельник'!$AG$3:$AK$1928,4,0)),IF(расчеты!AP10="02:050",IF(M10="",VLOOKUP(расчеты!L10,'КК и удельник'!$AG$3:$AK$1928,3,0),VLOOKUP(расчеты!M10,'КК и удельник'!$AG$3:$AK$1928,3,0)),IF(расчеты!AP10="02:014",IF(M10="",VLOOKUP(расчеты!L10,'КК и удельник'!$AG$3:$AK$1928,5,0),VLOOKUP(расчеты!M10,'КК и удельник'!$AG$3:$AK$1928,5,0))))))) -> 0 | BM10: =VLOOKUP(AP10,коэф.модели!$J$5:$K$7,2,0) -> #N/A | BN10: =VLOOKUP(BM10,коэф.модели!$F$6:$G$11,2,0) -> #N/A | BO10: =IF(M10="",IF(L10="47:004:1:1:1",IF(BM10="многоэтажный",9,VLOOKUP(BM10,коэф.модели!$K$5:$L$7,2,0)),VLOOKUP(BM10,коэф.модели!$K$5:$L$7,2,0)),IF(M10="47:004:1:1:1",IF(BM10="многоэтажный",9,VLOOKUP(BM10,коэф.модели!$K$5:$L$7,2,0)),VLOOKUP(BM10,коэф.модели!$K$5:$L$7,2,0))) -> #N/A | BP10: =IF(AQ10=AP10,J10,ROUND(0.6329*LN(BO10)+0.0442,4)) -> 0 | BQ10: =IF(AN10=AL10,IF(H10="отсутствие теплоснабжения","отсутствие теплоснабжения","наличие теплоснабжения"),"наличие теплоснабжения") -> наличие теплоснабжения | BR10: =VLOOKUP(BQ10,коэф.модели!$F$12:$G$17,2,0) -> 1 | BS10: =IF(AN10=AL10,IF(F10="отсутствие электроснабжения","отсутствие электроснабжения","наличие электроснабжения"),"наличие электроснабжения") -> наличие электроснабжения | BT10: =VLOOKUP(BS10,коэф.модели!$F$12:$G$17,2,0) -> 1 | BU10: =IF(AN10=AL10,IF(G10="отсутствие водоотведения","отсутствие водоотведения","наличие водоотведения"),"наличие водоотведения") -> наличие водоотведения | BV10: =VLOOKUP(BU10,коэф.модели!$F$12:$G$17,2,0) -> 1 | BW10: =ROUND(PRODUCT(BL10,BN10,BP10,BR10,BT10,BV10),2) -> #N/A | BX10: =ROUND(BW10*Q10,2) -> #N/A | BY10: =8002 -> 8002 | BZ10: СТ16_Ф1_М2_18052021_Бунаков | CA10: =IF(OR(BX10<0,BX10=0),"ОТРИЦАТЕЛЬНОЕ ЗНАЧЕНИЕ",IF(OR(CG10=0,CG10<1),"Пересчет не требуется","Готов")) -> #N/A | CB10: =AP10 -> 0 | CC10: =IF(CB10="02:014",$CQ$1,$CR$1) -> 2. СЕГМЕНТ "Жилая застройка (среднеэтажная и многоэтажная)" | CD10: =IF(CB10="02:014",$CQ$2,$CR$2) -> 2 | CE10: =VLOOKUP(CB10,'справочник ВРИ'!$A$3:$B$271,2,0) -> #N/A | CF10: =AO10 -> 0 | CG10: =IF(ISBLANK(N10),"Новый объект",IF(AL10=AN10,ABS(BX10-O10),"Объект из другой модели")) -> Новый объект | CH10: =IF(AN10=AL10,BW10-N10,IF(OR(BW10<866,BW10>17260),"Отклонение УПКС","УПКС объекта в допустимом интервале")) -> #N/A | CI10: =IF(CG10="Объект из другой модели",CG10,IF(CG10="Новый объект",CG10,IF(CG10>50000000,"Внимание!Изменение стоимости","Изменение менее 50 млн"))) -> Новый объект | CJ10: =IF(I10="","Новое значение",IF(I10=BL10,"Осталось предыдущее значение ЦФ","ИЗМЕНЕНИЕ")) -> Новое значение | CK10: =IF(F10="","Новое значение",IF(BS10=F10,"Осталось предыдущее значение ЦФ","ИЗМЕНЕНИЕ")) -> Новое значение | CL10: =IF(H10="","Новое значение",IF(BQ10=H10,"Осталось предыдущее значение ЦФ","ИЗМЕНЕНИЕ")) -> Новое значение | CM10: =IF(N10="","Объект новый",IF(AG10="не готов","ИЗМЕНЕНИЕ","Осталось предыдущее значение ЦФ")) -> Объект новый | CN10: =IF(J10="","Новое значение",IF(BP10=J10,"Осталось предыдущее значение ЦФ","ИЗМЕНЕНИЕ")) -> Новое значение | CO10: =IF(K10="","Новое значение",IF(BM10=K10,"Осталось предыдущее значение ЦФ","ИЗМЕНЕНИЕ")) -> Новое значение | CP10: =IF(AP10=AQ10,"Осталось предыдущее значение ЦФ","ИЗМЕНЕНИЕ") -> Осталось предыдущее значение ЦФ | CQ10: =IFERROR(IFERROR(IFERROR(VLOOKUP(BL10,'КК и удельник'!$E$3:$G$6521,3,0),VLOOKUP(BL10,'КК и удельник'!$D$3:$G$6521,4,0)),VLOOKUP(BL10,'КК и удельник'!$AI$3:$AL$1928,4,0)),VLOOKUP(BL10,'КК и удельник'!$AK$3:$AL$1928,2,0)) -> #N/A | CR10: =CQ10=BK10 -> #N/A

Sheet ГОТОВ
A1: CadastralNumber | B1: loc_factor_807 | D1: loc_Factor_838 | E1: loc_Factor_836 | H1: loc_Factor_835 | I1: loc_Factor_802 | K1: loc_Factor_804 | M1: loc_Factor_803 | O1: Specific_CadastralCost | P1: CadastralCost | Q1: id_group | R1: CadastralCostDesc | S1: Status_kc | T1: loc_VICode | U1: Segment | V1: loc_SgCode | W1: loc_GroupName | X1: Old_Utlbydoc

Sheet ПЕРЕСЧЕТ НЕ ТРЕБУЕТСЯ
A1: CadastralNumber | B1: Status_kc | C1: loc_VICode | D1: Segment | E1: loc_SgCode | F1: loc_GroupName | G1: Old_Utlbydoc

Sheet СТОПЛИСТ
A1: CadastralNumber | B1: ControlSP

Sheet справочник ВРИ
A1: loc_VICode | B1: loc_GroupName
A2: Код расчета вида использования | B2: Наименование вида использования
A3: 01:010 | B3: Растениеводство в целом. Включает коды расчета вида использования 01.020-01.060
A4: 01:020 | B4: Выращивание зерновых, бобовых, кормовых, технических, масличных, эфиромасличных и иных сельскохозяйственных культур
A5: 01:030 | B5: Овощеводство в целом, связанное с производством картофеля, листовых, плодовых, луковичных и бахчевых сельскохозяйственных культур, в том числе с использованием теплиц
A6: 01:031 | B6: Овощеводство в открытом грунте
A7: 01:032 | B7: Овощеводство тепличное
A8: 01:040 | B8: Выращивание тонизирующих, лекарственных, цветочных культур в целом
A9: 01:041 | B9: Выращивание тонизирующих, лекарственных, цветочных культур. Травы
A10: 01:042 | B10: Выращивание тонизирующих, лекарственных, цветочных культур. Кустарники
A11: 01:050 | B11: Садоводство в целом - выращивание многолетних плодовых и ягодных культур, винограда и иных многолетних культур
A12: 01:051 | B12: Садоводство плодовое
... A271: 14:000 | B271: Иное использование

Sheet коэф.модели
B2: Модель №2 | D2: y=V1*V2*V3*V4*V5*V6
B3: Фактор | C3: Обозначение фактора | D3: Номер модели | E3: Наименование ЦФ | F3: Градация (не хранится в БД как отдельное поле) | G3: Значение поправки
B4: Рыночная стоимость квартиры | C4: V1 | D4: 8002 | E4: =B4 -> Рыночная стоимость квартиры | F4: Число | G4: функция от местоположения квартиры | K4: Типовая характеристика | L4: Типовая этажность
B5: Коэффициент плотности | C5: V2 | D5: 8002 | E5: Коэффициент плотности | F5: Число | G5: функция от этажности | J5: 02:060 | K5: многоэтажный | L5: 9
B6: Коэффициент типовых характеристик | C6: V3 | D6: 8002 | E6: Коэффициент типовых характеристик | F6: малоэтажный | G6: 0.1228 | J6: 02:050 | K6: среднеэтажный | L6: 5
F7: малоэтажный | G7: 0.1228 | J7: 02:014 | K7: малоэтажный | L7: 3
F8: среднеэтажный | G8: 0.0831
F9: среднеэтажный | G9: 0.0831
F10: многоэтажный | G10: 0.0762
F11: многоэтажный | G11: 0.0762
B12: Теплоснабжение | C12: V4 | D12: 8002 | E12: Теплоснабжение | F12: наличие теплоснабжения | G12: 1
F13: отсутствие теплоснабжения | G13: 0.92
B14: Электроснабжение | C14: V5 | D14: 8002 | E14: Электроснабжение | F14: наличие электроснабжения | G14: 1
F15: отсутствие электроснабжения | G15: 0.92
B16: Водоотведение | C16: V6 | D16: 8002 | E16: Водоотведение | F16: наличие водоотведения | G16: 1
F17: отсутствие водоотведения | G17: 0.95

Sheet Лист4
A3: Названия строк | B3: Среднее по полю Удельник для Малоэтажного-02:014 | F3: Названия строк | G3: Количество по полю Удельник для Малоэтажного-02:014
A4: 66:12:1610001 | B4: 28935.146 | F4: 66:12:1610001 | G4: 1
A5: 66:12:1617001 | B5: 25951.934 | F5: 66:12:1617001 | G5: 1
A6: 66:12:5213006 | B6: 31984.905 | F6: 66:12:5213006 | G6: 1
A7: 66:12:6901001 | B7: 25946.143 | F7: 66:12:6901001 | G7: 1
A8: 66:19:0101006 | B8: 20837.465 | F8: 66:19:0101006 | G8: 1
A9: 66:19:0101017 | B9: 26241.208 | F9: 66:19:0101017 | G9: 1
A10: 66:19:0101018 | B10: 26241.208 | F10: 66:19:0101018 | G10: 1
A11: 66:19:0101019 | B11: 26241.208 | F11: 66:19:0101019 | G11: 1
A12: 66:19:0101020 | B12: 26241.208 | F12: 66:19:0101020 | G12: 1
A13: 66:19:0101022 | B13: 32052.277 | F13: 66:19:0101022 | G13: 1
A14: 66:19:0101023 | B14: 32052.277 | F14: 66:19:0101023 | G14: 1
A15: 66:19:0101024 | B15: 32052.277 | F15: 66:19:0101024 | G15: 1
... A5033: Общий итог | B5033: 49994.412 | F5033: Общий итог | G5033: 6529

Sheet КК и удельник
A1: На странице нельзя удалять строки | B1: С учетом трансформации | C1: Без учета инфляции | F1: На странице нельзя удалять строки | L1: Желтый цвет -КК в 1003 | M1: Таблица перекодировки ЕКБ | R1: Каменск | X1: Первоуральск | AC1: Тагил
A2: КК | B2: Зона | C2: Удельник для Среднеэтажного-02:050 | D2: Удельник для Многоэтажного-02:060 | E2: Удельник для Малоэтажного-02:014 | F2: Признак квартала | M2: АВТОВОКЗАЛ | N2: =M2 -> АВТОВОКЗАЛ | R2: Наименование жилого района | S2: Наименование объединенного жилого массива (зона) | T2: Сокращенное наименование для построения модели | X2: Наименование жилого района | Y2: Сокращенное наименование для построения модели | AC2: Наименование жилого района | AD2: Сокращенное наименование для построения модели | AF2: ГО | AG2: КОД НП | AH2: ГО | AI2: Удельник для Среднеэтажного-02:050 | AJ2: Удельник для Многоэтажного-02:060 | AK2: Удельник для Малоэтажного-02:014
A3: 66:41:0401041 | B3: Центр | C3: 93989.913 | D3: 93989.913 | E3: 85109.545 | F3: КК из расчетника | G3: =B3 -> Центр | M3: АКАДЕМИЧЕСКИЙ | N3: =M3 -> АКАДЕМИЧЕСКИЙ | R3: микрорайон Южный | S3: Южный | T3: Южный | X3: Совхоз Первоуральский | Y3: Совхоз_Первоур | AC3: Верхняя Черемшанка пос. | AD3: Евст_В-Черм | AF3: Арамильский городской округ | AG3: 01:000:0:0:0 | AH3: Арамильский городской округ | AI3: 39614.886 | AJ3: 39614.886 | AK3: 36792.697 | AL3: =AF3 -> Арамильский городской округ
A4: 66:41:0609023 | B4: КОМПРЕССОРНЫЙ | C4: 56392.544 | D4: 56392.544 | E4: 51064.462 | F4: КК из расчетника | G4: =B4 -> КОМПРЕССОРНЫЙ | M4: БОТАНИЧЕСКИЙ | N4: =M4 -> БОТАНИЧЕСКИЙ | R4: микрорайон Октябрьский-I | S4: Октябрьский | T4: Октябрьский | X4: Первомайский | Y4: Первомайский | AC4: СУХОЛОЖСКИЙ | AD4: Сух_Г-Кам_Н_Кушва_Н-Черм | AF4: Арамильский городской округ | AG4: 01:001:1:1:4 | AH4: Арамильский городской округ | AI4: 48945.107 | AJ4: 48945.107 | AK4: 45458.222 | AL4: =AF4 -> Арамильский городской округ
A5: 66:41:0110004 | B5: ЭЛЬМАШ | C5: 70734.024 | D5: 70734.024 | E5: 64050.921 | F5: КК из расчетника | G5: =B5 -> ЭЛЬМАШ | M5: ВИЗ | N5: =M5 -> ВИЗ | R5: микрорайон Октябрьский-II | S5: Октябрьский | T5: Октябрьский | X5: Магнитка | Y5: Магнитка | AC5: ГОЛЫЙ КАМЕНЬ | AD5: Сух_Г-Кам_Н_Кушва_Н-Черм | AF5: Арамильский городской округ | AG5: 01:002:2:3:5 | AH5: Арамильский городской округ | AI5: 40607.171 | AJ5: 40607.171 | AK5: 37714.286 | AL5: =AF5 -> Арамильский городской округ
A6: 66:41:0206014 | B6: Центр | C6: 93989.913 | D6: 93989.913 | E6: 85109.545 | F6: КК из расчетника | G6: =B6 -> Центр | M6: ВОКЗАЛЬНЫЙ | N6: =M6 -> ВОКЗАЛЬНЫЙ | R6: 49-й квартал | S6: УАЗ III – 49 квартал | T6: УАЗ-III - 49 кв. | X6: ДИНАС | Y6: ДинСанПод | AC6: НОВАЯ КУШВА | AD6: Сух_Г-Кам_Н_Кушва_Н-Черм | AF6: Арамильский городской округ | AG6: 01:003:2:3:5 | AH6: Арамильский городской округ | AI6: 40607.171 | AJ6: 40607.171 | AK6: 37714.286 | AL6: =AF6 -> Арамильский городской округ
A7: 66:41:0303094 | B7: ВИЗ | C7: 84298.205 | D7: 84298.205 | E7: 76333.533 | F7: КК из расчетника | G7: =B7 -> ВИЗ | M7: ВТУЗГОРОДОК | N7: =M7 -> ВТУЗГОРОДОК | R7: ПОС.УАЗ-III | T7: УАЗ-III - 49 кв. | X7: ПОДВОЛОШНАЯ | Y7: ДинСанПод | AC7: Нижняя Черемшанка | AD7: Сух_Г-Кам_Н_Кушва_Н-Черм | AF7: Артемовский городской округ | AG7: 02:000:0:0:0 | AH7: Артемовский городской округ | AI7: 19458.838 | AJ7: 19458.838 | AK7: 18072.573 | AL7: =AF7 -> Артемовский городской округ
A8: 66:41:0601039 | B8: Центр | C8: 93989.913 | D8: 93989.913 | E8: 85109.545 | F8: КК из расчетника | G8: =B8 -> Центр | M8: ГОРНЫЙ ЩИТ | N8: =M8 -> ГОРНЫЙ ЩИТ | R8: ПОС.УАЗ-II | S8: УАЗ-II | T8: УАЗ-II | X8: Сантехизделий | Y8: ДинСанПод | AC8: РУДНИК ИМ. III ИНТЕРНАЦИОНАЛА | AD8: Рудник_Север | AF8: Артемовский городской округ | AG8: 02:001:1:1:4 | AH8: Артемовский городской округ | AI8: 24041.837 | AJ8: 24041.837 | AK8: 22329.077 | AL8: =AF8 -> Артемовский городской округ
A9: 66:41:0702035 | B9: ПИОНЕРСКИЙ | C9: 77743.704 | D9: 77743.704 | E9: 70398.311 | F9: КК из расчетника | G9: =B9 -> ПИОНЕРСКИЙ | M9: ЕЛИЗАВЕТ | N9: =M9 -> ЕЛИЗАВЕТ | R9: посёлок Трубников | S9: Трубников | T9: Трубников | X9: Соцгород | Y9: Соцгород | AC9: СЕВЕРНЫЙ М-Н | AD9: Рудник_Север | AF9: Артемовский городской округ | AG9: 02:002:2:4:6 | AH9: Артемовский городской округ | AI9: 19458.838 | AJ9: 19458.838 | AK9: 18072.573 | AL9: =AF9 -> Артемовский городской округ
A10: 66:41:0108117 | B10: ЭЛЬМАШ | C10: 70734.024 | D10: 70734.024 | E10: 64050.921 | F10: КК из расчетника | G10: =B10 -> ЭЛЬМАШ | M10: ЖБИ | N10: =M10 -> ЖБИ | R10: посёлок Ленинский | S10: Ленинский-Олимпийский | T10: Ленин-Олимп | X10: ТАЛИЦА ПОС. | Y10: Талица | AC10: ТАГИЛСТРОЙ | AD10: Тагил_Кирп | AF10: Артемовский городской округ | AG10: 02:003:2:3:6 | AH10: Артемовский городской округ | AI10: 19458.838 | AJ10: 19458.838 | AK10: 18072.573 | AL10: =AF10 -> Артемовский городской округ
A11: 66:41:0504035 | B11: ЧЕРМЕТ | C11: 62652.94 | D11: 62652.94 | E11: 56733.356 | F11: КК из расчетника | G11: =B11 -> ЧЕРМЕТ | M11: ЗАВОКЗАЛЬНЫЙ | N11: =M11 -> ЗАВОКЗАЛЬНЫЙ | R11: посёлок Олимпийский | S11: Ленинский-Олимпийский | T11: Ленин-Олимп | X11: Шайтанка | Y11: Шайтанка | AC11: КИРПИЧНЫЙ | AD11: Тагил_Кирп | AF11: Артемовский городской округ | AG11: 02:004:2:3:6 | AH11: Артемовский городской округ | AI11: 19458.838 | AJ11: 19458.838 | AK11: 18072.573 | AL11: =AF11 -> Артемовский городской округ
A12: 66:41:0108111 | B12: ЭЛЬМАШ | C12: 70734.024 | D12: 70734.024 | E12: 64050.921 | F12: КК из расчетника | G12: =B12 -> ЭЛЬМАШ | M12: ЗАРЕЧНЫЙ | N12: =M12 -> ЗАРЕЧНЫЙ | R12: ПОС. СЕВЕРНЫЙ | S12: Северный | T12: Северный | X12: Хромпик | Y12: Хромпик | AC12: ВЫЯ | AD12: Выя_Леб_Горб_Кр-Кам | AF12: Артемовский городской округ | AG12: 02:005:2:4:6 | AH12: Артемовский городской округ | AI12: 19458.838 | AJ12: 19458.838 | AK12: 18072.573 | AL12: =AF12 -> Артемовский городской округ
A13: 66:41:0609024 | B13: КОМПРЕССОРНЫЙ | C13: 56392.544 | D13: 56392.544 | E13: 51064.462 | F13: КК из расчетника | G13: =B13 -> КОМПРЕССОРНЫЙ | M13: ИЗОПЛИТ | N13: =M13 -> ИЗОПЛИТ | R13: посёлок Чкаловский | S13: Чкаловский | T13: Чкаловский | X13: КОРАБЕЛЬНАЯ РОЩА | Y13: КорабельнаяРоща | AC13: ЛЕБЯЖКА | AD13: Выя_Леб_Горб_Кр-Кам | AF13: Артемовский городской округ | AG13: 02:006:2:4:6 | AH13: Артемовский городской округ | AI13: 19458.838 | AJ13: 19458.838 | AK13: 18072.573 | AL13: =AF13 -> Артемовский городской округ
A14: 66:41:0504008 | B14: ЧЕРМЕТ | C14: 62652.94 | D14: 62652.94 | E14: 56733.356 | F14: КК из расчетника | G14: =B14 -> ЧЕРМЕТ | M14: ИСТОК | N14: =M14 -> ИСТОК | R14: посёлок Хозспособ | S14: Хозспособ-Старый Кменск | T14: Ст.Каменск-Хозспособ | X14: Западный | Y14: Западный | AC14: Горбуново | AD14: Выя_Леб_Горб_Кр-Кам | AF14: Артемовский городской округ | AG14: 02:007:2:3:6 | AH14: Артемовский городской округ | AI14: 19458.838 | AJ14: 19458.838 | AK14: 18072.573 | AL14: =AF14 -> Артемовский городской округ
A15: 66:41:0108009 | B15: ЭЛЬМАШ | C15: 70734.024 | D15: 70734.024 | E15: 64050.921 | F15: КК из расчетника | G15: =B15 -> ЭЛЬМАШ | M15: КАЛИНОВСКИЙ | N15: =M15 -> КАЛИНОВСКИЙ | R15: Старый Каменск | S15: Хозспособ-Старый Кменск | T15: Ст.Каменск-Хозспособ | X15: Центр | Y15: ЦЕНТР-Перв | AC15: КРАСНЫЙ КАМЕНЬ | AD15: Выя_Леб_Горб_Кр-Кам | AF15: Артемовский городской округ | AG15: 02:008:2:3:6 | AH15: Артемовский городской округ | AI15: 19458.838 | AJ15: 19458.838 | AK15: 18072.573 | AL15: =AF15 -> Артемовский городской округ
A16: 66:41:0108079 | B16: ЭЛЬМАШ | C16: 70734.024 | D16: 70734.024 | E16: 64050.921 | F16: КК из расчетника | G16: =B16 -> ЭЛЬМАШ | M16: КАРАСЬЕОЗЕРСК | N16: ШИРОКАЯ РЕЧКА | R16: ПОС. УАЗ-I | S16: УАЗ-I | T16: УАЗ | X16: Веер | Y16: Веер | AC16: СТАРАТЕЛЬ М-Н | AD16: Ваг_Стар_Пихтовы-г | AF16: Артемовский городской округ | AG16: 02:009:2:5:6 | AH16: Артемовский городской округ | AI16: 19458.838 | AJ16: 19458.838 | AK16: 18072.573 | AL16: =AF16 -> Артемовский городской округ
A17: 66:41:0108096 | B17: ЭЛЬМАШ | C17: 70734.024 | D17: 70734.024 | E17: 64050.921 | F17: КК из расчетника | G17: =B17 -> ЭЛЬМАШ | M17: КОЛЬЦОВО | N17: =M17 -> КОЛЬЦОВО | X17: Техгород | Y17: Техгород | AC17: ВАГОНКА | AD17: Ваг_Стар_Пихтовы-г | AF17: Артемовский городской округ | AG17: 02:010:2:3:6 | AH17: Артемовский городской округ | AI17: 19458.838 | AJ17: 19458.838 | AK17: 18072.573 | AL17: =AF17 -> Артемовский городской округ
A18: 66:41:0106097 | B18: УРАЛМАШ | C18: 70026.76 | D18: 70026.76 | E18: 63410.482 | F18: КК из расчетника | G18: =B18 -> УРАЛМАШ | M18: КОМПРЕССОРНЫЙ | N18: =M18 -> КОМПРЕССОРНЫЙ | R18: 52:000:0:0:0 | S18: мс | T18: Каменск-Уральскиймс | X18: Севернее ЖД | Y18: ДинСанПод | AC18: ПИХТОВЫЕ ГОРЫ | AD18: Ваг_Стар_Пихтовы-г | AF18: Артемовский городской округ | AG18: 02:011:2:3:6 | AH18: Артемовский городской округ | AI18: 19458.838 | AJ18: 19458.838 | AK18: 18072.573 | AL18: =AF18 -> Артемовский городской округ
A19: 66:41:0303080 | B19: ВИЗ | C19: 84298.205 | D19: 84298.205 | E19: 76333.533 | F19: КК из расчетника | G19: =B19 -> ВИЗ | M19: ЛЕЧЕБНЫЙ | N19: =M19 -> ЛЕЧЕБНЫЙ | R19: 52:001:1:1:2 | S19: г | T19: Каменск-Уральский | X19: Южнее ЖД | Y19: Магнитка | AC19: Гальяно-горбуновский массив ж/м | AD19: Алт_Гальян_М-Кушва | AF19: Артемовский городской округ | AG19: 02:012:2:3:6 | AH19: Артемовский городской округ | AI19: 19458.838 | AJ19: 19458.838 | AK19: 18072.573 | AL19: =AF19 -> Артемовский городской округ
A20: 66:41:0106102 | B20: УРАЛМАШ | C20: 70026.76 | D20: 70026.76 | E20: 63410.482 | F20: КК из расчетника | G20: =B20 -> УРАЛМАШ | M20: МАЛЫЙ ИСТОК | N20: =M20 -> МАЛЫЙ ИСТОК | R20: 52:002:1:1:2 | S20: д | T20: Кодинка | X20: САМСТРОЙ | Y20: ДинСанПод | AC20: АЛТАЙСКИЙ | AD20: Алт_Гальян_М-Кушва | AF20: Артемовский городской округ | AG20: 02:013:2:4:6 | AH20: Артемовский городской округ | AI20: 19458.838 | AJ20: 19458.838 | AK20: 18072.573 | AL20: =AF20 -> Артемовский городской округ
A21: 66:41:0106118 | B21: УРАЛМАШ | C21: 70026.76 | D21: 70026.76 | E21: 63410.482 | F21: КК из расчетника | G21: =B21 -> УРАЛМАШ | M21: МЕДНЫЙ | N21: =M21 -> МЕДНЫЙ | R21: 52:003:2:5:6 | S21: д | T21: Малая Кодинка | X21: Ельничный | Y21: Шайтанка | AC21: МАЛАЯ КУШВА | AD21: Алт_Гальян_М-Кушва | AF21: Артемовский городской округ | AG21: 02:014:2:4:6 | AH21: Артемовский городской округ | AI21: 19458.838 | AJ21: 19458.838 | AK21: 18072.573 | AL21: =AF21 -> Артемовский городской округ
A22: 66:41:0404012 | B22: УНЦ | C22: 64795.756 | D22: 64795.756 | E22: 58673.716 | F22: КК из расчетника | G22: =B22 -> УНЦ | M22: Нижнеисетский | N22: =M22 -> Нижнеисетский | Q22: Расчитана как область | R22: 52:004:1:1:2 | S22: д | T22: Монастырка | X22: Пильная | Y22: Шайтанка | AC22: ЦЕНТР | AD22: Центр-Тагил | AF22: Артемовский городской округ | AG22: 02:015:2:5:6 | AH22: Артемовский городской округ | AI22: 19458.838 | AJ22: 19458.838 | AK22: 18072.573 | AL22: =AF22 -> Артемовский городской округ
A23: 66:41:0106020 | B23: УРАЛМАШ | C23: 70026.76 | D23: 70026.76 | E23: 63410.482 | F23: КК из расчетника | G23: =B23 -> УРАЛМАШ | M23: Новая сортировка | N23: =M23 -> Новая сортировка | Q23: Ст.Каменск-Хозспособ | R23: 52:005:1:1:2 | S23: д | T23: Новый Завод | AC23: 9-Й ПОСЁЛОК | AD23: Алт_Гальян_М-Кушва | AF23: Артемовский городской округ | AG23: 02:016:2:5:6 | AH23: Артемовский городской округ | AI23: 19458.838 | AJ23: 19458.838 | AK23: 18072.573 | AL23: =AF23 -> Артемовский городской округ
A24: 66:41:0402020 | B24: АВТОВОКЗАЛ | C24: 83744.997 | D24: 83744.997 | E24: 75832.596 | F24: КК из расчетника | G24: =B24 -> АВТОВОКЗАЛ | M24: Палкино | N24: Шувакиш | R24: 52:006:2:3:6 | S24: п | T24: Поселок Госдороги | AC24: Ключики | AD24: Сух_Г-Кам_Н_Кушва_Н-Черм | AF24: Артемовский городской округ | AG24: 02:017:2:5:6 | AH24: Артемовский городской округ | AI24: 19458.838 | AJ24: 19458.838 | AK24: 18072.573 | AL24: =AF24 -> Артемовский городской округ
A25: 66:41:0704018 | B25: ВТУЗГОРОДОК | C25: 77071.443 | D25: 77071.443 | E25: 69789.571 | F25: КК из расчетника | G25: =B25 -> ВТУЗГОРОДОК | M25: Палникс | N25: ШИРОКАЯ РЕЧКА | R25: 52:007:1:1:2 | S25: д | T25: Токарева | AC25: ОЛЬХОВКА С. | AD25: Евст_В-Черм | AF25: Артемовский городской округ | AG25: 02:018:2:4:6 | AH25: Артемовский городской округ | AI25: 19458.838 | AJ25: 19458.838 | AK25: 18072.573 | AL25: =AF25 -> Артемовский городской округ
A26: 66:41:0108091 | B26: ЭЛЬМАШ | C26: 70734.024 | D26: 70734.024 | E26: 64050.921 | F26: КК из расчетника | G26: =B26 -> ЭЛЬМАШ | M26: ПАРКОВЫЙ | N26: =M26 -> ПАРКОВЫЙ | AC26: ЗАПРУДНЫЙ | AD26: Алт_Гальян_М-Кушва | AF26: Артемовский городской округ | AG26: 02:019:2:4:6 | AH26: Артемовский городской округ | AI26: 19458.838 | AJ26: 19458.838 | AK26: 18072.573 | AL26: =AF26 -> Артемовский городской округ
A27: 66:41:0303105 | B27: ВИЗ | C27: 84298.205 | D27: 84298.205 | E27: 76333.533 | F27: КК из расчетника | G27: =B27 -> ВИЗ | M27: ПИОНЕРСКИЙ | N27: =M27 -> ПИОНЕРСКИЙ | AC27: ВАЛЕГИН БОР | AD27: Сух_Г-Кам_Н_Кушва_Н-Черм | AF27: Артемовский городской округ | AG27: 02:020:2:5:6 | AH27: Артемовский городской округ | AI27: 19458.838 | AJ27: 19458.838 | AK27: 18072.573 | AL27: =AF27 -> Артемовский городской округ
A28: 66:41:0106023 | B28: УРАЛМАШ | C28: 70026.76 | D28: 70026.76 | E28: 63410.482 | F28: КК из расчетника | G28: =B28 -> УРАЛМАШ | M28: ПОЛЕВОДСТВО | N28: =M28 -> ПОЛЕВОДСТВО | AC28: Выя_Леб_Горб_Кр-Кам | AD28: Выя_Леб_Горб_Кр-Кам | AF28: Артемовский городской округ | AG28: 02:021:2:3:6 | AH28: Артемовский городской округ | AI28: 19458.838 | AJ28: 19458.838 | AK28: 18072.573 | AL28: =AF28 -> Артемовский городской округ
A29: 66:41:0501066 | B29: БОТАНИЧЕСКИЙ | C29: 77064.444 | D29: 77064.444 | E29: 69783.233 | F29: КК из расчетника | G29: =B29 -> БОТАНИЧЕСКИЙ | M29: ПТИЦЕФАБРИКА | N29: =M29 -> ПТИЦЕФАБРИКА | AC29: Верхне-Выйская плотина | AD29: Сух_Г-Кам_Н_Кушва_Н-Черм | AF29: Артемовский городской округ | AG29: 02:022:2:4:6 | AH29: Артемовский городской округ | AI29: 19458.838 | AJ29: 19458.838 | AK29: 18072.573 | AL29: =AF29 -> Артемовский городской округ
A30: 66:41:0504003 | B30: ЧЕРМЕТ | C30: 62652.94 | D30: 62652.94 | E30: 56733.356 | F30: КК из расчетника | G30: =B30 -> ЧЕРМЕТ | M30: РУДНЫЙ | N30: =M30 -> РУДНЫЙ | AC30: Пырловка | AD30: Сух_Г-Кам_Н_Кушва_Н-Черм | AF30: Артемовский городской округ | AG30: 02:023:2:4:6 | AH30: Артемовский городской округ | AI30: 19458.838 | AJ30: 19458.838 | AK30: 18072.573 | AL30: =AF30 -> Артемовский городской округ
A31: 66:41:0402001 | B31: АВТОВОКЗАЛ | C31: 83744.997 | D31: 83744.997 | E31: 75832.596 | F31: КК из расчетника | G31: =B31 -> АВТОВОКЗАЛ | M31: САДОВЫЙ | N31: =M31 -> САДОВЫЙ | AC31: Фотеево | AD31: Алт_Гальян_М-Кушва | AF31: Артемовский городской округ | AG31: 02:024:2:5:6 | AH31: Артемовский городской округ | AI31: 19458.838 | AJ31: 19458.838 | AK31: 18072.573 | AL31: =AF31 -> Артемовский городской округ
A32: 66:41:0106043 | B32: УРАЛМАШ | C32: 70026.76 | D32: 70026.76 | E32: 63410.482 | F32: КК из расчетника | G32: =B32 -> УРАЛМАШ | M32: СЕВЕРКА | N32: =M32 -> СЕВЕРКА | AF32: Артемовский городской округ | AG32: 02:025:2:4:6 | AH32: Артемовский городской округ | AI32: 19458.838 | AJ32: 19458.838 | AK32: 18072.573 | AL32: =AF32 -> Артемовский городской округ
A33: 66:41:0608017 | B33: ЛЕЧЕБНЫЙ | C33: 57793.084 | D33: 57793.084 | E33: 52332.664 | F33: КК из расчетника | G33: =B33 -> ЛЕЧЕБНЫЙ | M33: СЕМЬ КЛЮЧЕЙ | N33: Старая сортировка | AF33: Артемовский городской округ | AG33: 02:026:2:3:6 | AH33: Артемовский городской округ | AI33: 19458.838 | AJ33: 19458.838 | AK33: 18072.573 | AL33: =AF33 -> Артемовский городской округ
A34: 66:41:0519050 | B34: ГОРНЫЙ ЩИТ | C34: 52246.96 | D34: 52246.96 | E34: 47310.557 | F34: КК из расчетника | G34: =B34 -> ГОРНЫЙ ЩИТ | M34: СИБИРСКИЙ | N34: =M34 -> СИБИРСКИЙ | AF34: Артемовский городской округ | AG34: 02:028:2:4:6 | AH34: Артемовский городской округ | AI34: 19458.838 | AJ34: 19458.838 | AK34: 18072.573 | AL34: =AF34 -> Артемовский городской округ
A35: 66:41:0504030 | B35: ЧЕРМЕТ | C35: 62652.94 | D35: 62652.94 | E35: 56733.356 | F35: КК из расчетника | G35: =B35 -> ЧЕРМЕТ | M35: СИНИЕ КАМНИ | N35: =M35 -> СИНИЕ КАМНИ | AF35: Артинский городской округ | AG35: 03:000:0:0:0 | AH35: Артинский городской округ | AI35: 23004.363 | AJ35: 23004.363 | AK35: 21365.518 | AL35: =AF35 -> Артинский городской округ
A36: 66:41:0609022 | B36: КОМПРЕССОРНЫЙ | C36: 56392.544 | D36: 56392.544 | E36: 51064.462 | F36: КК из расчетника | G36: =B36 -> КОМПРЕССОРНЫЙ | M36: СОВХОЗ | N36: =M36 -> СОВХОЗ | AF36: Артинский городской округ | AG36: 03:001:2:4:6 | AH36: Артинский городской округ | AI36: 23004.363 | AJ36: 23004.363 | AK36: 21365.518 | AL36: =AF36 -> Артинский городской округ
A37: 66:41:0601011 | B37: Центр | C37: 93989.913 | D37: 93989.913 | E37: 85109.545 | F37: КК из расчетника | G37: =B37 -> Центр | M37: СОЛНЕЧНЫЙ | N37: =M37 -> СОЛНЕЧНЫЙ | AF37: Артинский городской округ | AG37: 03:002:2:5:6 | AH37: Артинский городской округ | AI37: 23004.363 | AJ37: 23004.363 | AK37: 21365.518 | AL37: =AF37 -> Артинский городской округ
A38: 66:41:0106156 | B38: УРАЛМАШ | C38: 70026.76 | D38: 70026.76 | E38: 63410.482 | F38: КК из расчетника | G38: =B38 -> УРАЛМАШ | M38: Старая сортировка | N38: =M38 -> Старая сортировка | AF38: Артинский городской округ | AG38: 03:003:1:2:4 | AH38: Артинский городской округ | AI38: 28422.422 | AJ38: 28422.422 | AK38: 26397.596 | AL38: =AF38 -> Артинский городской округ
A39: 66:41:0108114 | B39: ЭЛЬМАШ | C39: 70734.024 | D39: 70734.024 | E39: 64050.921 | F39: КК из расчетника | G39: =B39 -> ЭЛЬМАШ | M39: Сулим.Торфянник | N39: =M39 -> Сулим.Торфянник | AF39: Артинский городской округ | AG39: 03:004:2:5:6 | AH39: Артинский городской округ | AI39: 23004.363 | AJ39: 23004.363 | AK39: 21365.518 | AL39: =AF39 -> Артинский городской округ
A40: 66:41:0204055 | B40: Старая сортировка | C40: 59368.686 | D40: 59368.686 | E40: 53759.402 | F40: КК из расчетника | G40: =B40 -> Старая сортировка | M40: УКТУС | N40: =M40 -> УКТУС | AF40: Артинский городской округ | AG40: 03:005:2:5:6 | AH40: Артинский городской округ | AI40: 23004.363 | AJ40: 23004.363 | AK40: 21365.518 | AL40: =AF40 -> Артинский городской округ
A41: 66:41:0303004 | B41: ВИЗ | C41: 84298.205 | D41: 84298.205 | E41: 76333.533 | F41: КК из расчетника | G41: =B41 -> ВИЗ | M41: УНЦ | N41: =M41 -> УНЦ | AF41: Артинский городской округ | AG41: 03:006:2:5:6 | AH41: Артинский городской округ | AI41: 23004.363 | AJ41: 23004.363 | AK41: 21365.518 | AL41: =AF41 -> Артинский городской округ
A42: 66:41:0601007 | B42: Центр | C42: 93989.913 | D42: 93989.913 | E42: 85109.545 | F42: КК из расчетника | G42: =B42 -> Центр | M42: УРАЛМАШ | N42: =M42 -> УРАЛМАШ | AF42: Артинский городской округ | AG42: 03:007:2:5:6 | AH42: Артинский городской округ | AI42: 23004.363 | AJ42: 23004.363 | AK42: 21365.518 | AL42: =AF42 -> Артинский городской округ
A43: 66:41:0206032 | B43: Центр | C43: 93989.913 | D43: 93989.913 | E43: 85109.545 | F43: КК из расчетника | G43: =B43 -> Центр | M43: ХИММАШ | N43: =M43 -> ХИММАШ | AF43: Артинский городской округ | AG43: 03:008:2:5:6 | AH43: Артинский городской округ | AI43: 23004.363 | AJ43: 23004.363 | AK43: 21365.518 | AL43: =AF43 -> Артинский городской округ
A44: 66:41:0108035 | B44: ЭЛЬМАШ | C44: 70734.024 | D44: 70734.024 | E44: 64050.921 | F44: КК из расчетника | G44: =B44 -> ЭЛЬМАШ | M44: Центр | N44: =M44 -> Центр | AF44: Артинский городской округ | AG44: 03:009:2:4:6 | AH44: Артинский городской округ | AI44: 23004.363 | AJ44: 23004.363 | AK44: 21365.518 | AL44: =AF44 -> Артинский городской округ
A45: 66:41:0501056 | B45: АВТОВОКЗАЛ | C45: 83744.997 | D45: 83744.997 | E45: 75832.596 | F45: КК из расчетника | G45: =B45 -> АВТОВОКЗАЛ | M45: ЧЕРМЕТ | N45: =M45 -> ЧЕРМЕТ | AF45: Артинский городской округ | AG45: 03:010:2:5:6 | AH45: Артинский городской округ | AI45: 23004.363 | AJ45: 23004.363 | AK45: 21365.518 | AL45: =AF45 -> Артинский городской округ
... A53: 66:41:0204051 | B53: Новая сортировка | C53: 64914.8 | D53: 64914.8 | E53: 58781.519 | F53: КК из расчетника | G53: =B53 -> Новая сортировка | M53: Ю-З | N53: =M53 -> Ю-З | AF53: Артинский городской округ | AG53: 03:018:2:5:6 | AH53: Артинский городской округ | AI53: 23004.363 | AJ53: 23004.363 | AK53: 21365.518 | AL53: =AF53 -> Артинский городской округ
A54: 66:41:0603013 | B54: СИБИРСКИЙ | C54: 63556.28 | D54: 63556.28 | E54: 57551.353 | F54: КК из расчетника | G54: =B54 -> СИБИРСКИЙ | M54: Верхнемакарово | N54: Чусовское озеро | AF54: Артинский городской округ | AG54: 03:019:2:5:6 | AH54: Артинский городской округ | AI54: 23004.363 | AJ54: 23004.363 | AK54: 21365.518 | AL54: =AF54 -> Артинский городской округ
A55: 66:41:0204011 | B55: Старая сортировка | C55: 59368.686 | D55: 59368.686 | E55: 53759.402 | F55: КК из расчетника | G55: =B55 -> Старая сортировка | M55: Березит | N55: САДОВЫЙ | AF55: Артинский городской округ | AG55: 03:020:2:5:6 | AH55: Артинский городской округ | AI55: 23004.363 | AJ55: 23004.363 | AK55: 21365.518 | AL55: =AF55 -> Артинский городской округ
A56: 66:41:0601045 | B56: ПАРКОВЫЙ | C56: 81392.098 | D56: 81392.098 | E56: 73702.001 | F56: КК из расчетника | G56: =B56 -> ПАРКОВЫЙ | M56: Палкинский торфяник | N56: Северка | AF56: Артинский городской округ | AG56: 03:021:2:5:6 | AH56: Артинский городской округ | AI56: 23004.363 | AJ56: 23004.363 | AK56: 21365.518 | AL56: =AF56 -> Артинский городской округ
A57: 66:41:0204036 | B57: Новая сортировка | C57: 64914.8 | D57: 64914.8 | E57: 58781.519 | F57: КК из расчетника | G57: =B57 -> Новая сортировка | M57: Технопарк | N57: Исток | AF57: Артинский городской округ | AG57: 03:022:2:5:6 | AH57: Артинский городской округ | AI57: 23004.363 | AJ57: 23004.363 | AK57: 21365.518 | AL57: =AF57 -> Артинский городской округ
A58: 66:41:0304006 | B58: Ю-З | C58: 76630.28 | D58: 76630.28 | E58: 69390.089 | F58: КК из расчетника | G58: =B58 -> Ю-З | M58: Межселенная территория-зона 1 | N58: Центр | AF58: Артинский городской округ | AG58: 03:023:2:5:6 | AH58: Артинский городской округ | AI58: 23004.363 | AJ58: 23004.363 | AK58: 21365.518 | AL58: =AF58 -> Артинский городской округ
A59: 66:41:0509002 | B59: ХИММАШ | C59: 61980.679 | D59: 61980.679 | E59: 56124.616 | F59: КК из расчетника | G59: =B59 -> ХИММАШ | M59: Межселенная территория-зона 2 | N59: ВИЗ | AF59: Артинский городской округ | AG59: 03:024:2:5:6 | AH59: Артинский городской округ | AI59: 23004.363 | AJ59: 23004.363 | AK59: 21365.518 | AL59: =AF59 -> Артинский городской округ
A60: 66:41:0303066 | B60: ВИЗ | C60: 84298.205 | D60: 84298.205 | E60: 76333.533 | F60: КК из расчетника | G60: =B60 -> ВИЗ | M60: Межселенная территория-зона 3 | N60: Уралмаш | AF60: Артинский городской округ | AG60: 03:025:2:5:6 | AH60: Артинский городской округ | AI60: 23004.363 | AJ60: 23004.363 | AK60: 21365.518 | AL60: =AF60 -> Артинский городской округ
A61: 66:41:0704040 | B61: ВТУЗГОРОДОК | C61: 77071.443 | D61: 77071.443 | E61: 69789.571 | F61: КК из расчетника | G61: =B61 -> ВТУЗГОРОДОК | M61: Межселенная территория-зона 4 | N61: Старая сортировка | AF61: Артинский городской округ | AG61: 03:026:2:5:6 | AH61: Артинский городской округ | AI61: 23004.363 | AJ61: 23004.363 | AK61: 21365.518 | AL61: =AF61 -> Артинский городской округ
A62: 66:41:0604021 | B62: АВТОВОКЗАЛ | C62: 83744.997 | D62: 83744.997 | E62: 75832.596 | F62: КК из расчетника | G62: =B62 -> АВТОВОКЗАЛ | M62: 66:41:0202007 | N62: Семь ключей | AF62: Артинский городской округ | AG62: 03:027:2:4:6 | AH62: Артинский городской округ | AI62: 23004.363 | AJ62: 23004.363 | AK62: 21365.518 | AL62: =AF62 -> Артинский городской округ
A63: 66:41:0506003 | B63: ЕЛИЗАВЕТ | C63: 60958.295 | D63: 60958.295 | E63: 55198.825 | F63: КК из расчетника | G63: =B63 -> ЕЛИЗАВЕТ | M63: 66:41:0306106 | N63: Широкая Речка | AF63: Артинский городской округ | AG63: 03:028:2:5:6 | AH63: Артинский городской округ | AI63: 23004.363 | AJ63: 23004.363 | AK63: 21365.518 | AL63: =AF63 -> Артинский городской округ
A64: 66:41:0604007 | B64: АВТОВОКЗАЛ | C64: 83744.997 | D64: 83744.997 | E64: 75832.596 | F64: КК из расчетника | G64: =B64 -> АВТОВОКЗАЛ | M64: 66:41:0306901 | N64: Широкая Речка | AF64: Артинский городской округ | AG64: 03:029:2:4:6 | AH64: Артинский городской округ | AI64: 23004.363 | AJ64: 23004.363 | AK64: 21365.518 | AL64: =AF64 -> Артинский городской округ
A65: 66:41:0702049 | B65: ПИОНЕРСКИЙ | C65: 77743.704 | D65: 77743.704 | E65: 70398.311 | F65: КК из расчетника | G65: =B65 -> ПИОНЕРСКИЙ | M65: 66:41:0315004 | N65: Палникс | AF65: Артинский городской округ | AG65: 03:030:2:5:6 | AH65: Артинский городской округ | AI65: 23004.363 | AJ65: 23004.363 | AK65: 21365.518 | AL65: =AF65 -> Артинский городской округ
... A71: 66:41:0301010 | B71: Центр | C71: 93989.913 | D71: 93989.913 | E71: 85109.545 | F71: КК из расчетника | G71: =B71 -> Центр | M71: 66:41:0000000 | N71: АКАДЕМИЧЕСКИЙ | AF71: Артинский городской округ | AG71: 03:036:2:5:6 | AH71: Артинский городской округ | AI71: 23004.363 | AJ71: 23004.363 | AK71: 21365.518 | AL71: =AF71 -> Артинский городской округ
A72: 66:41:0304023 | B72: Ю-З | C72: 76630.28 | D72: 76630.28 | E72: 69390.089 | F72: КК из расчетника | G72: =B72 -> Ю-З | AF72: Артинский городской округ | AG72: 03:037:2:5:6 | AH72: Артинский городской округ | AI72: 23004.363 | AJ72: 23004.363 | AK72: 21365.518 | AL72: =AF72 -> Артинский городской округ
A73: 66:41:0505027 | B73: ЧЕРМЕТ | C73: 62652.94 | D73: 62652.94 | E73: 56733.356 | F73: КК из расчетника | G73: =B73 -> ЧЕРМЕТ | AF73: Артинский городской округ | AG73: 03:038:2:5:6 | AH73: Артинский городской округ | AI73: 23004.363 | AJ73: 23004.363 | AK73: 21365.518 | AL73: =AF73 -> Артинский городской округ
A74: 66:41:0704025 | B74: ВТУЗГОРОДОК | C74: 77071.443 | D74: 77071.443 | E74: 69789.571 | F74: КК из расчетника | G74: =B74 -> ВТУЗГОРОДОК | AF74: Артинский городской округ | AG74: 03:039:2:4:6 | AH74: Артинский городской округ | AI74: 23004.363 | AJ74: 23004.363 | AK74: 21365.518 | AL74: =AF74 -> Артинский городской округ
A75: 66:41:0106119 | B75: УРАЛМАШ | C75: 70026.76 | D75: 70026.76 | E75: 63410.482 | F75: КК из расчетника | G75: =B75 -> УРАЛМАШ | AF75: Артинский городской округ | AG75: 03:040:2:4:5 | AH75: Артинский городской округ | AI75: 23580.588 | AJ75: 23580.588 | AK75: 21900.693 | AL75: =AF75 -> Артинский городской округ
A76: 66:41:0504041 | B76: ЧЕРМЕТ | C76: 62652.94 | D76: 62652.94 | E76: 56733.356 | F76: КК из расчетника | G76: =B76 -> ЧЕРМЕТ | AF76: Артинский городской округ | AG76: 03:041:2:5:6 | AH76: Артинский городской округ | AI76: 23004.363 | AJ76: 23004.363 | AK76: 21365.518 | AL76: =AF76 -> Артинский городской округ
A77: 66:41:0504007 | B77: ЧЕРМЕТ | C77: 62652.94 | D77: 62652.94 | E77: 56733.356 | F77: КК из расчетника | G77: =B77 -> ЧЕРМЕТ | AF77: Артинский городской округ | AG77: 03:042:2:4:5 | AH77: Артинский городской округ | AI77: 23580.588 | AJ77: 23580.588 | AK77: 21900.693 | AL77: =AF77 -> Артинский городской округ
A78: 66:41:0313010 | B78: АКАДЕМИЧЕСКИЙ | C78: 61763.597 | D78: 61763.597 | E78: 55928.043 | F78: КК из расчетника | G78: =B78 -> АКАДЕМИЧЕСКИЙ | AF78: Артинский городской округ | AG78: 03:043:2:4:6 | AH78: Артинский городской округ | AI78: 23004.363 | AJ78: 23004.363 | AK78: 21365.518 | AL78: =AF78 -> Артинский городской округ
A79: 66:41:0402012 | B79: АВТОВОКЗАЛ | C79: 83744.997 | D79: 83744.997 | E79: 75832.596 | F79: КК из расчетника | G79: =B79 -> АВТОВОКЗАЛ | AF79: Артинский городской округ | AG79: 03:044:2:5:6 | AH79: Артинский городской округ | AI79: 23004.363 | AJ79: 23004.363 | AK79: 21365.518 | AL79: =AF79 -> Артинский городской округ
A80: 66:41:0502069 | B80: УКТУС | C80: 63640.312 | D80: 63640.312 | E80: 57627.447 | F80: КК из расчетника | G80: =B80 -> УКТУС | AF80: Артинский городской округ | AG80: 03:045:2:4:6 | AH80: Артинский городской округ | AI80: 23004.363 | AJ80: 23004.363 | AK80: 21365.518 | AL80: =AF80 -> Артинский городской округ
A81: 66:41:0106064 | B81: УРАЛМАШ | C81: 70026.76 | D81: 70026.76 | E81: 63410.482 | F81: КК из расчетника | G81: =B81 -> УРАЛМАШ | AF81: Артинский городской округ | AG81: 03:046:2:5:6 | AH81: Артинский городской округ | AI81: 23004.363 | AJ81: 23004.363 | AK81: 21365.518 | AL81: =AF81 -> Артинский городской округ
A82: 66:41:0306106 | B82: ШИРОКАЯ РЕЧКА | C82: 63178.134 | D82: 63178.134 | E82: 57208.931 | F82: КК из расчетника | G82: =B82 -> ШИРОКАЯ РЕЧКА | AF82: Артинский городской округ | AG82: 03:047:2:5:6 | AH82: Артинский городской округ | AI82: 23004.363 | AJ82: 23004.363 | AK82: 21365.518 | AL82: =AF82 -> Артинский городской округ
A83: 66:41:0516002 | B83: ЧУСОВСКОЕ ОЗЕРО | C83: 49782.025 | D83: 49782.025 | E83: 45078.507 | F83: КК из расчетника | G83: =B83 -> ЧУСОВСКОЕ ОЗЕРО | AF83: Артинский городской округ | AG83: 03:048:2:4:6 | AH83: Артинский городской округ | AI83: 23004.363 | AJ83: 23004.363 | AK83: 21365.518 | AL83: =AF83 -> Артинский городской округ
... A1528: 66:58:0108002 | B1528: Шайтанка | C1528: 34007.852 | D1528: 34007.852 | E1528: 30956.029 | F1528: КК из расчетника | G1528: =B1528 -> Шайтанка | AF1528: Слободо-Туринский муниципальный район | AG1528: 65:047:2:5:6 | AH1528: Слободо-Туринский муниципальный район | AI1528: 22738.943 | AJ1528: 22738.943 | AK1528: 21119.008 | AL1528: =AF1528 -> Слободо-Туринский муниципальный район
A1529: 66:58:0110003 | B1529: Шайтанка | C1529: 34007.852 | D1529: 34007.852 | E1529: 30956.029 | F1529: КК из расчетника | G1529: =B1529 -> Шайтанка | L1529: Ниже начинаются добавочные кварталы | AF1529: Слободо-Туринский муниципальный район | AG1529: 65:048:2:5:6 | AH1529: Слободо-Туринский муниципальный район | AI1529: 22738.943 | AJ1529: 22738.943 | AK1529: 21119.008 | AL1529: =AF1529 -> Слободо-Туринский муниципальный район
A1530: 66:58:2901002 | B1530: Шайтанка | C1530: 34007.852 | D1530: 34007.852 | E1530: 30956.029 | G1530: =B1530 -> Шайтанка | AF1530: Сосьвинский городской округ | AG1530: 66:000:0:0:0 | AH1530: Сосьвинский городской округ | AI1530: 13782.017 | AJ1530: 13782.017 | AK1530: 12800.178 | AL1530: =AF1530 -> Сосьвинский городской округ
A1531: 66:58:2901001 | B1531: Шайтанка | C1531: 34007.852 | D1531: 34007.852 | E1531: 30956.029 | G1531: =B1531 -> Шайтанка | AF1531: Сосьвинский городской округ | AG1531: 66:001:2:3:5 | AH1531: Сосьвинский городской округ | AI1531: 14127.236 | AJ1531: 14127.236 | AK1531: 13120.8 | AL1531: =AF1531 -> Сосьвинский городской округ
A1532: 66:58:2802001 | B1532: ДинСанПод | C1532: 36244.599 | D1532: 36244.599 | E1532: 32992.054 | G1532: =B1532 -> ДинСанПод | AF1532: Сосьвинский городской округ | AG1532: 66:002:2:5:6 | AH1532: Сосьвинский городской округ | AI1532: 13782.017 | AJ1532: 13782.017 | AK1532: 12800.178 | AL1532: =AF1532 -> Сосьвинский городской округ
A1533: 66:41:0101006 | B1533: САДОВЫЙ | C1533: 53262.346 | D1533: 53262.346 | E1533: 48230.01 | G1533: =B1533 -> САДОВЫЙ | AF1533: Сосьвинский городской округ | AG1533: 66:003:2:3:6 | AH1533: Сосьвинский городской округ | AI1533: 13782.017 | AJ1533: 13782.017 | AK1533: 12800.178 | AL1533: =AF1533 -> Сосьвинский городской округ
A1534: 66:58:2802005 | B1534: ДинСанПод | C1534: 36244.599 | D1534: 36244.599 | E1534: 32992.054 | G1534: =B1534 -> ДинСанПод | AF1534: Сосьвинский городской округ | AG1534: 66:004:2:5:6 | AH1534: Сосьвинский городской округ | AI1534: 13782.017 | AJ1534: 13782.017 | AK1534: 12800.178 | AL1534: =AF1534 -> Сосьвинский городской округ
A1535: 66:19:0101020 | B1535: 1003 | C1535: 21261.029 | D1535: 21261.029 | E1535: 20837.465 | G1535: =B1535 -> 1003 | AF1535: Сосьвинский городской округ | AG1535: 66:005:2:5:6 | AH1535: Сосьвинский городской округ | AI1535: 13782.017 | AJ1535: 13782.017 | AK1535: 12800.178 | AL1535: =AF1535 -> Сосьвинский городской округ
A1536: 66:19:1904004 | B1536: 1003 | C1536: 21261.029 | D1536: 21261.029 | E1536: 20837.465 | G1536: =B1536 -> 1003 | AF1536: Сосьвинский городской округ | AG1536: 66:006:2:4:6 | AH1536: Сосьвинский городской округ | AI1536: 13782.017 | AJ1536: 13782.017 | AK1536: 12800.178 | AL1536: =AF1536 -> Сосьвинский городской округ
A1537: 66:19:1905005 | B1537: 1003 | C1537: 21261.029 | D1537: 21261.029 | E1537: 20837.465 | G1537: =B1537 -> 1003 | AF1537: Сосьвинский городской округ | AG1537: 66:007:2:5:6 | AH1537: Сосьвинский городской округ | AI1537: 13782.017 | AJ1537: 13782.017 | AK1537: 12800.178 | AL1537: =AF1537 -> Сосьвинский городской округ
A1538: 66:58:2902008 | B1538: ДинСанПод | C1538: 36244.599 | D1538: 36244.599 | E1538: 32992.054 | G1538: =B1538 -> ДинСанПод | AF1538: Сосьвинский городской округ | AG1538: 66:008:2:5:6 | AH1538: Сосьвинский городской округ | AI1538: 13782.017 | AJ1538: 13782.017 | AK1538: 12800.178 | AL1538: =AF1538 -> Сосьвинский городской округ
A1539: 66:19:1905006 | B1539: 1003 | C1539: 21261.029 | D1539: 21261.029 | E1539: 20837.465 | G1539: =B1539 -> 1003 | AF1539: Сосьвинский городской округ | AG1539: 66:009:2:5:6 | AH1539: Сосьвинский городской округ | AI1539: 13782.017 | AJ1539: 13782.017 | AK1539: 12800.178 | AL1539: =AF1539 -> Сосьвинский городской округ
A1540: 66:58:2902016 | B1540: СОВХОЗ ПЕРВОУРАЛЬСКИЙ | C1540: 27332.119 | D1540: 27332.119 | E1540: 24879.375 | G1540: =B1540 -> СОВХОЗ ПЕРВОУРАЛЬСКИЙ | AF1540: Сосьвинский городской округ | AG1540: 66:010:2:5:6 | AH1540: Сосьвинский городской округ | AI1540: 13782.017 | AJ1540: 13782.017 | AK1540: 12800.178 | AL1540: =AF1540 -> Сосьвинский городской округ
A1541: 66:58:2902040 | B1541: СОВХОЗ ПЕРВОУРАЛЬСКИЙ | C1541: 27332.119 | D1541: 27332.119 | E1541: 24879.375 | G1541: =B1541 -> СОВХОЗ ПЕРВОУРАЛЬСКИЙ | AF1541: Сосьвинский городской округ | AG1541: 66:011:2:5:6 | AH1541: Сосьвинский городской округ | AI1541: 13782.017 | AJ1541: 13782.017 | AK1541: 12800.178 | AL1541: =AF1541 -> Сосьвинский городской округ
A1542: 66:58:2902032 | B1542: СОВХОЗ ПЕРВОУРАЛЬСКИЙ | C1542: 27332.119 | D1542: 27332.119 | E1542: 24879.375 | G1542: =B1542 -> СОВХОЗ ПЕРВОУРАЛЬСКИЙ | AF1542: Сосьвинский городской округ | AG1542: 66:012:2:5:6 | AH1542: Сосьвинский городской округ | AI1542: 13782.017 | AJ1542: 13782.017 | AK1542: 12800.178 | AL1542: =AF1542 -> Сосьвинский городской округ
A1543: 66:19:0101019 | B1543: 1003 | C1543: 21261.029 | D1543: 21261.029 | E1543: 20837.465 | G1543: =B1543 -> 1003 | AF1543: Сосьвинский городской округ | AG1543: 66:013:2:5:6 | AH1543: Сосьвинский городской округ | AI1543: 13782.017 | AJ1543: 13782.017 | AK1543: 12800.178 | AL1543: =AF1543 -> Сосьвинский городской округ
A1544: 66:19:1905007 | B1544: 1003 | C1544: 21261.029 | D1544: 21261.029 | E1544: 20837.465 | G1544: =B1544 -> 1003 | AF1544: Сосьвинский городской округ | AG1544: 66:014:2:4:6 | AH1544: Сосьвинский городской округ | AI1544: 13782.017 | AJ1544: 13782.017 | AK1544: 12800.178 | AL1544: =AF1544 -> Сосьвинский городской округ
A1545: 66:58:2902002 | B1545: Шайтанка | C1545: 34007.852 | D1545: 34007.852 | E1545: 30956.029 | G1545: =B1545 -> Шайтанка | AF1545: Сосьвинский городской округ | AG1545: 66:015:2:3:6 | AH1545: Сосьвинский городской округ | AI1545: 13782.017 | AJ1545: 13782.017 | AK1545: 12800.178 | AL1545: =AF1545 -> Сосьвинский городской округ
A1546: 66:58:2902057 | B1546: СОВХОЗ ПЕРВОУРАЛЬСКИЙ | C1546: 27332.119 | D1546: 27332.119 | E1546: 24879.375 | G1546: =B1546 -> СОВХОЗ ПЕРВОУРАЛЬСКИЙ | AF1546: Сосьвинский городской округ | AG1546: 66:016:2:3:6 | AH1546: Сосьвинский городской округ | AI1546: 13782.017 | AJ1546: 13782.017 | AK1546: 12800.178 | AL1546: =AF1546 -> Сосьвинский городской округ
A1547: 66:58:2902023 | B1547: Талица | C1547: 36808.582 | D1547: 36808.582 | E1547: 33505.429 | G1547: =B1547 -> Талица | AF1547: Сосьвинский городской округ | AG1547: 66:017:2:4:6 | AH1547: Сосьвинский городской округ | AI1547: 13782.017 | AJ1547: 13782.017 | AK1547: 12800.178 | AL1547: =AF1547 -> Сосьвинский городской округ
A1548: 66:58:2902021 | B1548: СОВХОЗ ПЕРВОУРАЛЬСКИЙ | C1548: 27332.119 | D1548: 27332.119 | E1548: 24879.375 | G1548: =B1548 -> СОВХОЗ ПЕРВОУРАЛЬСКИЙ | AF1548: Сосьвинский городской округ | AG1548: 66:018:1:2:4 | AH1548: Сосьвинский городской округ | AI1548: 17028.007 | AJ1548: 17028.007 | AK1548: 15814.914 | AL1548: =AF1548 -> Сосьвинский городской округ
A1549: 66:58:2902034 | B1549: СОВХОЗ ПЕРВОУРАЛЬСКИЙ | C1549: 27332.119 | D1549: 27332.119 | E1549: 24879.375 | G1549: =B1549 -> СОВХОЗ ПЕРВОУРАЛЬСКИЙ | AF1549: Сосьвинский городской округ | AG1549: 66:019:2:3:6 | AH1549: Сосьвинский городской округ | AI1549: 13782.017 | AJ1549: 13782.017 | AK1549: 12800.178 | AL1549: =AF1549 -> Сосьвинский городской округ
A1550: 66:58:2902039 | B1550: СОВХОЗ ПЕРВОУРАЛЬСКИЙ | C1550: 27332.119 | D1550: 27332.119 | E1550: 24879.375 | G1550: =B1550 -> СОВХОЗ ПЕРВОУРАЛЬСКИЙ | AF1550: Сосьвинский городской округ | AG1550: 66:020:2:5:6 | AH1550: Сосьвинский городской округ | AI1550: 13782.017 | AJ1550: 13782.017 | AK1550: 12800.178 | AL1550: =AF1550 -> Сосьвинский городской округ
A1551: 66:58:2901012 | B1551: Шайтанка | C1551: 34007.852 | D1551: 34007.852 | E1551: 30956.029 | G1551: =B1551 -> Шайтанка | AF1551: Сосьвинский городской округ | AG1551: 66:021:2:5:6 | AH1551: Сосьвинский городской округ | AI1551: 13782.017 | AJ1551: 13782.017 | AK1551: 12800.178 | AL1551: =AF1551 -> Сосьвинский городской округ
A1552: 66:58:2803019 | B1552: ДинСанПод | C1552: 36244.599 | D1552: 36244.599 | E1552: 32992.054 | G1552: =B1552 -> ДинСанПод | AF1552: Сосьвинский городской округ | AG1552: 66:022:2:5:6 | AH1552: Сосьвинский городской округ | AI1552: 13782.017 | AJ1552: 13782.017 | AK1552: 12800.178 | AL1552: =AF1552 -> Сосьвинский городской округ
A1553: 66:58:2902037 | B1553: СОВХОЗ ПЕРВОУРАЛЬСКИЙ | C1553: 27332.119 | D1553: 27332.119 | E1553: 24879.375 | G1553: =B1553 -> СОВХОЗ ПЕРВОУРАЛЬСКИЙ | AF1553: Сосьвинский городской округ | AG1553: 66:023:2:5:6 | AH1553: Сосьвинский городской округ | AI1553: 13782.017 | AJ1553: 13782.017 | AK1553: 12800.178 | AL1553: =AF1553 -> Сосьвинский городской округ
A1554: 66:58:2902047 | B1554: СОВХОЗ ПЕРВОУРАЛЬСКИЙ | C1554: 27332.119 | D1554: 27332.119 | E1554: 24879.375 | G1554: =B1554 -> СОВХОЗ ПЕРВОУРАЛЬСКИЙ | AF1554: Сосьвинский городской округ | AG1554: 66:024:2:3:6 | AH1554: Сосьвинский городской округ | AI1554: 13782.017 | AJ1554: 13782.017 | AK1554: 12800.178 | AL1554: =AF1554 -> Сосьвинский городской округ
A1555: 66:58:2902046 | B1555: СОВХОЗ ПЕРВОУРАЛЬСКИЙ | C1555: 27332.119 | D1555: 27332.119 | E1555: 24879.375 | G1555: =B1555 -> СОВХОЗ ПЕРВОУРАЛЬСКИЙ | AF1555: Сысертский городской округ | AG1555: 67:000:0:0:0 | AH1555: Сысертский городской округ | AI1555: 36346.662 | AJ1555: 36346.662 | AK1555: 33757.306 | AL1555: =AF1555 -> Сысертский городской округ
A1556: 66:19:0101006 | B1556: п.Чащино | C1556: 21261.029 | D1556: 21261.029 | E1556: 20837.465 | G1556: =B1556 -> п.Чащино | AF1556: Сысертский городской округ | AG1556: 67:001:2:4:6 | AH1556: Сысертский городской округ | AI1556: 36346.662 | AJ1556: 36346.662 | AK1556: 33757.306 | AL1556: =AF1556 -> Сысертский городской округ
...
