Workbook

Sheet Земельные участки
A1: Идентификатор | B1: Кадастровый номер | C1: Номер кадастрового квартала | D1: Площадь (ЦФ) | E1: Категория земель (ЦФ) | F1: Расстояние до административного центра МО (ЦФ) | G1: Вид разрешённого использования (ЦФ) | H1: Газоснабжение (ЦФ) | I1: Электроснабжение (ЦФ) | J1: Водоотведение (ЦФ) | K1: Водоснабжение (ЦФ) | L1: Код МО (ЦФ) | M1: Зона влияния для ИЖС (ЦФ) | N1: ЛЭП над участком (ЦФ) | O1: Зона вляния для ИЖС | P1: Удельный показатель кадастровой стоимости(руб/м2) | Q1: Кадастровая стоимость (руб) | R1: Кадастровая стоимость описание вых | S1: Площадь в квадратных метрах | T1: Категория земель | U1: Расстояние до центра МО | V1: Наличие газоснабжения | W1: Наличие электроснабжения | X1: Наличие водоотведения | Y1: Наличие водоснабжения | Z1: Номер заявления | AA1: Тип заявления | AB1: Статус заявления | AC1: Код Муниципального образования | AD1: флажок | AE1: Дата пакета | AF1: Статус расчета | AG1: Дата комиссии | AH1: Решение комиссии | AI1: Флаг ВРИ по документу | AJ1: Флаг площади | AK1: Флаг ВРИ старый спр | AL1: Флаг ВРИ новый спр | AM1: Флаг Категории ЗУ | AN1: Группа для XML | AO1: ВРИ по документу старое | AP1: Код расчета вида использования текущий (старый) | AQ1: ВРИ по документу новое | AR1: Код расчета вида использования новый | AS1: Правило для ВРИ | AT1: Новая модель | AU1: Особый контроль | AV1: Суд | AW1: Дата заседания | AX1: Повтор предыдущего расчета | BY1: loc_factor_804 | CA1: loc_factor_822 | CC1: loc_factor_828 | CE1: loc_factor_803 | CG1: loc_factor_812 | CH1: loc_factor_8121 | CI1: loc_factor_817 | CK1: loc_factor_825 | CM1: loc_factor_807 | CN1: loc_factor_8071 | CO1: loc_factor_826 | CQ1: loc_factor_827 | CS1: Specific_CadastralCost | CT1: CadastralCost | CU1: CadastralCostDesc | CV1: id_group | CW1: Status_kc | CX1: loc_VICode | CY1: Segment | CZ1: loc_SgCode | DA1: loc_GroupName | DB1: Old_Utlbydoc | DD1: Текущий диапазон УПКС от 8 руб. до 1069 руб. | DK1: Возможно изменение кода расчета, но при этом ЦФ может не меняться, например: 02:010 стал 02:011 - все ИЖС
A2: ID | B2: CadastralNumber | C2: CadastralBlock | D2: loc_factor_807 | E2: loc_factor_817 | F2: loc_factor_812 | G2: loc_factor_825 | H2: loc_factor_822 | I2: loc_factor_804 | J2: loc_factor_803 | K2: loc_factor_828 | L2: loc_factor_830 | M2: loc_factor_826 | N2: loc_factor_829 | O2: InfluenceZone_IGS | P2: Specific_CadastralCost | Q2: CadastralCost | R2: CadastralCostDesc | S2: Area | T2: ParcelCategory | U2: DistanceToCMO | V2: PresenceGas | W2: PresencePower | X2: PresenceWaterDisposal | Y2: PresenceWaterSupply | Z2: Statement | AA2: Type_Statement | AB2: Status_Statement | AC2: KodMO | AD2: Sp_flag | AE2: inputpacket_date | AF2: Status_kc | AG2: Date_comm | AH2: Sol_comm | AI2: Flag_VRI | AJ2: FlagParam | AK2: Flag_VRIoldspr | AL2: Flag_VRInewspr | AM2: Flag_Category | AN2: ID_Group | AO2: Old_Utlbydoc | AP2: loc_VICode | AQ2: UtilizationByDoc | AR2: VRICode_NEW | AS2: PraviloVRI | AT2: New_id_group | AU2: ControlSP | AV2: Court | AW2: Date_Court | AX2: Константа | AY2: Электроснабжение | AZ2: Поправка на электроснабжение | BA2: Газоснабжение | BB2: Поправка на газоснабжение | BC2: Водоснабжение | BD2: Поправка на вобоснабжение | BE2: Водоотведение | BF2: Поправка на вдоотведение | BG2: Расстояние до Нижнего Тагила | BH2: Поправка на расстояние до Нижнего Тагила | BI2: Категория земель | BJ2: Поправка на категорию земель | BK2: ВРИ | BL2: Поправка на ВРИ | BM2: Поправка на площадь | BN2: Зона влияния Нижнего Тагила | BO2: Поправка на зону влияния Нижнего Тагила | BP2: Уторгование | BQ2: Поправка на уторгование | BR2: УПС | BS2: Итоговое | BT2: id_group | BU2: Обязательная проверка | BW2: Кадастровый номер | BX2: Константа | BY2: Электроснабжение | BZ2: Поправка на электроснабжение | CA2: Газоснабжение | CB2: Поправка на газоснабжение | CC2: Водоснабжение | CD2: Поправка на вобоснабжение | CE2: Водоотведение | CF2: Поправка на вдоотведение | CG2: Расстояние до Нижнего Тагила | CH2: Поправка на расстояние до Нижнего Тагила | CI2: Категория земель | CJ2: Поправка на категорию земель | CK2: ВРИ | CL2: Поправка на ВРИ | CM2: Площадь в квадратных метрах | CN2: Поправка на площадь | CO2: Зона влияния Нижнего Тагила | CP2: Поправка на зону влияния Нижнего Тагила | CQ2: Уторгование | CR2: Поправка на уторгование | CS2: УПС | CT2: Общая стоимость | CU2: Идентификатор стоимости | CV2: номер группы | CW2: Статус расчета | CX2: ВРИ | CY2: Сегмент | CZ2: Код сегменгта | DA2: Расшифровка расчетной подгруппы | DB2: ВРИ по документу старое (формирование или обновление поля) | DC2: Сравнение расчета с предыдущим расчетом | DD2: Проверка отклонения УПКС от текущего диапазона и контроль значительного изменения КС | DE2: Код МО | DF2: Электроснабжение | DG2: Газоснабжение | DH2: Площадь | DI2: Расстояние до административного центра МО | DJ2: Категория земель | DK2: Ценовой фактор ВРИ в модели | DL2: Изменение Кода расчета | DM2: Водоснабжение | DN2: Водоотведение | DO2: Зона влияния Нижнего Тагила (ИЖС)
A3: Parcels | B3: Parcels | C3: Parcels | D3: Parcels | E3: Parcels | F3: Parcels | G3: Parcels | H3: Parcels | I3: Parcels | J3: Parcels | K3: Parcels | L3: Parcels | M3: Parcels | N3: Parcels | O3: Parcels | P3: Parcels | Q3: Parcels | R3: Parcels | S3: Parcels | T3: Parcels | U3: Parcels | V3: Parcels | W3: Parcels | X3: Parcels | Y3: Parcels | Z3: Parcels | AA3: Parcels | AB3: Parcels | AC3: Parcels | AD3: Parcels | AE3: Parcels | AF3: Parcels | AG3: Parcels | AH3: Parcels | AI3: Parcels | AJ3: Parcels | AK3: Parcels | AL3: Parcels | AM3: Parcels | AN3: Parcels | AO3: Parcels | AP3: Parcels | AQ3: Parcels | AR3: Parcels | AS3: Parcels | AT3: Parcels | AU3: Parcels | AV3: Parcels | AW3: Parcels | BU3: Вверно, если расходждение составляет 0,00 руб. Если расхождение составляет более 0,01 -ценовые факторы подобраны неверно. Требуется анализ | BV3: Участие объекта на комиссии, в заявлениях, в судах и прочее
AX4: =Поправки!$G$4 -> 509.3919 | AY4: =I4 -> 0 | AZ4: =VLOOKUP(AY4,Поправки!$F$5:$G$6,2,0) -> #N/A | BA4: =H4 -> 0 | BB4: =VLOOKUP(BA4,Поправки!$F$7:$G$10,2,0) -> #N/A | BC4: =K4 -> 0 | BD4: =VLOOKUP(BC4,Поправки!$F$11:$G$13,2,0) -> #N/A | BE4: =J4 -> 0 | BF4: =VLOOKUP(BE4,Поправки!$F$14:$G$16,2,0) -> #N/A | BG4: =F4 -> 0 | BH4: =ROUND(EXP(0.713742903251*(9.03038414-2.63139367*LN(IF(BG4<4,4,BG4))+0.82725877*LN(IF(BG4<4,4,BG4))^2-0.11025986*LN(IF(BG4<4,4,BG4))^3))/EXP(0.713742903251*(9.03038414-2.63139367*LN(5)+0.82725877*LN(5)^2-0.11025986*LN(5)^3)),4) -> 1.1535 | BI4: =E4 -> 0 | BJ4: =VLOOKUP(BI4,Поправки!$F$18:$G$20,2,0) -> #N/A | BK4: =G4 -> 0 | BL4: =VLOOKUP(BK4,Поправки!$F$21:$G$29,2,0) -> #N/A | BM4: =ROUND(EXP(0.266642520892*(15.0191281-1.312096*LN(IF(D4<600,600,D4))))/EXP(0.266642520892*(15.0191281-1.312096*LN(1000))),4) -> 1.1957 | BN4: =M4 -> 0 | BO4: =VLOOKUP(BN4,Поправки!$F$31:$G$32,2,0) -> #N/A | BP4: Наличие уторгования | BQ4: =VLOOKUP(BP4,Поправки!$F$33:$G$34,2,0) -> 0.91 | BR4: =ROUND(AX4*AZ4*BB4*BD4*BF4*BH4*BJ4*BL4*BM4*BO4*BQ4,2) -> #N/A | BS4: =ROUND(BR4*D4,2) -> #N/A | BT4: =8015 -> 8015 | BU4: =IF(P4="","Новый объект",IF(AT4=AN4,BS4-Q4,"Объект пришел из другой модели")) -> Новый объект | BV4: =IF(AU4="",IF(AG4<>"","ОСПАРИВАНИЕ",IF(AV4<>"","СУД",IF(Z4="","",Z4))),AU4) | BW4: =B4 -> 0 | BX4: =Поправки!$G$4 -> 509.3919 | BY4: =IF(P4="","Наличие электроснабжения",IF(I4="",IF(W4="отсутствие","Отсутствие электроснабжения","Наличие электроснабжения"),I4)) -> Наличие электроснабжения | BZ4: =VLOOKUP(BY4,Поправки!$F$5:$G$6,2,0) -> 1 | CA4: =IF(P4="","Отсутствие газоснабжения",IF(H4="",IF(V4="наличие","Наличие газоснабжения","Отсутствие газоснабжения"),H4)) -> Отсутствие газоснабжения | CB4: =VLOOKUP(CA4,Поправки!$F$7:$G$10,2,0) -> 1 | CC4: Отсутствие водоснабжения | CD4: =VLOOKUP(CC4,Поправки!$F$11:$G$13,2,0) -> 1 | CE4: Отсутствие водоотведения | CF4: =VLOOKUP(CE4,Поправки!$F$14:$G$16,2,0) -> 1 | CG4: =IF(F4="",IF(U4="",VLOOKUP(AC4,Поправки!$G$37:$H$38,2,0),U4),F4) -> #N/A | CH4: =ROUND(EXP(0.713742903251*(9.03038414-2.63139367*LN(IF(CG4<4,4,CG4))+0.82725877*LN(IF(CG4<4,4,CG4))^2-0.11025986*LN(IF(CG4<4,4,CG4))^3))/EXP(0.713742903251*(9.03038414-2.63139367*LN(5)+0.82725877*LN(5)^2-0.11025986*LN(5)^3)),4) -> #N/A | CI4: =IF(T4="Земли населенных пунктов",Поправки!$F$18,Поправки!$F$19) -> Прочие | CJ4: =VLOOKUP(CI4,Поправки!$F$18:$G$20,2,0) -> 0.8419 | CK4: =IF(AR4="13:031",Поправки!$F$29,Поправки!$F$21) -> ИЖС | CL4: =VLOOKUP(CK4,Поправки!$F$21:$G$29,2,0) -> 1 | CM4: =S4 -> 0 | CN4: =ROUND(EXP(0.266642520892*(15.0191281-1.312096*LN(IF(CM4<600,600,CM4))))/EXP(0.266642520892*(15.0191281-1.312096*LN(1000))),4) -> 1.1957 | CO4: =IF(M4="",IF(O4="Влияние Нижнего Тагила","Наличие влияния Нижнего Тагила","Отсутствие влияния Нижнего Тагила"),IF(M4="Наличие влияния Нижнего Тагила","Наличие влияния Нижнего Тагила","Отсутствие влияния Нижнего Тагила")) -> Отсутствие влияния Нижнего Тагила | CP4: =VLOOKUP(CO4,Поправки!$F$31:$G$32,2,0) -> 1 | CQ4: Наличие уторгования | CR4: =VLOOKUP(CQ4,Поправки!$F$33:$G$34,2,0) -> 0.91 | CS4: =ROUND(BX4*BZ4*CB4*CD4*CF4*CH4*CJ4*CL4*CN4*CP4*CR4,2) -> #N/A | CT4: =ROUND(CS4*S4,2) -> #N/A | CU4: СТ16_Ф1_М15_18052021_Бунаков | CV4: =8015 -> 8015 | CW4: =IF(OR(CT4<0,CT4=0),"ОТРИЦАТЕЛЬНАЯ СТОИМОСТЬ",IF(DC4=0,"Пересчет не требуется","Готов")) -> #N/A | CX4: =AR4 -> 0 | CY4: 13. СЕГМЕНТ "Садоводство и огородничество, малоэтажная жилая застройка" | CZ4: =13 -> 13 | DA4: =VLOOKUP(CX4,'справочник ври'!$A$3:$B$271,2,0) -> #N/A | DB4: =AQ4 -> 0 | DC4: =IF(ISBLANK(P4),"Новый объект",IF(CV4=AN4,ABS(CT4-Q4),"Объект из другой модели")) -> Новый объект | DD4: =IF(OR(DC4="Объект из другой модели",DC4="Новый объект"),IF(OR(CS4<8,CS4>1070),"Отклонение УПКС","УПКС находится в допустимом интервале"),IF(DC4>1000000,"Внимение!Изменение более 1 млн","Изменение менее 1 млн")) -> #N/A | DE4: =IF(L4="","Новое значение",IF(L4=AC4,"Осталось предыдущее значение ЦФ","ИЗМЕНЕНИЕ")) -> Новое значение | DF4: =IF(I4="","Новое значение",IF(BY4=I4,"Осталось предыдущее значение ЦФ","ИЗМЕНЕНИЕ")) -> Новое значение | DG4: =IF(H4="","Новое значение",IF(CA4=H4,"Осталось предыдущее значение ЦФ","ИЗМЕНЕНИЕ")) -> Новое значение | DH4: =IF(P4="","Объект новый",IF(AJ4="не готов","ИЗМЕНЕНИЕ","Осталось предыдущее значение ЦФ")) -> Объект новый | DI4: =IF(F4="","Новое значение",IF(CG4=F4,"Осталось предыдущее значение ЦФ","ИЗМЕНЕНИЕ")) -> Новое значение | DJ4: =IF(E4="","Новое значение",IF(CI4=E4,"Осталось предыдущее значение ЦФ","ИЗМЕНЕНИЕ")) -> Новое значение | DK4: =IF(G4="","Новое значение",IF(CK4=G4,"Осталось предыдущее значение ЦФ","ИЗМЕНЕНИЕ")) -> Новое значение | DL4: =IF(AP4="","Новое значение",IF(AP4=AR4,"Осталось предыдущее значение ЦФ","ИЗМЕНЕНИЕ")) -> Новое значение | DM4: =IF(K4="","Новое значение",IF(CC4=K4,"Осталось предыдущее значение ЦФ","ИЗМЕНЕНИЕ")) -> Новое значение | DN4: =IF(J4="","Новое значение",IF(CE4=J4,"Осталось предыдущее значение ЦФ","ИЗМЕНЕНИЕ")) -> Новое значение | DO4: =IF(M4="","Новое значение",IF(CO4=M4,"Осталось предыдущее значение ЦФ","ИЗМЕНЕНИЕ")) -> Новое значение
AX5: =Поправки!$G$4 -> 509.3919 | AY5: =I5 -> 0 | AZ5: =VLOOKUP(AY5,Поправки!$F$5:$G$6,2,0) -> #N/A | BA5: =H5 -> 0 | BB5: =VLOOKUP(BA5,Поправки!$F$7:$G$10,2,0) -> #N/A | BC5: =K5 -> 0 | BD5: =VLOOKUP(BC5,Поправки!$F$11:$G$13,2,0) -> #N/A | BE5: =J5 -> 0 | BF5: =VLOOKUP(BE5,Поправки!$F$14:$G$16,2,0) -> #N/A | BG5: =F5 -> 0 | BH5: =ROUND(EXP(0.713742903251*(9.03038414-2.63139367*LN(IF(BG5<4,4,BG5))+0.82725877*LN(IF(BG5<4,4,BG5))^2-0.11025986*LN(IF(BG5<4,4,BG5))^3))/EXP(0.713742903251*(9.03038414-2.63139367*LN(5)+0.82725877*LN(5)^2-0.11025986*LN(5)^3)),4) -> 1.1535 | BI5: =E5 -> 0 | BJ5: =VLOOKUP(BI5,Поправки!$F$18:$G$20,2,0) -> #N/A | BK5: =G5 -> 0 | BL5: =VLOOKUP(BK5,Поправки!$F$21:$G$29,2,0) -> #N/A | BM5: =ROUND(EXP(0.266642520892*(15.0191281-1.312096*LN(IF(D5<600,600,D5))))/EXP(0.266642520892*(15.0191281-1.312096*LN(1000))),4) -> 1.1957 | BN5: =M5 -> 0 | BO5: =VLOOKUP(BN5,Поправки!$F$31:$G$32,2,0) -> #N/A | BP5: Наличие уторгования | BQ5: =VLOOKUP(BP5,Поправки!$F$33:$G$34,2,0) -> 0.91 | BR5: =ROUND(AX5*AZ5*BB5*BD5*BF5*BH5*BJ5*BL5*BM5*BO5*BQ5,2) -> #N/A | BS5: =ROUND(BR5*D5,2) -> #N/A | BT5: =8015 -> 8015 | BU5: =IF(P5="","Новый объект",IF(AT5=AN5,BS5-Q5,"Объект пришел из другой модели")) -> Новый объект | BV5: =IF(AU5="",IF(AG5<>"","ОСПАРИВАНИЕ",IF(AV5<>"","СУД",IF(Z5="","",Z5))),AU5) | BW5: =B5 -> 0 | BX5: =Поправки!$G$4 -> 509.3919 | BY5: =IF(P5="","Наличие электроснабжения",IF(I5="",IF(W5="отсутствие","Отсутствие электроснабжения","Наличие электроснабжения"),I5)) -> Наличие электроснабжения | BZ5: =VLOOKUP(BY5,Поправки!$F$5:$G$6,2,0) -> 1 | CA5: =IF(P5="","Отсутствие газоснабжения",IF(H5="",IF(V5="наличие","Наличие газоснабжения","Отсутствие газоснабжения"),H5)) -> Отсутствие газоснабжения | CB5: =VLOOKUP(CA5,Поправки!$F$7:$G$10,2,0) -> 1 | CC5: Отсутствие водоснабжения | CD5: =VLOOKUP(CC5,Поправки!$F$11:$G$13,2,0) -> 1 | CE5: Отсутствие водоотведения | CF5: =VLOOKUP(CE5,Поправки!$F$14:$G$16,2,0) -> 1 | CG5: =IF(F5="",IF(U5="",VLOOKUP(AC5,Поправки!$G$37:$H$38,2,0),U5),F5) -> #N/A | CH5: =ROUND(EXP(0.713742903251*(9.03038414-2.63139367*LN(IF(CG5<4,4,CG5))+0.82725877*LN(IF(CG5<4,4,CG5))^2-0.11025986*LN(IF(CG5<4,4,CG5))^3))/EXP(0.713742903251*(9.03038414-2.63139367*LN(5)+0.82725877*LN(5)^2-0.11025986*LN(5)^3)),4) -> #N/A | CI5: =IF(T5="Земли населенных пунктов",Поправки!$F$18,Поправки!$F$19) -> Прочие | CJ5: =VLOOKUP(CI5,Поправки!$F$18:$G$20,2,0) -> 0.8419 | CK5: =IF(AR5="13:031",Поправки!$F$29,Поправки!$F$21) -> ИЖС | CL5: =VLOOKUP(CK5,Поправки!$F$21:$G$29,2,0) -> 1 | CM5: =S5 -> 0 | CN5: =ROUND(EXP(0.266642520892*(15.0191281-1.312096*LN(IF(CM5<600,600,CM5))))/EXP(0.266642520892*(15.0191281-1.312096*LN(1000))),4) -> 1.1957 | CO5: =IF(M5="",IF(O5="Влияние Нижнего Тагила","Наличие влияния Нижнего Тагила","Отсутствие влияния Нижнего Тагила"),IF(M5="Наличие влияния Нижнего Тагила","Наличие влияния Нижнего Тагила","Отсутствие влияния Нижнего Тагила")) -> Отсутствие влияния Нижнего Тагила | CP5: =VLOOKUP(CO5,Поправки!$F$31:$G$32,2,0) -> 1 | CQ5: Наличие уторгования | CR5: =VLOOKUP(CQ5,Поправки!$F$33:$G$34,2,0) -> 0.91 | CS5: =ROUND(BX5*BZ5*CB5*CD5*CF5*CH5*CJ5*CL5*CN5*CP5*CR5,2) -> #N/A | CT5: =ROUND(CS5*S5,2) -> #N/A | CU5: СТ16_Ф1_М15_18052021_Бунаков | CV5: =8015 -> 8015 | CW5: =IF(OR(CT5<0,CT5=0),"ОТРИЦАТЕЛЬНАЯ СТОИМОСТЬ",IF(DC5=0,"Пересчет не требуется","Готов")) -> #N/A | CX5: =AR5 -> 0 | CY5: 13. СЕГМЕНТ "Садоводство и огородничество, малоэтажная жилая застройка" | CZ5: =13 -> 13 | DA5: =VLOOKUP(CX5,'справочник ври'!$A$3:$B$271,2,0) -> #N/A | DB5: =AQ5 -> 0 | DC5: =IF(ISBLANK(P5),"Новый объект",IF(CV5=AN5,ABS(CT5-Q5),"Объект из другой модели")) -> Новый объект | DD5: =IF(OR(DC5="Объект из другой модели",DC5="Новый объект"),IF(OR(CS5<8,CS5>1070),"Отклонение УПКС","УПКС находится в допустимом интервале"),IF(DC5>1000000,"Внимение!Изменение более 1 млн","Изменение менее 1 млн")) -> #N/A | DE5: =IF(L5="","Новое значение",IF(L5=AC5,"Осталось предыдущее значение ЦФ","ИЗМЕНЕНИЕ")) -> Новое значение | DF5: =IF(I5="","Новое значение",IF(BY5=I5,"Осталось предыдущее значение ЦФ","ИЗМЕНЕНИЕ")) -> Новое значение | DG5: =IF(H5="","Новое значение",IF(CA5=H5,"Осталось предыдущее значение ЦФ","ИЗМЕНЕНИЕ")) -> Новое значение | DH5: =IF(P5="","Объект новый",IF(AJ5="не готов","ИЗМЕНЕНИЕ","Осталось предыдущее значение ЦФ")) -> Объект новый | DI5: =IF(F5="","Новое значение",IF(CG5=F5,"Осталось предыдущее значение ЦФ","ИЗМЕНЕНИЕ")) -> Новое значение | DJ5: =IF(E5="","Новое значение",IF(CI5=E5,"Осталось предыдущее значение ЦФ","ИЗМЕНЕНИЕ")) -> Новое значение | DK5: =IF(G5="","Новое значение",IF(CK5=G5,"Осталось предыдущее значение ЦФ","ИЗМЕНЕНИЕ")) -> Новое значение | DL5: =IF(AP5="","Новое значение",IF(AP5=AR5,"Осталось предыдущее значение ЦФ","ИЗМЕНЕНИЕ")) -> Новое значение | DM5: =IF(K5="","Новое значение",IF(CC5=K5,"Осталось предыдущее значение ЦФ","ИЗМЕНЕНИЕ")) -> Новое значение | DN5: =IF(J5="","Новое значение",IF(CE5=J5,"Осталось предыдущее значение ЦФ","ИЗМЕНЕНИЕ")) -> Новое значение | DO5: =IF(M5="","Новое значение",IF(CO5=M5,"Осталось предыдущее значение ЦФ","ИЗМЕНЕНИЕ")) -> Новое значение
A6: Select ID,Source_ID,CadastralNumber,DateCreated,CadastralBlock,Name,ObjectType,Area,AreaUnit,AreaInaccuracy,LocationinBounds,LocationPlaced,ElaborationReferenceMark,ElaborationDistance,ElaborationDirection,AddressOrLocation,FIAS,OKATO,KLADR,OKTMO,PostalCode,AddressRF,Region,DistrictName,DistrictType,CityName,CityType,UrbanDistrictName,UrbanDistrictType,SovietVillageName,SovietVillageType,LocalityName,LocalityType,PlanningElementName,PlanningElementType,StreetName,StreetType,Level1Type,Level1Value,Level2Type,Level2Value,Level3Type,Level3Value,ApartmentType,ApartmentValue,AddressOther,AddressNote,ParcelCategory,Utilization,UtilizationByDoc,UtilizationLandUse,UtilizationТхт,CostValue,CostUnit,CostDateValuation,CostDateEntering,CostDateApproval,CostDocNumber,CostDocDate,CostApplicationDate,CostRevisalStatementDate,CostApplicationLastDate,CostDocName,FacilityKN,FacilityKNPurpose,SurveyProjectNum,DecisionCodeDocument,DecisionName,DecisionSeries,DecisionNumber,DecisionDate,DecisionIssueOrgan,DecisionDesc,HiredHouseUse,HouseActBuilding,HouseActDevelopment,BuildingContractName,DevelopContractName,OwnerDecision,SupportContractName,CodeDocument,DocHiredHouseName,DocHiredHouseSeries,DocHiredHouseNumber,DocHiredHouseDate,DocHiredHouseIssueOrgan,DocHiredHouseDesc,LimitedRightNumber,CREATEOPERATORNAME,CREATEDATE,OPERATORNAME,MODIFYDATE,MI_STYLE,Specific_CadastralCost,CadastralCost,CadastralCostDesc,MO_Name,ID_Group,LocalityCode,locTypeUse2,loc_VICode,loc_GroupName,loc_VRICode,Sourse_loc_VICode,locTypeUse,inputpacket_id,loc_SgCode,VIP_Sp,Quant_Kontur,Quant_Point,Sum_Square,Sum_Perim,Proc_Diff_Square,Pr_Diff,Source_Sum_Square,SourceLocalityCode,Upload_Scroll,Date_KC,Segment,FlagLocalityCode,DistanceToRoad,DistanceToCMO,СМО,PresenceGas,SourcePresenceGas,PresenceHeating,SourcePresenceHeating,PresencePower,SourcePresencePower,PresenceWaterDisposal,SourcePresenceWaterDisposal,PresenceWaterSupply,SourcePresenceWaterSupply,DistanceToEKB,DistanceToRoadEKB,CCoordX,CCoordY,DistanceToMetro,DistanceToStationEKB,CostZone,DistanceToRRStation,costzone2,Textloc_VICode,act_sign,MaxFloor,Enc_squre,Enc_proc,Adm_rn_EKB,forestry,InfluenceZone_IGS,loc_factor_801,loc_factor_802,loc_factor_803,loc_factor_804,loc_factor_806,loc_factor_807,loc_factor_8071,loc_factor_809,loc_factor_8091,loc_factor_810,loc_factor_8101,loc_factor_811,loc_factor_8111,loc_factor_812,loc_factor_8121,loc_factor_813,loc_factor_814,loc_factor_815,loc_factor_816,loc_factor_8161,loc_factor_817,loc_factor_818,loc_factor_819,loc_factor_820,loc_factor_8201,loc_factor_821,loc_factor_822,loc_factor_823,loc_factor_8231,loc_factor_824,loc_factor_825,loc_factor_826,loc_factor_827,loc_factor_828,loc_factor_829,loc_factor_830,loc_factor_831,loc_factor_832,loc_factor_833,loc_factor_8331,loc_factor_835,loc_factor_836,loc_factor_837,loc_factor_838,Statement,Type_Statement,Status_Statement,DistanceToVZC,VRI_IGS,Cot_name,DistanceToZTB,PowerLines,loc_factor_839,KodMO,loc_factor_840,loc_factor_841,presence_entrance,loc_factor_8371,ControlSP,Sp_flag,loc_VRICode540,Status_kc,Date_comm,Sol_comm,Flag_LocalityCode,Flag_VRI,Flag_Location,FlagParam,Flag_VRIoldspr,Flag_VRInewspr,Flag_Category,OldLocalityCode,Flag_VRI_All,VRICode_NEW,PraviloVRI,New_id_group,New_loc_SgCode,New_Segment,Old_Utlbydoc,VRICode_OLD,PraviloVRI_old,Court,Date_Court,Sol_Court,(select (case count(*) when 0 then 0 else 1 end) from GEO.docboxes b where b.obj_id=PARCELS.ID and b.table_id=265) Attachment,(select sign(Count(*)) from PARCELS g where (not GEOM_OBJ is null) and (PARCELS.ID = g.ID)) GeometryExists,((select DatePacket from inputpacket where id=Parcels.inputpacket_id) ) [inputpacket_date] From PARCELS WHERE status_kc = 'НЕ ГОТОВ' AND New_id_group=8015 | AX6: =Поправки!$G$4 -> 509.3919 | AY6: =I6 -> 0 | AZ6: =VLOOKUP(AY6,Поправки!$F$5:$G$6,2,0) -> #N/A | BA6: =H6 -> 0 | BB6: =VLOOKUP(BA6,Поправки!$F$7:$G$10,2,0) -> #N/A | BC6: =K6 -> 0 | BD6: =VLOOKUP(BC6,Поправки!$F$11:$G$13,2,0) -> #N/A | BE6: =J6 -> 0 | BF6: =VLOOKUP(BE6,Поправки!$F$14:$G$16,2,0) -> #N/A | BG6: =F6 -> 0 | BH6: =ROUND(EXP(0.713742903251*(9.03038414-2.63139367*LN(IF(BG6<4,4,BG6))+0.82725877*LN(IF(BG6<4,4,BG6))^2-0.11025986*LN(IF(BG6<4,4,BG6))^3))/EXP(0.713742903251*(9.03038414-2.63139367*LN(5)+0.82725877*LN(5)^2-0.11025986*LN(5)^3)),4) -> 1.1535 | BI6: =E6 -> 0 | BJ6: =VLOOKUP(BI6,Поправки!$F$18:$G$20,2,0) -> #N/A | BK6: =G6 -> 0 | BL6: =VLOOKUP(BK6,Поправки!$F$21:$G$29,2,0) -> #N/A | BM6: =ROUND(EXP(0.266642520892*(15.0191281-1.312096*LN(IF(D6<600,600,D6))))/EXP(0.266642520892*(15.0191281-1.312096*LN(1000))),4) -> 1.1957 | BN6: =M6 -> 0 | BO6: =VLOOKUP(BN6,Поправки!$F$31:$G$32,2,0) -> #N/A | BP6: Наличие уторгования | BQ6: =VLOOKUP(BP6,Поправки!$F$33:$G$34,2,0) -> 0.91 | BR6: =ROUND(AX6*AZ6*BB6*BD6*BF6*BH6*BJ6*BL6*BM6*BO6*BQ6,2) -> #N/A | BS6: =ROUND(BR6*D6,2) -> #N/A | BT6: =8015 -> 8015 | BU6: =IF(P6="","Новый объект",IF(AT6=AN6,BS6-Q6,"Объект пришел из другой модели")) -> Новый объект | BV6: =IF(AU6="",IF(AG6<>"","ОСПАРИВАНИЕ",IF(AV6<>"","СУД",IF(Z6="","",Z6))),AU6) | BW6: =B6 -> 0 | BX6: =Поправки!$G$4 -> 509.3919 | BY6: =IF(P6="","Наличие электроснабжения",IF(I6="",IF(W6="отсутствие","Отсутствие электроснабжения","Наличие электроснабжения"),I6)) -> Наличие электроснабжения | BZ6: =VLOOKUP(BY6,Поправки!$F$5:$G$6,2,0) -> 1 | CA6: =IF(P6="","Отсутствие газоснабжения",IF(H6="",IF(V6="наличие","Наличие газоснабжения","Отсутствие газоснабжения"),H6)) -> Отсутствие газоснабжения | CB6: =VLOOKUP(CA6,Поправки!$F$7:$G$10,2,0) -> 1 | CC6: Отсутствие водоснабжения | CD6: =VLOOKUP(CC6,Поправки!$F$11:$G$13,2,0) -> 1 | CE6: Отсутствие водоотведения | CF6: =VLOOKUP(CE6,Поправки!$F$14:$G$16,2,0) -> 1 | CG6: =IF(F6="",IF(U6="",VLOOKUP(AC6,Поправки!$G$37:$H$38,2,0),U6),F6) -> #N/A | CH6: =ROUND(EXP(0.713742903251*(9.03038414-2.63139367*LN(IF(CG6<4,4,CG6))+0.82725877*LN(IF(CG6<4,4,CG6))^2-0.11025986*LN(IF(CG6<4,4,CG6))^3))/EXP(0.713742903251*(9.03038414-2.63139367*LN(5)+0.82725877*LN(5)^2-0.11025986*LN(5)^3)),4) -> #N/A | CI6: =IF(T6="Земли населенных пунктов",Поправки!$F$18,Поправки!$F$19) -> Прочие | CJ6: =VLOOKUP(CI6,Поправки!$F$18:$G$20,2,0) -> 0.8419 | CK6: =IF(AR6="13:031",Поправки!$F$29,Поправки!$F$21) -> ИЖС | CL6: =VLOOKUP(CK6,Поправки!$F$21:$G$29,2,0) -> 1 | CM6: =S6 -> 0 | CN6: =ROUND(EXP(0.266642520892*(15.0191281-1.312096*LN(IF(CM6<600,600,CM6))))/EXP(0.266642520892*(15.0191281-1.312096*LN(1000))),4) -> 1.1957 | CO6: =IF(M6="",IF(O6="Влияние Нижнего Тагила","Наличие влияния Нижнего Тагила","Отсутствие влияния Нижнего Тагила"),IF(M6="Наличие влияния Нижнего Тагила","Наличие влияния Нижнего Тагила","Отсутствие влияния Нижнего Тагила")) -> Отсутствие влияния Нижнего Тагила | CP6: =VLOOKUP(CO6,Поправки!$F$31:$G$32,2,0) -> 1 | CQ6: Наличие уторгования | CR6: =VLOOKUP(CQ6,Поправки!$F$33:$G$34,2,0) -> 0.91 | CS6: =ROUND(BX6*BZ6*CB6*CD6*CF6*CH6*CJ6*CL6*CN6*CP6*CR6,2) -> #N/A | CT6: =ROUND(CS6*S6,2) -> #N/A | CU6: СТ16_Ф1_М15_18052021_Бунаков | CV6: =8015 -> 8015 | CW6: =IF(OR(CT6<0,CT6=0),"ОТРИЦАТЕЛЬНАЯ СТОИМОСТЬ",IF(DC6=0,"Пересчет не требуется","Готов")) -> #N/A | CX6: =AR6 -> 0 | CY6: 13. СЕГМЕНТ "Садоводство и огородничество, малоэтажная жилая застройка" | CZ6: =13 -> 13 | DA6: =VLOOKUP(CX6,'справочник ври'!$A$3:$B$271,2,0) -> #N/A | DB6: =AQ6 -> 0 | DC6: =IF(ISBLANK(P6),"Новый объект",IF(CV6=AN6,ABS(CT6-Q6),"Объект из другой модели")) -> Новый объект | DD6: =IF(OR(DC6="Объект из другой модели",DC6="Новый объект"),IF(OR(CS6<8,CS6>1070),"Отклонение УПКС","УПКС находится в допустимом интервале"),IF(DC6>1000000,"Внимение!Изменение более 1 млн","Изменение менее 1 млн")) -> #N/A | DE6: =IF(L6="","Новое значение",IF(L6=AC6,"Осталось предыдущее значение ЦФ","ИЗМЕНЕНИЕ")) -> Новое значение | DF6: =IF(I6="","Новое значение",IF(BY6=I6,"Осталось предыдущее значение ЦФ","ИЗМЕНЕНИЕ")) -> Новое значение | DG6: =IF(H6="","Новое значение",IF(CA6=H6,"Осталось предыдущее значение ЦФ","ИЗМЕНЕНИЕ")) -> Новое значение | DH6: =IF(P6="","Объект новый",IF(AJ6="не готов","ИЗМЕНЕНИЕ","Осталось предыдущее значение ЦФ")) -> Объект новый | DI6: =IF(F6="","Новое значение",IF(CG6=F6,"Осталось предыдущее значение ЦФ","ИЗМЕНЕНИЕ")) -> Новое значение | DJ6: =IF(E6="","Новое значение",IF(CI6=E6,"Осталось предыдущее значение ЦФ","ИЗМЕНЕНИЕ")) -> Новое значение | DK6: =IF(G6="","Новое значение",IF(CK6=G6,"Осталось предыдущее значение ЦФ","ИЗМЕНЕНИЕ")) -> Новое значение | DL6: =IF(AP6="","Новое значение",IF(AP6=AR6,"Осталось предыдущее значение ЦФ","ИЗМЕНЕНИЕ")) -> Новое значение | DM6: =IF(K6="","Новое значение",IF(CC6=K6,"Осталось предыдущее значение ЦФ","ИЗМЕНЕНИЕ")) -> Новое значение | DN6: =IF(J6="","Новое значение",IF(CE6=J6,"Осталось предыдущее значение ЦФ","ИЗМЕНЕНИЕ")) -> Новое значение | DO6: =IF(M6="","Новое значение",IF(CO6=M6,"Осталось предыдущее значение ЦФ","ИЗМЕНЕНИЕ")) -> Новое значение

Sheet справочник ври
A1: loc_VICode | B1: loc_GroupName
A2: Код расчета вида использования | B2: Наименование вида использования
A3: 01:010 | B3: Растениеводство в целом. Включает коды расчета вида использования 01.020-01.060
A4: 01:020 | B4: Выращивание зерновых, бобовых, кормовых, технических, масличных, эфиромасличных и иных сельскохозяйственных культур
A5: 01:030 | B5: Овощеводство в целом, связанное с производством картофеля, листовых, плодовых, луковичных и бахчевых сельскохозяйственных культур, в том числе с использованием теплиц
A6: 01:031 | B6: Овощеводство в открытом грунте
A7: 01:032 | B7: Овощеводство тепличное
A8: 01:040 | B8: Выращивание тонизирующих, лекарственных, цветочных культур в целом
A9: 01:041 | B9: Выращивание тонизирующих, лекарственных, цветочных культур. Травы
A10: 01:042 | B10: Выращивание тонизирующих, лекарственных, цветочных культур. Кустарники
A11: 01:050 | B11: Садоводство в целом - выращивание многолетних плодовых и ягодных культур, винограда и иных многолетних культур
A12: 01:051 | B12: Садоводство плодовое
... A271: 14:000 | B271: Иное использование

Sheet СТОПЛИСТ
A1: CadastralNumber | B1: ControlSP

Sheet ПЕРЕСЧЕТ НЕ ТРЕБУЕТСЯ
A1: CadastralNumber | B1: Status_kc | C1: loc_VICode | D1: Segment | E1: loc_SgCode | F1: loc_GroupName | G1: Old_Utlbydoc
A2: Кадастровый номер | B2: Статус расчета | C2: ВРИ | D2: Сегмент | E2: Код сегмента | F2: Расшифровка расчетной подгруппы | G2: ВРИ по документу старое(обновление поля)

Sheet ГОТОВ
A1: CadastralNumber | C1: loc_factor_804 | E1: loc_factor_822 | G1: loc_factor_828 | I1: loc_factor_803 | K1: loc_factor_812 | L1: loc_factor_8121 | M1: loc_factor_817 | O1: loc_factor_825 | Q1: loc_factor_807 | R1: loc_factor_8071 | S1: loc_factor_826 | U1: loc_factor_827 | W1: Specific_CadastralCost | X1: CadastralCost | Y1: CadastralCostDesc | Z1: id_group | AA1: Status_kc | AB1: loc_VICode | AC1: Segment | AD1: loc_SgCode | AE1: loc_GroupName | AF1: Old_Utlbydoc

Sheet Поправки
A1: Модель №15. Садоводческое, огородническое и дачное использование, малоэтажная жилая застройка. Нижний Тагил_ИЖС | M1: y=с*V1*V2*V3*V4*V5*V6*V7*V8*V9*V10 Где: y – удельный показатель; V1 – Поправочный коэффициент фактора "Наличие электричества"; V2 – Поправочный коэффициент фактора "Наличие газа"; V3 – Поправочный коэффициент фактора "Наличие водоснабжения"; V4 – Поправочный коэффициент фактора "Наличие канализации"; V5 – Поправочный коэффициент фактора «Расстояние до центра г. Нижний Тагил». V6 – Поправочный коэффициент фактора «Категория земель»; V7 – Поправочный коэффициент фактора «Вид разрешённого использования» V8 – Поправочный коэффициент фактора «Общая площадь»; V9 – Поправочный коэффициент фактора "Зона влияния г. Нижний Тагил"; V10 – Поправочный коэффициент фактора «Уторгование».
A2: Код МО (19 и 56). В других моделях это ценовой фактор | B2: Специально заводить в БД такое полев БД не нужно (Будем определять как два первых знака от кода НП)
A3: Фактор | B3: Обозначение фактора | C3: Номер модели | D3: Наименование поля БД | E3: Значение поля БД | F3: Градация (не хранится в БД как отдельное поле) | G3: Значение поправки
A4: Константа | B4: С0 | C4: 8015 | D4: НЕТ | E4: НЕТ | F4: Константа | G4: 509.3919 | K4: Учитываем при расчетах в Экселе
A5: Электроснабжение | B5: V1 | C5: 8015 | D5: Электроснабжение | E5: наличие | F5: Наличие электроснабжения | G5: 1
E6: отсутствие | F6: Отсутствие электроснабжения | G6: 0.6816
A7: Газоснабжение | B7: V2 | C7: 8015 | D7: Газоснабжение | E7: наличие | F7: Наличие газоснабжения | G7: 1.6714
E8: отсутствие | F8: Отсутствие газоснабжения | G8: 1
E9: пересечение | G9: 1
E10: пусто | G10: 1
A11: Водоснабжение | B11: V3 | C11: 8015 | D11: Водоснабжение | E11: наличие | F11: Наличие водоснабжения | G11: 1.371 | K11: Это особенность ИЖС, по воде и канализации всем ставим отсутствие
E12: отсутствие | F12: Отсутствие водоснабжения | G12: 1
E13: пусто | G13: 1
A14: Водоотведение | B14: V4 | C14: 8015 | D14: Водоотведение | E14: наличие | F14: Наличие водоотведения | G14: 1.371 | K14: Это особенность ИЖС, по воде и канализации всем ставим отсутствие
E15: отсутствие | F15: Отсутствие водоотведения | G15: 1
E16: пусто | G16: 1
A17: Расстояние до Нижнего Тагила | B17: V5 | C17: 8015 | D17: Расстояние до центра МО | E17: 5 | F17: Количественный | K17: для МО13 при пустом расстоянии берется 11км,для МО 14 при пустом расстоянии берется 19км
A18: Категория земель | B18: V6 | C18: 8015 | D18: Категория | E18: Земли населенных пунктов | F18: ЗНП | G18: 1
E19: Земли сельскохозяйственного назначения | F19: Прочие | G19: 0.8419
E20: Иные категории, пусто
A21: Вид разрешённого использования | B21: V7 | C21: 8015 | D21: Код расчетный | E21: 02:010 | F21: ИЖС | G21: 1 | K21: Если "0" то значит другой код ВРИ и другая модель
E22: 02:011
E23: 02:019
E24: 02:020
E25: 02:021
E26: 02:023
E27: 02:030
E28: 02:031
E29: 13:031 | F29: Дачный участок | G29: 0.9769
A30: Площадь | B30: V8 | C30: 8015 | D30: Площадь | E30: 1000 | F30: Количественный | G30: 1
A31: Зона влияния Нижнего Тагила | B31: V9 | C31: 8015 | D31: Зона влияния для ИЖС | E31: Влияние Нижнего Тагила | F31: Наличие влияния Нижнего Тагила | G31: 1.4006
E32: Иные значения, пусто | F32: Отсутствие влияния Нижнего Тагила | G32: 1
A33: Уторгование | B33: V10 | C33: 8015 | D33: НЕТ | E33: НЕТ | F33: Наличие уторгования | G33: 0.91
E34: НЕТ | F34: Отсутствие уторгования | G34: 1
G35: средние
G36: мо | H36: км
G37: 13 | H37: 11
G38: 14 | H38: 19
