Workbook

Sheet расчет
A1: Идентификатор | B1: Кадастровый номер | C1: Номер кадастрового квартала | D1: Площадь (ЦФ) | E1: Расстояние до административного центра МО (ЦФ) | F1: Электроснабжение (ЦФ) | G1: Водоотведение (ЦФ) | H1: Расстояние до центра Екатеринбурга (ЦФ) | I1: Газоснабжение (ЦФ) | J1: Водоснабжение (ЦФ) | K1: Локальные центры (отрицательные и положительные зоны влияния) (ЦФ) | L1: Статус и численность населенного пункта(ЦФ) | M1: Вид разрешённого использования (ЦФ) | N1: Управленческий округ (ЦФ) | O1: ЛЭП над участком (ЦФ) | P1: Удельный показатель кадастровой стоимости(руб/м2) | Q1: Кадастровая стоимость (руб) | R1: Кадастровая стоимость описание вых | S1: Площадь в квадратных метрах | T1: Категория земель | U1: Расстояние до центра МО | V1: Наличие электроснабжения | W1: Код Муниципального образования | X1: Наличие газоснабжения | Y1: Наличие водоотведения | Z1: Наличие водоснабжения | AA1: Расстояние до ЕКБ | AB1: Код населённого пункта | AC1: Старый код НП | AD1: Номер заявления | AE1: Тип заявления | AF1: Статус заявления | AG1: флажок | AH1: Дата пакета | AI1: Статус расчета | AJ1: Дата комиссии | AK1: Решение комиссии | AL1: Флаг кода НП | AM1: Флаг ВРИ по документу | AN1: Флаг площади | AO1: Флаг ВРИ старый спр | AP1: Флаг ВРИ новый спр | AQ1: Код расчета вида использования новый | AR1: Правило для ВРИ | AS1: Группа для XML | AT1: ВРИ по документу новое | AU1: Новая модель | AV1: Код расчета вида использования текущий (старый) | AW1: ВРИ по документу старое | AX1: Особый контроль | AY1: Суд | AZ1: Дата заседания | BA1: Повтор предыдущего расчета | CK1: Расчет стоимости в рамках 16 статьи | DY1: Анализ
A2: ID | B2: CadastralNumber | C2: CadastralBlock | D2: loc_factor_807 | E2: loc_factor_812 | F2: loc_factor_804 | G2: loc_factor_803 | H2: loc_factor_816 | I2: loc_factor_822 | J2: loc_factor_828 | K2: loc_factor_815 | L2: loc_factor_841 | M2: loc_factor_825 | N2: loc_factor_813 | O2: loc_factor_829 | P2: Specific_CadastralCost | Q2: CadastralCost | R2: CadastralCostDesc | S2: Area | T2: ParcelCategory | U2: DistanceToCMO | V2: PresencePower | W2: KodMO | X2: PresenceGas | Y2: PresenceWaterDisposal | Z2: PresenceWaterSupply | AA2: DistanceToEKB | AB2: LocalityCode | AC2: OldLocalityCode | AD2: Statement | AE2: Type_Statement | AF2: Status_Statement | AG2: Sp_flag | AH2: inputpacket_date | AI2: Status_kc | AJ2: Date_comm | AK2: Sol_comm | AL2: FlagLocalityCode | AM2: Flag_VRI | AN2: FlagParam | AO2: Flag_VRIoldspr | AP2: Flag_VRInewspr | AQ2: VRICode_NEW | AR2: PraviloVRI | AS2: ID_Group | AT2: UtilizationByDoc | AU2: New_id_group | AV2: loc_VICode | AW2: Old_Utlbydoc | AX2: ControlSP | AY2: Court | AZ2: Date_Court | BC2: V1 | BE2: V2 | BG2: V3 | BI2: V4 | BK2: V5 | BM2: V6 | BO2: V7 | BQ2: V8 | BT2: V9 | BW2: V10 | BZ2: V11 | CB2: V12 | CD2: V13 | CH2: Обязательная проверка | CJ2: CadastralNumber | CL2: loc_factor_822 | CN2: loc_factor_804 | CP2: loc_factor_828 | CR2: loc_factor_803 | CT2: loc_factor_813 | CV2: loc_factor_841 | CX2: loc_factor_825 | CZ2: loc_factor_829 | DC2: loc_factor_8071 | DD2: loc_factor_807 | DE2: loc_factor_816 | DG2: loc_factor_8161 | DH2: loc_factor_812 | DJ2: loc_factor_8121 | DK2: loc_factor_815 | DM2: loc_factor_827 | DO2: Specific_CadastralCost | DP2: CadastralCost | DQ2: CadastralCostDesc | DR2: id_group | DS2: Status_kc | DT2: loc_VICode | DU2: Segment | DV2: loc_SgCode | DW2: loc_GroupName | DX2: Old_Utlbydoc | DZ2: Текущий диапазон УПКС от 9 руб. до 873 руб. | EF2: Возможно изменение кода расчета, но при этом ЦФ может не меняться ,например: 02:010 стал 02:011- все ИЖС
A3: Parcels | B3: Parcels | C3: Parcels | D3: Parcels | E3: Parcels | F3: Parcels | G3: Parcels | H3: Parcels | I3: Parcels | J3: Parcels | K3: Parcels | L3: Parcels | M3: Parcels | N3: Parcels | O3: Parcels | P3: Parcels | Q3: Parcels | R3: Parcels | S3: Parcels | T3: Parcels | U3: Parcels | V3: Parcels | W3: Parcels | X3: Parcels | Y3: Parcels | Z3: Parcels | AA3: Parcels | AB3: Parcels | AC3: Parcels | AD3: Parcels | AE3: Parcels | AF3: Parcels | AG3: Parcels | AH3: Parcels | AI3: Parcels | AJ3: Parcels | AK3: Parcels | AL3: Parcels | AM3: Parcels | AN3: Parcels | AO3: Parcels | AP3: Parcels | AQ3: Parcels | AR3: Parcels | AS3: Parcels | AT3: Parcels | AU3: Parcels | AV3: Parcels | AW3: Parcels | AX3: Parcels | AY3: Parcels | AZ3: Parcels | BA3: Базовая стоимость | BB3: Газоснабжение | BC3: Поправка на Газоснабжение | BD3: Электроснабжение | BE3: Поправка на Электроснабжение | BF3: Водоснабжение | BG3: Поправка на Водоснабжение | BH3: Водоотведение | BI3: Поправка на Водоотведение | BJ3: Управленческий округ | BK3: Поправка на Управленческий округ | BL3: Статус и численность населенного пункта | BM3: Поправка на Статус и численность населенного пункта | BN3: Вид разрешённого использования | BO3: Поправка на Вид разрешённого использования | BP3: ЛЭП над участком | BQ3: Поправка на ЛЭП над участком | BR3: Общая площадь ЦФ | BS3: Общая площадь(вспомогательный столбец) | BT3: Поправка на площадь | BU3: Расстояние до Екатеринбурга | BV3: Расстояние до Екатеринбурга(вспомогательный столбец) | BW3: Поправка на Расстояние до Екатеринбурга | BX3: Расстояние до центра муниципального образования | BY3: Расстояние до центра муниципального образования(вспомогательный столбец) | BZ3: Поправка на Расстояние до центра муниципального образования | CA3: Локальный центр | CB3: Поправка на Локальный центр | CC3: Уторгование | CD3: Поправка на Уторгование | CE3: УПС | CF3: Кадастровая стоимость | CG3: id_group | CH3: Вверно, если расходждение составляет 0,00 руб. Если расхождение составляет более 0,01 -ценовые факторы подобраны неверно. Требуется анализ | CI3: Участие объекта на комиссии, в заявлениях, в судах и прочее | CJ3: КН | CK3: Базовая стоимость | CL3: Газоснабжение | CM3: Поправка на Газоснабжение | CN3: Электроснабжение | CO3: Поправка на Электроснабжение | CP3: Водоснабжение | CQ3: Поправка на Водоснабжение | CR3: Водоотведение | CS3: Поправка на Водоотведение | CT3: Управленческий округ | CU3: Поправка на Управленческий округ | CV3: Статус и численность населенного пункта | CW3: Поправка на Статус и численность населенного пункта | CX3: Вид разрешённого использования | CY3: Поправка на Вид разрешённого использования | CZ3: ЛЭП над участком | DA3: Поправка на ЛЭП над участком | DB3: Общая площадь(вспомогательный столбец) | DC3: Поправка на площадь | DD3: Общая площадь | DE3: Расстояние до Екатеринбурга(вспомогательный столбец) | DF3: Расстояние до Екатеринбурга | DG3: Поправка на Расстояние до Екатеринбурга | DH3: Расстояние до центра муниципального образования(вспомогательный столбец) | DI3: Расстояние до центра муниципального образования | DJ3: Поправка на Расстояние до центра муниципального образования | DK3: Локальный центр | DL3: Поправка на Локальный центр | DM3: Уторгование | DN3: Поправка на Уторгование | DO3: УПС | DP3: Кадастровая стоимость | DQ3: CadastralCostDesc | DR3: id_group | DS3: Статус расчета | DT3: ВРИ | DU3: Сегмент | DV3: Код сегмента | DW3: Расшифровка расчетной подгруппы | DX3: ВРИ по документу старое (обновление поля) | DY3: Сравнение расчета с предыдущим расчетом | DZ3: Проверка отклонения УПКС от текущего диапазона и контроль значительного изменения КС | EA3: Электроснабжение | EB3: Газоснабжение | EC3: Площадь | ED3: Расстояние до административного центра МО | EE3: Расстояние до Екатеринбурга | EF3: Ценовой фактор ВРИ в модели | EG3: Изменение Кода расчета | EH3: Водоснабжение | EI3: Водоотведение | EJ3: ЛЭП над участком | EK3: Локальный центр | EL3: Управленческий округ | EM3: Статус и численность населенного пункта
T4: spr | BA4: =317.4645 -> 317.4645 | BB4: =IF(I4="Наличие газоснабжения","Наличие газоснабжения","Отсутствие газоснабжения") -> Отсутствие газоснабжения | BC4: =VLOOKUP(BB4,'Описание (градации)'!$E$7:$F$8,2,0) -> 1 | BD4: =IF(F4="Наличие электроснабжения","Наличие электроснабжения","Отсутствие электроснабжения") -> Отсутствие электроснабжения | BE4: =VLOOKUP(BD4,'Описание (градации)'!$E$9:$F$10,2,0) -> 0.6102 | BF4: =IF(J4="Наличие водоснабжения","Наличие водоснабжения","Отсутствие водоснабжения") -> Отсутствие водоснабжения | BG4: =VLOOKUP(BF4,'Описание (градации)'!$E$11:$F$12,2,0) -> 1 | BH4: =IF(I4="Наличие водоотведения","Наличие водоотведения","Отсутствие водоотведения") -> Отсутствие водоотведения | BI4: =VLOOKUP(BH4,'Описание (градации)'!$E$13:$F$14,2,0) -> 1 | BJ4: =N4 -> 0 | BK4: =VLOOKUP(BJ4,'Описание (градации)'!$E$15:$F$19,2,0) -> #N/A | BL4: =L4 -> 0 | BM4: =VLOOKUP(BL4,'Описание (градации)'!$E$20:$F$24,2,0) -> #N/A | BN4: =M4 -> 0 | BO4: =VLOOKUP(BN4,'Описание (градации)'!$E$25:$F$27,2,0) -> #N/A | BP4: =O4 -> 0 | BQ4: =VLOOKUP(BP4,'Описание (градации)'!$E$28:$F$29,2,0) -> #N/A | BR4: =D4 -> 0 | BS4: =IF(BR4<400,400,IF(BR4>4510000,4510000,BR4)) -> 400 | BT4: =ROUND(EXP(0.3620826966*(15.93881008-5.49662653*LN(LN(BS4))))/EXP(0.3620826966*(15.93881008-5.49662653*LN(LN(1000)))),4) -> 1.3274 | BU4: =H4 -> 0 | BV4: =IF(BU4<50,50,IF(BU4>630,630,BU4)) -> 50 | BW4: =ROUND(EXP(4.118629221*(EXP(1)^(1.71093948-0.01799629*LN(BV4))))/EXP(4.118629221*(EXP(1)^(1.71093948-0.01799629*LN(100)))),4) -> 1.3013 | BX4: =E4 -> 0 | BY4: =IF(BX4<1,1,IF(BX4>203.57,203.57,BX4)) -> 1 | BZ4: =ROUND(EXP(0.4276469859*(5.64644498-0.48211057*LN(BY4)+0.10557587*LN(BY4)^2+0.00096428*LN(BY4)^3-0.00414511*LN(BY4)^4))/EXP(0.4276469859*(5.64644498-0.48211057*LN(5)+0.10557587*LN(5)^2+0.00096428*LN(5)^3-0.00414511*LN(5)^4)),4) -> 1.2524 | CA4: =K4 -> 0 | CB4: =VLOOKUP(CA4,'Описание (градации)'!$E$33:$F$35,2,0) -> #N/A | CC4: Наличие уторгования | CD4: =0.91 -> 0.91 | CE4: =ROUND(BA4*BC4*BE4*BG4*BI4*BK4*BM4*BO4*BQ4*BT4*BW4*BZ4*CB4*CD4,2) -> #N/A | CF4: =ROUND(CE4*BR4,2) -> #N/A | CG4: =8013 -> 8013 | CH4: =IF(P4="","Объект новый",IF(AS4=CG4,CE4-P4,"объект пришел из другой модели")) -> Объект новый | CI4: =IF(AX4="",IF(AJ4<>"","ОСПАРИВАНИЕ",IF(AY4<>"","СУД",IF(AD4="","",AD4))),AX4) | CJ4: =B4 -> 0 | CK4: =317.4645 -> 317.4645 | CL4: =IF(I4="",IF(AQ4="13:011","Отсутствие газоснабжения",IF(AQ4="13:021","Отсутствие газоснабжения",IF(X4="наличие","Наличие газоснабжения","Отсутствие газоснабжения"))),I4) -> Отсутствие газоснабжения | CM4: =VLOOKUP(CL4,'Описание (градации)'!$E$7:$F$8,2,0) -> 1 | CN4: =IF(F4="",IF(V4="","Отсутствие электроснабжения",IF(V4="отсутствие","Отсутствие электроснабжения","Наличие электроснабжения")),F4) -> Отсутствие электроснабжения | CO4: =VLOOKUP(CN4,'Описание (градации)'!$E$9:$F$10,2,0) -> 0.6102 | CP4: ="Отсутствие водоснабжения" -> Отсутствие водоснабжения | CQ4: =VLOOKUP(CP4,'Описание (градации)'!$E$11:$F$12,2,0) -> 1 | CR4: ="Отсутствие водоотведения" -> Отсутствие водоотведения | CS4: =VLOOKUP(CR4,'Описание (градации)'!$E$13:$F$14,2,0) -> 1 | CT4: =IF(AC4="",VLOOKUP(AB4,'ВПР статус и численность'!$A$2:$C$1992,3,0),VLOOKUP(AC4,'ВПР статус и численность'!$A$2:$C$1992,3,0)) -> #N/A | CU4: =VLOOKUP(CT4,'Описание (градации)'!$E$15:$F$19,2,0) -> #N/A | CV4: =IF(AC4="",VLOOKUP(AB4,'ВПР статус и численность'!$A$2:$B$1992,2,0),VLOOKUP(AC4,'ВПР статус и численность'!$A$2:$B$1992,2,0)) -> #N/A | CW4: =VLOOKUP(CV4,'Описание (градации)'!$E$20:$F$24,2,0) -> #N/A | CX4: =IF(AQ4="13:011","Садовый участок",IF(AQ4="13:021","Садовый участок",IF(AQ4="13:031","Дачный участок","ИЖС"))) -> ИЖС | CY4: =VLOOKUP(CX4,'Описание (градации)'!$E$25:$F$27,2,0) -> 1 | CZ4: =IF(Y4="Наличие ЛЭП","Наличие ЛЭП","Отсутствие ЛЭП") -> Отсутствие ЛЭП | DA4: =VLOOKUP(CZ4,'Описание (градации)'!$E$28:$F$29,2,0) -> 1 | DB4: =IF(S4<400,400,IF(S4>4510000,4510000,S4)) -> 400 | DC4: =ROUND(EXP(0.3620826966*(15.93881008-5.49662653*LN(LN(DB4))))/EXP(0.3620826966*(15.93881008-5.49662653*LN(LN(1000)))),4) -> 1.3274 | DD4: =S4 -> 0 | DE4: =IF(H4="",VLOOKUP(расчет!W4,'Средние расстояния'!$A$2:$C$55,2,0),H4) -> #N/A | DF4: =IF(DE4<50,50,IF(DE4>630,630,DE4)) -> #N/A | DG4: =ROUND(EXP(4.118629221*(EXP(1)^(1.71093948-0.01799629*LN(DF4))))/EXP(4.118629221*(EXP(1)^(1.71093948-0.01799629*LN(100)))),4) -> #N/A | DH4: =IF(E4="",VLOOKUP(W4,'Средние расстояния'!$A$2:$C$55,3,0),E4) -> #N/A | DI4: =IF(DH4<1,1,IF(DH4>203.57,203.57,DH4)) -> #N/A | DJ4: =ROUND(EXP(0.4276469859*(5.64644498-0.48211057*LN(DI4)+0.10557587*LN(DI4)^2+0.00096428*LN(DI4)^3-0.00414511*LN(DI4)^4))/EXP(0.4276469859*(5.64644498-0.48211057*LN(5)+0.10557587*LN(5)^2+0.00096428*LN(5)^3-0.00414511*LN(5)^4)),4) -> #N/A | DK4: Не находится в зоне влияния локальных центров | DL4: =VLOOKUP(DK4,'Описание (градации)'!$E$33:$F$35,2,0) -> 1 | DM4: Наличие уторгования | DN4: =0.91 -> 0.91 | DO4: =ROUND(CK4*CM4*CO4*CQ4*CS4*CU4*CW4*CY4*DA4*DC4*DG4*DJ4*DL4*DN4,2) -> #N/A | DP4: =ROUND(DO4*S4,2) -> #N/A | DQ4: СТ16_Ф1_М13_18052021_Бунаков_Измененные | DR4: =8013 -> 8013 | DS4: =IF(OR(DP4<0,DP4=0),"ОТРИЦАТЕЛЬНОЕ ЗНАЧЕНИЕ",IF(DY4=0,"Пересчет не требуется","Готов")) -> #N/A | DT4: =AQ4 -> 0 | DU4: 13. СЕГМЕНТ "Садоводство и огородничество, малоэтажная жилая застройка" | DV4: =13 -> 13 | DW4: =VLOOKUP(DT4,'справочник ври'!$A$3:$B$271,2,0) -> #N/A | DX4: =AT4 -> 0 | DY4: =IF(ISBLANK(P4),"Новый объект",IF(DR4=AS4,ABS(DP4-Q4),"Объект из другой модели")) -> Новый объект | DZ4: =IF(DY4="Объект из другой модели",IF(OR(DO4<9,DO4>873),"Отклонение УПКС","УПКС в допустимом интервале "),IF(DY4<1000000,"Изменение менее 1 млн","Внимание!Изменение более 1млн")) -> Внимание!Изменение более 1млн | EA4: =IF(F4="","Новое значение",IF(CN4=F4,"Осталось предыдущее значение ЦФ","ИЗМЕНЕНИЕ")) -> Новое значение | EB4: =IF(I4="","Новое значение",IF(I4=CL4,"Осталось предыдущее значение ЦФ","ИЗМЕНЕНИЕ")) -> Новое значение | EC4: =IF(AN4="не готов","ИЗМЕНЕНИЕ","Осталось предыдущее значение ЦФ") -> Осталось предыдущее значение ЦФ | ED4: =IF(E4="","Новое значение",IF(E4=DH4,"Осталось предыдущее значение ЦФ","ИЗМЕНЕНИЕ")) -> Новое значение | EE4: =IF(H4="","Новое значение",IF(H4=DF4,"Осталось предыдущее значение ЦФ","ИЗМЕНЕНИЕ")) -> Новое значение | EF4: =IF(M4="","Новое значение",IF(CX4=M4,"Осталось предыдущее значение ЦФ","ИЗМЕНЕНИЕ")) -> Новое значение | EG4: =IF(AV4=AQ4,"Осталось предыдущее значение ЦФ","ИЗМЕНЕНИЕ") -> Осталось предыдущее значение ЦФ | EH4: =IF(J4="","Новое значение",IF(CP4=J4,"Осталось предыдущее значение ЦФ","ИЗМЕНЕНИЕ")) -> Новое значение | EI4: =IF(G4="","Новое значение",IF(CR4=G4,"Осталось предыдущее значение ЦФ","ИЗМЕНЕНИЕ")) -> Новое значение | EJ4: =IF(O4="","Новое значение",IF(CZ4=O4,"Осталось предыдущее значение ЦФ","ИЗМЕНЕНИЕ")) -> Новое значение | EK4: =IF(K4="","Новое значение",IF(DK4=K4,"Осталось предыдущее значение ЦФ","ИЗМЕНЕНИЕ")) -> Новое значение | EL4: =IF(N4="","Новое значение",IF(CT4=N4,"Осталось предыдущее значение ЦФ","ИЗМЕНЕНИЕ")) -> Новое значение | EM4: =IF(L4="","Новое значение",IF(CV4=L4,"Осталось предыдущее значение ЦФ","ИЗМЕНЕНИЕ")) -> Новое значение
BA5: =317.4645 -> 317.4645 | BB5: =IF(I5="Наличие газоснабжения","Наличие газоснабжения","Отсутствие газоснабжения") -> Отсутствие газоснабжения | BC5: =VLOOKUP(BB5,'Описание (градации)'!$E$7:$F$8,2,0) -> 1 | BD5: =IF(F5="Наличие электроснабжения","Наличие электроснабжения","Отсутствие электроснабжения") -> Отсутствие электроснабжения | BE5: =VLOOKUP(BD5,'Описание (градации)'!$E$9:$F$10,2,0) -> 0.6102 | BF5: =IF(J5="Наличие водоснабжения","Наличие водоснабжения","Отсутствие водоснабжения") -> Отсутствие водоснабжения | BG5: =VLOOKUP(BF5,'Описание (градации)'!$E$11:$F$12,2,0) -> 1 | BH5: =IF(I5="Наличие водоотведения","Наличие водоотведения","Отсутствие водоотведения") -> Отсутствие водоотведения | BI5: =VLOOKUP(BH5,'Описание (градации)'!$E$13:$F$14,2,0) -> 1 | BJ5: =N5 -> 0 | BK5: =VLOOKUP(BJ5,'Описание (градации)'!$E$15:$F$19,2,0) -> #N/A | BL5: =L5 -> 0 | BM5: =VLOOKUP(BL5,'Описание (градации)'!$E$20:$F$24,2,0) -> #N/A | BN5: =M5 -> 0 | BO5: =VLOOKUP(BN5,'Описание (градации)'!$E$25:$F$27,2,0) -> #N/A | BP5: =O5 -> 0 | BQ5: =VLOOKUP(BP5,'Описание (градации)'!$E$28:$F$29,2,0) -> #N/A | BR5: =D5 -> 0 | BS5: =IF(BR5<400,400,IF(BR5>4510000,4510000,BR5)) -> 400 | BT5: =ROUND(EXP(0.3620826966*(15.93881008-5.49662653*LN(LN(BS5))))/EXP(0.3620826966*(15.93881008-5.49662653*LN(LN(1000)))),4) -> 1.3274 | BU5: =H5 -> 0 | BV5: =IF(BU5<50,50,IF(BU5>630,630,BU5)) -> 50 | BW5: =ROUND(EXP(4.118629221*(EXP(1)^(1.71093948-0.01799629*LN(BV5))))/EXP(4.118629221*(EXP(1)^(1.71093948-0.01799629*LN(100)))),4) -> 1.3013 | BX5: =E5 -> 0 | BY5: =IF(BX5<1,1,IF(BX5>203.57,203.57,BX5)) -> 1 | BZ5: =ROUND(EXP(0.4276469859*(5.64644498-0.48211057*LN(BY5)+0.10557587*LN(BY5)^2+0.00096428*LN(BY5)^3-0.00414511*LN(BY5)^4))/EXP(0.4276469859*(5.64644498-0.48211057*LN(5)+0.10557587*LN(5)^2+0.00096428*LN(5)^3-0.00414511*LN(5)^4)),4) -> 1.2524 | CA5: =K5 -> 0 | CB5: =VLOOKUP(CA5,'Описание (градации)'!$E$33:$F$35,2,0) -> #N/A | CC5: Наличие уторгования | CD5: =0.91 -> 0.91 | CE5: =ROUND(BA5*BC5*BE5*BG5*BI5*BK5*BM5*BO5*BQ5*BT5*BW5*BZ5*CB5*CD5,2) -> #N/A | CF5: =ROUND(CE5*BR5,2) -> #N/A | CG5: =8013 -> 8013 | CH5: =IF(P5="","Объект новый",IF(AS5=CG5,CE5-P5,"объект пришел из другой модели")) -> Объект новый | CI5: =IF(AX5="",IF(AJ5<>"","ОСПАРИВАНИЕ",IF(AY5<>"","СУД",IF(AD5="","",AD5))),AX5) | CJ5: =B5 -> 0 | CK5: =317.4645 -> 317.4645 | CL5: =IF(I5="",IF(AQ5="13:011","Отсутствие газоснабжения",IF(AQ5="13:021","Отсутствие газоснабжения",IF(X5="наличие","Наличие газоснабжения","Отсутствие газоснабжения"))),I5) -> Отсутствие газоснабжения | CM5: =VLOOKUP(CL5,'Описание (градации)'!$E$7:$F$8,2,0) -> 1 | CN5: =IF(F5="",IF(V5="","Отсутствие электроснабжения",IF(V5="отсутствие","Отсутствие электроснабжения","Наличие электроснабжения")),F5) -> Отсутствие электроснабжения | CO5: =VLOOKUP(CN5,'Описание (градации)'!$E$9:$F$10,2,0) -> 0.6102 | CP5: ="Отсутствие водоснабжения" -> Отсутствие водоснабжения | CQ5: =VLOOKUP(CP5,'Описание (градации)'!$E$11:$F$12,2,0) -> 1 | CR5: ="Отсутствие водоотведения" -> Отсутствие водоотведения | CS5: =VLOOKUP(CR5,'Описание (градации)'!$E$13:$F$14,2,0) -> 1 | CT5: =IF(AC5="",VLOOKUP(AB5,'ВПР статус и численность'!$A$2:$C$1992,3,0),VLOOKUP(AC5,'ВПР статус и численность'!$A$2:$C$1992,3,0)) -> #N/A | CU5: =VLOOKUP(CT5,'Описание (градации)'!$E$15:$F$19,2,0) -> #N/A | CV5: =IF(AC5="",VLOOKUP(AB5,'ВПР статус и численность'!$A$2:$B$1992,2,0),VLOOKUP(AC5,'ВПР статус и численность'!$A$2:$B$1992,2,0)) -> #N/A | CW5: =VLOOKUP(CV5,'Описание (градации)'!$E$20:$F$24,2,0) -> #N/A | CX5: =IF(AQ5="13:011","Садовый участок",IF(AQ5="13:021","Садовый участок",IF(AQ5="13:031","Дачный участок","ИЖС"))) -> ИЖС | CY5: =VLOOKUP(CX5,'Описание (градации)'!$E$25:$F$27,2,0) -> 1 | CZ5: =IF(Y5="Наличие ЛЭП","Наличие ЛЭП","Отсутствие ЛЭП") -> Отсутствие ЛЭП | DA5: =VLOOKUP(CZ5,'Описание (градации)'!$E$28:$F$29,2,0) -> 1 | DB5: =IF(S5<400,400,IF(S5>4510000,4510000,S5)) -> 400 | DC5: =ROUND(EXP(0.3620826966*(15.93881008-5.49662653*LN(LN(DB5))))/EXP(0.3620826966*(15.93881008-5.49662653*LN(LN(1000)))),4) -> 1.3274 | DD5: =S5 -> 0 | DE5: =IF(H5="",VLOOKUP(расчет!W5,'Средние расстояния'!$A$2:$C$55,2,0),H5) -> #N/A | DF5: =IF(DE5<50,50,IF(DE5>630,630,DE5)) -> #N/A | DG5: =ROUND(EXP(4.118629221*(EXP(1)^(1.71093948-0.01799629*LN(DF5))))/EXP(4.118629221*(EXP(1)^(1.71093948-0.01799629*LN(100)))),4) -> #N/A | DH5: =IF(E5="",VLOOKUP(W5,'Средние расстояния'!$A$2:$C$55,3,0),E5) -> #N/A | DI5: =IF(DH5<1,1,IF(DH5>203.57,203.57,DH5)) -> #N/A | DJ5: =ROUND(EXP(0.4276469859*(5.64644498-0.48211057*LN(DI5)+0.10557587*LN(DI5)^2+0.00096428*LN(DI5)^3-0.00414511*LN(DI5)^4))/EXP(0.4276469859*(5.64644498-0.48211057*LN(5)+0.10557587*LN(5)^2+0.00096428*LN(5)^3-0.00414511*LN(5)^4)),4) -> #N/A | DK5: Не находится в зоне влияния локальных центров | DL5: =VLOOKUP(DK5,'Описание (градации)'!$E$33:$F$35,2,0) -> 1 | DM5: Наличие уторгования | DN5: =0.91 -> 0.91 | DO5: =ROUND(CK5*CM5*CO5*CQ5*CS5*CU5*CW5*CY5*DA5*DC5*DG5*DJ5*DL5*DN5,2) -> #N/A | DP5: =ROUND(DO5*S5,2) -> #N/A | DQ5: СТ16_Ф1_М13_18052021_Бунаков_Измененные | DR5: =8013 -> 8013 | DS5: =IF(OR(DP5<0,DP5=0),"ОТРИЦАТЕЛЬНОЕ ЗНАЧЕНИЕ",IF(DY5=0,"Пересчет не требуется","Готов")) -> #N/A | DT5: =AQ5 -> 0 | DU5: 13. СЕГМЕНТ "Садоводство и огородничество, малоэтажная жилая застройка" | DV5: =13 -> 13 | DW5: =VLOOKUP(DT5,'справочник ври'!$A$3:$B$271,2,0) -> #N/A | DX5: =AT5 -> 0 | DY5: =IF(ISBLANK(P5),"Новый объект",IF(DR5=AS5,ABS(DP5-Q5),"Объект из другой модели")) -> Новый объект | DZ5: =IF(DY5="Объект из другой модели",IF(OR(DO5<9,DO5>873),"Отклонение УПКС","УПКС в допустимом интервале "),IF(DY5<1000000,"Изменение менее 1 млн","Внимание!Изменение более 1млн")) -> Внимание!Изменение более 1млн | EA5: =IF(F5="","Новое значение",IF(CN5=F5,"Осталось предыдущее значение ЦФ","ИЗМЕНЕНИЕ")) -> Новое значение | EB5: =IF(I5="","Новое значение",IF(I5=CL5,"Осталось предыдущее значение ЦФ","ИЗМЕНЕНИЕ")) -> Новое значение | EC5: =IF(AN5="не готов","ИЗМЕНЕНИЕ","Осталось предыдущее значение ЦФ") -> Осталось предыдущее значение ЦФ | ED5: =IF(E5="","Новое значение",IF(E5=DH5,"Осталось предыдущее значение ЦФ","ИЗМЕНЕНИЕ")) -> Новое значение | EE5: =IF(H5="","Новое значение",IF(H5=DF5,"Осталось предыдущее значение ЦФ","ИЗМЕНЕНИЕ")) -> Новое значение | EF5: =IF(M5="","Новое значение",IF(CX5=M5,"Осталось предыдущее значение ЦФ","ИЗМЕНЕНИЕ")) -> Новое значение | EG5: =IF(AV5=AQ5,"Осталось предыдущее значение ЦФ","ИЗМЕНЕНИЕ") -> Осталось предыдущее значение ЦФ | EH5: =IF(J5="","Новое значение",IF(CP5=J5,"Осталось предыдущее значение ЦФ","ИЗМЕНЕНИЕ")) -> Новое значение | EI5: =IF(G5="","Новое значение",IF(CR5=G5,"Осталось предыдущее значение ЦФ","ИЗМЕНЕНИЕ")) -> Новое значение | EJ5: =IF(O5="","Новое значение",IF(CZ5=O5,"Осталось предыдущее значение ЦФ","ИЗМЕНЕНИЕ")) -> Новое значение | EK5: =IF(K5="","Новое значение",IF(DK5=K5,"Осталось предыдущее значение ЦФ","ИЗМЕНЕНИЕ")) -> Новое значение | EL5: =IF(N5="","Новое значение",IF(CT5=N5,"Осталось предыдущее значение ЦФ","ИЗМЕНЕНИЕ")) -> Новое значение | EM5: =IF(L5="","Новое значение",IF(CV5=L5,"Осталось предыдущее значение ЦФ","ИЗМЕНЕНИЕ")) -> Новое значение
A6: Select ID,Source_ID,CadastralNumber,DateCreated,CadastralBlock,Name,ObjectType,Area,AreaUnit,AreaInaccuracy,LocationinBounds,LocationPlaced,ElaborationReferenceMark,ElaborationDistance,ElaborationDirection,AddressOrLocation,FIAS,OKATO,KLADR,OKTMO,PostalCode,AddressRF,Region,DistrictName,DistrictType,CityName,CityType,UrbanDistrictName,UrbanDistrictType,SovietVillageName,SovietVillageType,LocalityName,LocalityType,PlanningElementName,PlanningElementType,StreetName,StreetType,Level1Type,Level1Value,Level2Type,Level2Value,Level3Type,Level3Value,ApartmentType,ApartmentValue,AddressOther,AddressNote,ParcelCategory,Utilization,UtilizationByDoc,UtilizationLandUse,UtilizationТхт,CostValue,CostUnit,CostDateValuation,CostDateEntering,CostDateApproval,CostDocNumber,CostDocDate,CostApplicationDate,CostRevisalStatementDate,CostApplicationLastDate,CostDocName,FacilityKN,FacilityKNPurpose,SurveyProjectNum,DecisionCodeDocument,DecisionName,DecisionSeries,DecisionNumber,DecisionDate,DecisionIssueOrgan,DecisionDesc,HiredHouseUse,HouseActBuilding,HouseActDevelopment,BuildingContractName,DevelopContractName,OwnerDecision,SupportContractName,CodeDocument,DocHiredHouseName,DocHiredHouseSeries,DocHiredHouseNumber,DocHiredHouseDate,DocHiredHouseIssueOrgan,DocHiredHouseDesc,LimitedRightNumber,CREATEOPERATORNAME,CREATEDATE,OPERATORNAME,MODIFYDATE,MI_STYLE,Specific_CadastralCost,CadastralCost,CadastralCostDesc,MO_Name,ID_Group,LocalityCode,locTypeUse2,loc_VICode,loc_GroupName,loc_VRICode,Sourse_loc_VICode,locTypeUse,inputpacket_id,loc_SgCode,VIP_Sp,Quant_Kontur,Quant_Point,Sum_Square,Sum_Perim,Proc_Diff_Square,Pr_Diff,Source_Sum_Square,SourceLocalityCode,Upload_Scroll,Date_KC,Segment,FlagLocalityCode,DistanceToRoad,DistanceToCMO,СМО,PresenceGas,SourcePresenceGas,PresenceHeating,SourcePresenceHeating,PresencePower,SourcePresencePower,PresenceWaterDisposal,SourcePresenceWaterDisposal,PresenceWaterSupply,SourcePresenceWaterSupply,DistanceToEKB,DistanceToRoadEKB,CCoordX,CCoordY,DistanceToMetro,DistanceToStationEKB,CostZone,DistanceToRRStation,costzone2,Textloc_VICode,act_sign,MaxFloor,Enc_squre,Enc_proc,Adm_rn_EKB,forestry,InfluenceZone_IGS,loc_factor_801,loc_factor_802,loc_factor_803,loc_factor_804,loc_factor_806,loc_factor_807,loc_factor_8071,loc_factor_809,loc_factor_8091,loc_factor_810,loc_factor_8101,loc_factor_811,loc_factor_8111,loc_factor_812,loc_factor_8121,loc_factor_813,loc_factor_814,loc_factor_815,loc_factor_816,loc_factor_8161,loc_factor_817,loc_factor_818,loc_factor_819,loc_factor_820,loc_factor_8201,loc_factor_821,loc_factor_822,loc_factor_823,loc_factor_8231,loc_factor_824,loc_factor_825,loc_factor_826,loc_factor_827,loc_factor_828,loc_factor_829,loc_factor_830,loc_factor_831,loc_factor_832,loc_factor_833,loc_factor_8331,loc_factor_835,loc_factor_836,loc_factor_837,loc_factor_838,Statement,Type_Statement,Status_Statement,DistanceToVZC,VRI_IGS,Cot_name,DistanceToZTB,PowerLines,loc_factor_839,KodMO,loc_factor_840,loc_factor_841,presence_entrance,loc_factor_8371,ControlSP,Sp_flag,loc_VRICode540,Status_kc,Date_comm,Sol_comm,Flag_LocalityCode,Flag_VRI,Flag_Location,FlagParam,Flag_VRIoldspr,Flag_VRInewspr,Flag_Category,OldLocalityCode,Flag_VRI_All,VRICode_NEW,PraviloVRI,New_id_group,New_loc_SgCode,New_Segment,Old_Utlbydoc,VRICode_OLD,PraviloVRI_old,Court,Date_Court,Sol_Court,(select (case count(*) when 0 then 0 else 1 end) from GEO.docboxes b where b.obj_id=PARCELS.ID and b.table_id=265) Attachment,(select sign(Count(*)) from PARCELS g where (not GEOM_OBJ is null) and (PARCELS.ID = g.ID)) GeometryExists,((select DatePacket from inputpacket where id=Parcels.inputpacket_id) ) [inputpacket_date] From PARCELS where status_kc='НЕ ГОТОВ' AND ( CadastralCost is not Null) AND New_id_group=8013 | BA6: =317.4645 -> 317.4645 | BB6: =IF(I6="Наличие газоснабжения","Наличие газоснабжения","Отсутствие газоснабжения") -> Отсутствие газоснабжения | BC6: =VLOOKUP(BB6,'Описание (градации)'!$E$7:$F$8,2,0) -> 1 | BD6: =IF(F6="Наличие электроснабжения","Наличие электроснабжения","Отсутствие электроснабжения") -> Отсутствие электроснабжения | BE6: =VLOOKUP(BD6,'Описание (градации)'!$E$9:$F$10,2,0) -> 0.6102 | BF6: =IF(J6="Наличие водоснабжения","Наличие водоснабжения","Отсутствие водоснабжения") -> Отсутствие водоснабжения | BG6: =VLOOKUP(BF6,'Описание (градации)'!$E$11:$F$12,2,0) -> 1 | BH6: =IF(I6="Наличие водоотведения","Наличие водоотведения","Отсутствие водоотведения") -> Отсутствие водоотведения | BI6: =VLOOKUP(BH6,'Описание (градации)'!$E$13:$F$14,2,0) -> 1 | BJ6: =N6 -> 0 | BK6: =VLOOKUP(BJ6,'Описание (градации)'!$E$15:$F$19,2,0) -> #N/A | BL6: =L6 -> 0 | BM6: =VLOOKUP(BL6,'Описание (градации)'!$E$20:$F$24,2,0) -> #N/A | BN6: =M6 -> 0 | BO6: =VLOOKUP(BN6,'Описание (градации)'!$E$25:$F$27,2,0) -> #N/A | BP6: =O6 -> 0 | BQ6: =VLOOKUP(BP6,'Описание (градации)'!$E$28:$F$29,2,0) -> #N/A | BR6: =D6 -> 0 | BS6: =IF(BR6<400,400,IF(BR6>4510000,4510000,BR6)) -> 400 | BT6: =ROUND(EXP(0.3620826966*(15.93881008-5.49662653*LN(LN(BS6))))/EXP(0.3620826966*(15.93881008-5.49662653*LN(LN(1000)))),4) -> 1.3274 | BU6: =H6 -> 0 | BV6: =IF(BU6<50,50,IF(BU6>630,630,BU6)) -> 50 | BW6: =ROUND(EXP(4.118629221*(EXP(1)^(1.71093948-0.01799629*LN(BV6))))/EXP(4.118629221*(EXP(1)^(1.71093948-0.01799629*LN(100)))),4) -> 1.3013 | BX6: =E6 -> 0 | BY6: =IF(BX6<1,1,IF(BX6>203.57,203.57,BX6)) -> 1 | BZ6: =ROUND(EXP(0.4276469859*(5.64644498-0.48211057*LN(BY6)+0.10557587*LN(BY6)^2+0.00096428*LN(BY6)^3-0.00414511*LN(BY6)^4))/EXP(0.4276469859*(5.64644498-0.48211057*LN(5)+0.10557587*LN(5)^2+0.00096428*LN(5)^3-0.00414511*LN(5)^4)),4) -> 1.2524 | CA6: =K6 -> 0 | CB6: =VLOOKUP(CA6,'Описание (градации)'!$E$33:$F$35,2,0) -> #N/A | CC6: Наличие уторгования | CD6: =0.91 -> 0.91 | CE6: =ROUND(BA6*BC6*BE6*BG6*BI6*BK6*BM6*BO6*BQ6*BT6*BW6*BZ6*CB6*CD6,2) -> #N/A | CF6: =ROUND(CE6*BR6,2) -> #N/A | CG6: =8013 -> 8013 | CH6: =IF(P6="","Объект новый",IF(AS6=CG6,CE6-P6,"объект пришел из другой модели")) -> Объект новый | CI6: =IF(AX6="",IF(AJ6<>"","ОСПАРИВАНИЕ",IF(AY6<>"","СУД",IF(AD6="","",AD6))),AX6) | CJ6: =B6 -> 0 | CK6: =317.4645 -> 317.4645 | CL6: =IF(I6="",IF(AQ6="13:011","Отсутствие газоснабжения",IF(AQ6="13:021","Отсутствие газоснабжения",IF(X6="наличие","Наличие газоснабжения","Отсутствие газоснабжения"))),I6) -> Отсутствие газоснабжения | CM6: =VLOOKUP(CL6,'Описание (градации)'!$E$7:$F$8,2,0) -> 1 | CN6: =IF(F6="",IF(V6="","Отсутствие электроснабжения",IF(V6="отсутствие","Отсутствие электроснабжения","Наличие электроснабжения")),F6) -> Отсутствие электроснабжения | CO6: =VLOOKUP(CN6,'Описание (градации)'!$E$9:$F$10,2,0) -> 0.6102 | CP6: ="Отсутствие водоснабжения" -> Отсутствие водоснабжения | CQ6: =VLOOKUP(CP6,'Описание (градации)'!$E$11:$F$12,2,0) -> 1 | CR6: ="Отсутствие водоотведения" -> Отсутствие водоотведения | CS6: =VLOOKUP(CR6,'Описание (градации)'!$E$13:$F$14,2,0) -> 1 | CT6: =IF(AC6="",VLOOKUP(AB6,'ВПР статус и численность'!$A$2:$C$1992,3,0),VLOOKUP(AC6,'ВПР статус и численность'!$A$2:$C$1992,3,0)) -> #N/A | CU6: =VLOOKUP(CT6,'Описание (градации)'!$E$15:$F$19,2,0) -> #N/A | CV6: =IF(AC6="",VLOOKUP(AB6,'ВПР статус и численность'!$A$2:$B$1992,2,0),VLOOKUP(AC6,'ВПР статус и численность'!$A$2:$B$1992,2,0)) -> #N/A | CW6: =VLOOKUP(CV6,'Описание (градации)'!$E$20:$F$24,2,0) -> #N/A | CX6: =IF(AQ6="13:011","Садовый участок",IF(AQ6="13:021","Садовый участок",IF(AQ6="13:031","Дачный участок","ИЖС"))) -> ИЖС | CY6: =VLOOKUP(CX6,'Описание (градации)'!$E$25:$F$27,2,0) -> 1 | CZ6: =IF(Y6="Наличие ЛЭП","Наличие ЛЭП","Отсутствие ЛЭП") -> Отсутствие ЛЭП | DA6: =VLOOKUP(CZ6,'Описание (градации)'!$E$28:$F$29,2,0) -> 1 | DB6: =IF(S6<400,400,IF(S6>4510000,4510000,S6)) -> 400 | DC6: =ROUND(EXP(0.3620826966*(15.93881008-5.49662653*LN(LN(DB6))))/EXP(0.3620826966*(15.93881008-5.49662653*LN(LN(1000)))),4) -> 1.3274 | DD6: =S6 -> 0 | DE6: =IF(H6="",VLOOKUP(расчет!W6,'Средние расстояния'!$A$2:$C$55,2,0),H6) -> #N/A | DF6: =IF(DE6<50,50,IF(DE6>630,630,DE6)) -> #N/A | DG6: =ROUND(EXP(4.118629221*(EXP(1)^(1.71093948-0.01799629*LN(DF6))))/EXP(4.118629221*(EXP(1)^(1.71093948-0.01799629*LN(100)))),4) -> #N/A | DH6: =IF(E6="",VLOOKUP(W6,'Средние расстояния'!$A$2:$C$55,3,0),E6) -> #N/A | DI6: =IF(DH6<1,1,IF(DH6>203.57,203.57,DH6)) -> #N/A | DJ6: =ROUND(EXP(0.4276469859*(5.64644498-0.48211057*LN(DI6)+0.10557587*LN(DI6)^2+0.00096428*LN(DI6)^3-0.00414511*LN(DI6)^4))/EXP(0.4276469859*(5.64644498-0.48211057*LN(5)+0.10557587*LN(5)^2+0.00096428*LN(5)^3-0.00414511*LN(5)^4)),4) -> #N/A | DK6: Не находится в зоне влияния локальных центров | DL6: =VLOOKUP(DK6,'Описание (градации)'!$E$33:$F$35,2,0) -> 1 | DM6: Наличие уторгования | DN6: =0.91 -> 0.91 | DO6: =ROUND(CK6*CM6*CO6*CQ6*CS6*CU6*CW6*CY6*DA6*DC6*DG6*DJ6*DL6*DN6,2) -> #N/A | DP6: =ROUND(DO6*S6,2) -> #N/A | DQ6: СТ16_Ф1_М13_18052021_Бунаков_Измененные | DR6: =8013 -> 8013 | DS6: =IF(OR(DP6<0,DP6=0),"ОТРИЦАТЕЛЬНОЕ ЗНАЧЕНИЕ",IF(DY6=0,"Пересчет не требуется","Готов")) -> #N/A | DT6: =AQ6 -> 0 | DU6: 13. СЕГМЕНТ "Садоводство и огородничество, малоэтажная жилая застройка" | DV6: =13 -> 13 | DW6: =VLOOKUP(DT6,'справочник ври'!$A$3:$B$271,2,0) -> #N/A | DX6: =AT6 -> 0 | DY6: =IF(ISBLANK(P6),"Новый объект",IF(DR6=AS6,ABS(DP6-Q6),"Объект из другой модели")) -> Новый объект | DZ6: =IF(DY6="Объект из другой модели",IF(OR(DO6<9,DO6>873),"Отклонение УПКС","УПКС в допустимом интервале "),IF(DY6<1000000,"Изменение менее 1 млн","Внимание!Изменение более 1млн")) -> Внимание!Изменение более 1млн | EA6: =IF(F6="","Новое значение",IF(CN6=F6,"Осталось предыдущее значение ЦФ","ИЗМЕНЕНИЕ")) -> Новое значение | EB6: =IF(I6="","Новое значение",IF(I6=CL6,"Осталось предыдущее значение ЦФ","ИЗМЕНЕНИЕ")) -> Новое значение | EC6: =IF(AN6="не готов","ИЗМЕНЕНИЕ","Осталось предыдущее значение ЦФ") -> Осталось предыдущее значение ЦФ | ED6: =IF(E6="","Новое значение",IF(E6=DH6,"Осталось предыдущее значение ЦФ","ИЗМЕНЕНИЕ")) -> Новое значение | EE6: =IF(H6="","Новое значение",IF(H6=DF6,"Осталось предыдущее значение ЦФ","ИЗМЕНЕНИЕ")) -> Новое значение | EF6: =IF(M6="","Новое значение",IF(CX6=M6,"Осталось предыдущее значение ЦФ","ИЗМЕНЕНИЕ")) -> Новое значение | EG6: =IF(AV6=AQ6,"Осталось предыдущее значение ЦФ","ИЗМЕНЕНИЕ") -> Осталось предыдущее значение ЦФ | EH6: =IF(J6="","Новое значение",IF(CP6=J6,"Осталось предыдущее значение ЦФ","ИЗМЕНЕНИЕ")) -> Новое значение | EI6: =IF(G6="","Новое значение",IF(CR6=G6,"Осталось предыдущее значение ЦФ","ИЗМЕНЕНИЕ")) -> Новое значение | EJ6: =IF(O6="","Новое значение",IF(CZ6=O6,"Осталось предыдущее значение ЦФ","ИЗМЕНЕНИЕ")) -> Новое значение | EK6: =IF(K6="","Новое значение",IF(DK6=K6,"Осталось предыдущее значение ЦФ","ИЗМЕНЕНИЕ")) -> Новое значение | EL6: =IF(N6="","Новое значение",IF(CT6=N6,"Осталось предыдущее значение ЦФ","ИЗМЕНЕНИЕ")) -> Новое значение | EM6: =IF(L6="","Новое значение",IF(CV6=L6,"Осталось предыдущее значение ЦФ","ИЗМЕНЕНИЕ")) -> Новое значение
BA7: =317.4645 -> 317.4645 | BB7: =IF(I7="Наличие газоснабжения","Наличие газоснабжения","Отсутствие газоснабжения") -> Отсутствие газоснабжения | BC7: =VLOOKUP(BB7,'Описание (градации)'!$E$7:$F$8,2,0) -> 1 | BD7: =IF(F7="Наличие электроснабжения","Наличие электроснабжения","Отсутствие электроснабжения") -> Отсутствие электроснабжения | BE7: =VLOOKUP(BD7,'Описание (градации)'!$E$9:$F$10,2,0) -> 0.6102 | BF7: =IF(J7="Наличие водоснабжения","Наличие водоснабжения","Отсутствие водоснабжения") -> Отсутствие водоснабжения | BG7: =VLOOKUP(BF7,'Описание (градации)'!$E$11:$F$12,2,0) -> 1 | BH7: =IF(I7="Наличие водоотведения","Наличие водоотведения","Отсутствие водоотведения") -> Отсутствие водоотведения | BI7: =VLOOKUP(BH7,'Описание (градации)'!$E$13:$F$14,2,0) -> 1 | BJ7: =N7 -> 0 | BK7: =VLOOKUP(BJ7,'Описание (градации)'!$E$15:$F$19,2,0) -> #N/A | BL7: =L7 -> 0 | BM7: =VLOOKUP(BL7,'Описание (градации)'!$E$20:$F$24,2,0) -> #N/A | BN7: =M7 -> 0 | BO7: =VLOOKUP(BN7,'Описание (градации)'!$E$25:$F$27,2,0) -> #N/A | BP7: =O7 -> 0 | BQ7: =VLOOKUP(BP7,'Описание (градации)'!$E$28:$F$29,2,0) -> #N/A | BR7: =D7 -> 0 | BS7: =IF(BR7<400,400,IF(BR7>4510000,4510000,BR7)) -> 400 | BT7: =ROUND(EXP(0.3620826966*(15.93881008-5.49662653*LN(LN(BS7))))/EXP(0.3620826966*(15.93881008-5.49662653*LN(LN(1000)))),4) -> 1.3274 | BU7: =H7 -> 0 | BV7: =IF(BU7<50,50,IF(BU7>630,630,BU7)) -> 50 | BW7: =ROUND(EXP(4.118629221*(EXP(1)^(1.71093948-0.01799629*LN(BV7))))/EXP(4.118629221*(EXP(1)^(1.71093948-0.01799629*LN(100)))),4) -> 1.3013 | BX7: =E7 -> 0 | BY7: =IF(BX7<1,1,IF(BX7>203.57,203.57,BX7)) -> 1 | BZ7: =ROUND(EXP(0.4276469859*(5.64644498-0.48211057*LN(BY7)+0.10557587*LN(BY7)^2+0.00096428*LN(BY7)^3-0.00414511*LN(BY7)^4))/EXP(0.4276469859*(5.64644498-0.48211057*LN(5)+0.10557587*LN(5)^2+0.00096428*LN(5)^3-0.00414511*LN(5)^4)),4) -> 1.2524 | CA7: =K7 -> 0 | CB7: =VLOOKUP(CA7,'Описание (градации)'!$E$33:$F$35,2,0) -> #N/A | CC7: Наличие уторгования | CD7: =0.91 -> 0.91 | CE7: =ROUND(BA7*BC7*BE7*BG7*BI7*BK7*BM7*BO7*BQ7*BT7*BW7*BZ7*CB7*CD7,2) -> #N/A | CF7: =ROUND(CE7*BR7,2) -> #N/A | CG7: =8013 -> 8013 | CH7: =IF(P7="","Объект новый",IF(AS7=CG7,CE7-P7,"объект пришел из другой модели")) -> Объект новый | CI7: =IF(AX7="",IF(AJ7<>"","ОСПАРИВАНИЕ",IF(AY7<>"","СУД",IF(AD7="","",AD7))),AX7) | CJ7: =B7 -> 0 | CK7: =317.4645 -> 317.4645 | CL7: =IF(I7="",IF(AQ7="13:011","Отсутствие газоснабжения",IF(AQ7="13:021","Отсутствие газоснабжения",IF(X7="наличие","Наличие газоснабжения","Отсутствие газоснабжения"))),I7) -> Отсутствие газоснабжения | CM7: =VLOOKUP(CL7,'Описание (градации)'!$E$7:$F$8,2,0) -> 1 | CN7: =IF(F7="",IF(V7="","Отсутствие электроснабжения",IF(V7="отсутствие","Отсутствие электроснабжения","Наличие электроснабжения")),F7) -> Отсутствие электроснабжения | CO7: =VLOOKUP(CN7,'Описание (градации)'!$E$9:$F$10,2,0) -> 0.6102 | CP7: ="Отсутствие водоснабжения" -> Отсутствие водоснабжения | CQ7: =VLOOKUP(CP7,'Описание (градации)'!$E$11:$F$12,2,0) -> 1 | CR7: ="Отсутствие водоотведения" -> Отсутствие водоотведения | CS7: =VLOOKUP(CR7,'Описание (градации)'!$E$13:$F$14,2,0) -> 1 | CT7: =IF(AC7="",VLOOKUP(AB7,'ВПР статус и численность'!$A$2:$C$1992,3,0),VLOOKUP(AC7,'ВПР статус и численность'!$A$2:$C$1992,3,0)) -> #N/A | CU7: =VLOOKUP(CT7,'Описание (градации)'!$E$15:$F$19,2,0) -> #N/A | CV7: =IF(AC7="",VLOOKUP(AB7,'ВПР статус и численность'!$A$2:$B$1992,2,0),VLOOKUP(AC7,'ВПР статус и численность'!$A$2:$B$1992,2,0)) -> #N/A | CW7: =VLOOKUP(CV7,'Описание (градации)'!$E$20:$F$24,2,0) -> #N/A | CX7: =IF(AQ7="13:011","Садовый участок",IF(AQ7="13:021","Садовый участок",IF(AQ7="13:031","Дачный участок","ИЖС"))) -> ИЖС | CY7: =VLOOKUP(CX7,'Описание (градации)'!$E$25:$F$27,2,0) -> 1 | CZ7: =IF(Y7="Наличие ЛЭП","Наличие ЛЭП","Отсутствие ЛЭП") -> Отсутствие ЛЭП | DA7: =VLOOKUP(CZ7,'Описание (градации)'!$E$28:$F$29,2,0) -> 1 | DB7: =IF(S7<400,400,IF(S7>4510000,4510000,S7)) -> 400 | DC7: =ROUND(EXP(0.3620826966*(15.93881008-5.49662653*LN(LN(DB7))))/EXP(0.3620826966*(15.93881008-5.49662653*LN(LN(1000)))),4) -> 1.3274 | DD7: =S7 -> 0 | DE7: =IF(H7="",VLOOKUP(расчет!W7,'Средние расстояния'!$A$2:$C$55,2,0),H7) -> #N/A | DF7: =IF(DE7<50,50,IF(DE7>630,630,DE7)) -> #N/A | DG7: =ROUND(EXP(4.118629221*(EXP(1)^(1.71093948-0.01799629*LN(DF7))))/EXP(4.118629221*(EXP(1)^(1.71093948-0.01799629*LN(100)))),4) -> #N/A | DH7: =IF(E7="",VLOOKUP(W7,'Средние расстояния'!$A$2:$C$55,3,0),E7) -> #N/A | DI7: =IF(DH7<1,1,IF(DH7>203.57,203.57,DH7)) -> #N/A | DJ7: =ROUND(EXP(0.4276469859*(5.64644498-0.48211057*LN(DI7)+0.10557587*LN(DI7)^2+0.00096428*LN(DI7)^3-0.00414511*LN(DI7)^4))/EXP(0.4276469859*(5.64644498-0.48211057*LN(5)+0.10557587*LN(5)^2+0.00096428*LN(5)^3-0.00414511*LN(5)^4)),4) -> #N/A | DK7: Не находится в зоне влияния локальных центров | DL7: =VLOOKUP(DK7,'Описание (градации)'!$E$33:$F$35,2,0) -> 1 | DM7: Наличие уторгования | DN7: =0.91 -> 0.91 | DO7: =ROUND(CK7*CM7*CO7*CQ7*CS7*CU7*CW7*CY7*DA7*DC7*DG7*DJ7*DL7*DN7,2) -> #N/A | DP7: =ROUND(DO7*S7,2) -> #N/A | DQ7: СТ16_Ф1_М13_18052021_Бунаков_Измененные | DR7: =8013 -> 8013 | DS7: =IF(OR(DP7<0,DP7=0),"ОТРИЦАТЕЛЬНОЕ ЗНАЧЕНИЕ",IF(DY7=0,"Пересчет не требуется","Готов")) -> #N/A | DT7: =AQ7 -> 0 | DU7: 13. СЕГМЕНТ "Садоводство и огородничество, малоэтажная жилая застройка" | DV7: =13 -> 13 | DW7: =VLOOKUP(DT7,'справочник ври'!$A$3:$B$271,2,0) -> #N/A | DX7: =AT7 -> 0 | DY7: =IF(ISBLANK(P7),"Новый объект",IF(DR7=AS7,ABS(DP7-Q7),"Объект из другой модели")) -> Новый объект | DZ7: =IF(DY7="Объект из другой модели",IF(OR(DO7<9,DO7>873),"Отклонение УПКС","УПКС в допустимом интервале "),IF(DY7<1000000,"Изменение менее 1 млн","Внимание!Изменение более 1млн")) -> Внимание!Изменение более 1млн | EA7: =IF(F7="","Новое значение",IF(CN7=F7,"Осталось предыдущее значение ЦФ","ИЗМЕНЕНИЕ")) -> Новое значение | EB7: =IF(I7="","Новое значение",IF(I7=CL7,"Осталось предыдущее значение ЦФ","ИЗМЕНЕНИЕ")) -> Новое значение | EC7: =IF(AN7="не готов","ИЗМЕНЕНИЕ","Осталось предыдущее значение ЦФ") -> Осталось предыдущее значение ЦФ | ED7: =IF(E7="","Новое значение",IF(E7=DH7,"Осталось предыдущее значение ЦФ","ИЗМЕНЕНИЕ")) -> Новое значение | EE7: =IF(H7="","Новое значение",IF(H7=DF7,"Осталось предыдущее значение ЦФ","ИЗМЕНЕНИЕ")) -> Новое значение | EF7: =IF(M7="","Новое значение",IF(CX7=M7,"Осталось предыдущее значение ЦФ","ИЗМЕНЕНИЕ")) -> Новое значение | EG7: =IF(AV7=AQ7,"Осталось предыдущее значение ЦФ","ИЗМЕНЕНИЕ") -> Осталось предыдущее значение ЦФ | EH7: =IF(J7="","Новое значение",IF(CP7=J7,"Осталось предыдущее значение ЦФ","ИЗМЕНЕНИЕ")) -> Новое значение | EI7: =IF(G7="","Новое значение",IF(CR7=G7,"Осталось предыдущее значение ЦФ","ИЗМЕНЕНИЕ")) -> Новое значение | EJ7: =IF(O7="","Новое значение",IF(CZ7=O7,"Осталось предыдущее значение ЦФ","ИЗМЕНЕНИЕ")) -> Новое значение | EK7: =IF(K7="","Новое значение",IF(DK7=K7,"Осталось предыдущее значение ЦФ","ИЗМЕНЕНИЕ")) -> Новое значение | EL7: =IF(N7="","Новое значение",IF(CT7=N7,"Осталось предыдущее значение ЦФ","ИЗМЕНЕНИЕ")) -> Новое значение | EM7: =IF(L7="","Новое значение",IF(CV7=L7,"Осталось предыдущее значение ЦФ","ИЗМЕНЕНИЕ")) -> Новое значение

Sheet СТОПЛИСТ
A1: CadastralNumber | B1: ControlSP

Sheet ПЕРЕСЧЕТ НЕ ТРЕБУЕТСЯ
A1: CadastralNumber | B1: Status_kc | C1: loc_VICode | D1: Segment | E1: loc_SgCode | F1: loc_GroupName | G1: Old_Utlbydoc

Sheet ГОТОВ
A1: CadastralNumber | C1: loc_factor_822 | E1: loc_factor_804 | G1: loc_factor_828 | I1: loc_factor_803 | K1: loc_factor_813 | M1: loc_factor_841 | O1: loc_factor_825 | Q1: loc_factor_829 | T1: loc_factor_8071 | U1: loc_factor_807 | V1: loc_factor_816 | X1: loc_factor_8161 | Y1: loc_factor_812 | AA1: loc_factor_8121 | AB1: loc_factor_815 | AD1: loc_factor_827 | AF1: Specific_CadastralCost | AG1: CadastralCost | AH1: CadastralCostDesc | AI1: id_group | AJ1: Status_kc | AK1: loc_VICode | AL1: Segment | AM1: loc_SgCode | AN1: loc_GroupName | AO1: Old_Utlbydoc

Sheet Средние расстояния
A1: Названия строк | B1: Среднее по полю Расстояние до ЕКБ | C1: Среднее по полю Расстояние до центра МО
A2: 02 | B2: 121 | C2: 12
A3: 03 | B3: 184 | C3: 17
A4: 04 | B4: 87 | C4: 8
A5: 05 | B5: 179 | C5: 19
A6: 06 | B6: 253 | C6: 17
A7: 09 | B7: 106 | C7: 8
A8: 10 | B8: 177 | C8: 7
A9: 11 | B9: 412 | C9: 6
A10: 12 | B10: 521 | C10: 18
A11: 15 | B11: 243 | C11: 10
A12: 16 | B12: 97 | C12: 12
A13: 18 | B13: 78 | C13: 2
... A55: 73 | B55: 169 | C55: 26

Sheet Формула модели
A1: Модель №13 «Садоводческое, огородническое и дачное использование, малоэтажная жилая застройка. ИЖС и сады». y=317,4645*V1*V2*V3*V4*V5*V6*V7*V8*V9*V10*V11*V12*V13 Где: y – удельный показатель; 317,4645 – базовая стоимость (стоимость типового объекта); V1 – Поправочный коэффициент фактора «газоснабжение»; V2 – Поправочный коэффициент фактора «электроснабжение»; V3 – Поправочный коэффициент фактора «водоснабжение»; V4 – Поправочный коэффициент фактора «водоотведение»; V5 - Поправочный коэффициент фактора «управленческий округ»; V6 – Поправочный коэффициент фактора «статус и численность населенного пункта»; V7 – Поправочный коэффициент фактора «вид разрешенного использования»; V8 – Поправочный коэффициент фактора «ЛЭП над участком»; V9 – Поправочный коэффициент фактора «общая площадь»; V10 – Поправочный коэффициент фактора «расстояние до Екатеринбурга»; V11– Поправочный коэффициент фактора «расстояние до центра муниципального образования»; V12 – Поправочный коэффициент фактора «локальные центры (отрицательные и положительные зоны влияния)»; V13 – Поправочный коэффициент фактора «уторгование».

Sheet справочник ври
A1: loc_VICode | B1: loc_GroupName
A2: Код расчета вида использования | B2: Наименование вида использования
A3: 01:010 | B3: Растениеводство в целом. Включает коды расчета вида использования 01.020-01.060
A4: 01:020 | B4: Выращивание зерновых, бобовых, кормовых, технических, масличных, эфиромасличных и иных сельскохозяйственных культур
A5: 01:030 | B5: Овощеводство в целом, связанное с производством картофеля, листовых, плодовых, луковичных и бахчевых сельскохозяйственных культур, в том числе с использованием теплиц
A6: 01:031 | B6: Овощеводство в открытом грунте
A7: 01:032 | B7: Овощеводство тепличное
A8: 01:040 | B8: Выращивание тонизирующих, лекарственных, цветочных культур в целом
A9: 01:041 | B9: Выращивание тонизирующих, лекарственных, цветочных культур. Травы
A10: 01:042 | B10: Выращивание тонизирующих, лекарственных, цветочных культур. Кустарники
A11: 01:050 | B11: Садоводство в целом - выращивание многолетних плодовых и ягодных культур, винограда и иных многолетних культур
A12: 01:051 | B12: Садоводство плодовое
... A271: 14:000 | B271: Иное использование

Sheet ВПР статус и численность
A1: Код НП | B1: Численность НП по справочнику | C1: Управленческий округ
A2: 49:018:2:5:6 | B2: СНП менее 1 000 | C2: Восточный управленческий округ
A3: 00:002:0:0:0 | B3: Межселенная территория | C3: Западный управленческий округ
A4: 06:038:2:5:6 | B4: СНП менее 1 000 | C4: Восточный управленческий округ
A5: 00:003:0:0:0 | B5: Межселенная территория | C5: Восточный управленческий округ
A6: 06:015:2:5:6 | B6: СНП менее 1 000 | C6: Восточный управленческий округ
A7: 10:009:2:5:6 | B7: СНП менее 1 000 | C7: Горнозаводской управленческий округ
A8: 22:044:2:5:6 | B8: СНП менее 1 000 | C8: Северный управленческий округ
A9: 12:013:2:5:6 | B9: СНП менее 1 000 | C9: Северный управленческий округ
A10: 12:012:2:3:6 | B10: СНП менее 1 000 | C10: Северный управленческий округ
A11: 12:005:2:5:6 | B11: СНП менее 1 000 | C11: Северный управленческий округ
A12: 12:030:2:5:6 | B12: СНП менее 1 000 | C12: Северный управленческий округ
... A1992: 52:006:2:3:6 | B1992: СНП менее 1 000 | C1992: Южный управленческий округ

Sheet Описание (градации)
A3: Наименование модели | B3: Ответственный
B4: Кандель Е.А. | F4: Это сохраняем в БД как значение ценового фактора | G4: Это для описании модели
A5: Фактор | B5: Обозначение фактора | C5: Номер модели | D5: Наименование поля БД | E5: Градации ЦФ | F5: Поправка | G5: Максимальное значение поправки (при наличии) | H5: Минимальное значение поправки (при наличии)
A6: Константа | B6: С0 | C6: 8013 | D6: НЕТ | E6: Коэффициент | F6: 317.4645
A7: Газоснабжение | B7: V1 | C7: 8013 | D7: Газоснабжение | E7: Наличие газоснабжения | F7: 1.7823 | I7: loc_factor_822
E8: Отсутствие газоснабжения | F8: 1 | I8: loc_factor_822
A9: Электроснабжение | B9: V2 | C9: 8013 | D9: Электроснабжение | E9: Наличие электроснабжения | F9: 1 | I9: loc_factor_804
E10: Отсутствие электроснабжения | F10: 0.6102 | I10: loc_factor_804
A11: Водоснабжение | B11: V3 | C11: 8013 | D11: Водоснабжение | E11: Наличие водоснабжения | F11: 1.4141 | I11: loc_factor_828
E12: Отсутствие водоснабжения | F12: 1 | I12: loc_factor_828
A13: Водоотведение | B13: V4 | C13: 8013 | D13: Водоотведение | E13: Наличие водоотведения | F13: 1.4155 | I13: loc_factor_803
E14: Отсутствие водоотведения | F14: 1 | I14: loc_factor_803
A15: Управленческий округ | B15: V5 | C15: 8013 | D15: Управленческий округ | E15: Горнозаводской управленческий округ | F15: 0.8788 | I15: loc_factor_813 | J15: Справочник !
E16: Восточный управленческий округ | F16: 1 | I16: loc_factor_813
E17: Западный управленческий округ | F17: 0.8296 | I17: loc_factor_813
E18: Южный управленческий округ | F18: 0.9731 | I18: loc_factor_813
E19: Северный управленческий округ | F19: 0.7852 | I19: loc_factor_813
A20: Статус и численность населенного пункта | B20: V6 | C20: 8013 | D20: Статус и численность населенного пункта | E20: ГНП от 50 000 до 100 000 | F20: 1 | I20: loc_factor_841 | J20: Справочник !
E21: ГНП менее 50 000 | F21: 0.8017 | I21: loc_factor_841
E22: СНП более 1 000 | F22: 0.7544 | I22: loc_factor_841
E23: СНП менее 1 000 | F23: 0.742 | I23: loc_factor_841
E24: Межселенная территория | F24: 0.6143 | I24: loc_factor_841
A25: Вид разрешённого использования | B25: V7 | C25: 8013 | D25: Код расчета вида использования | E25: ИЖС | F25: 1 | I25: loc_factor_825
E26: Дачный участок | F26: 0.7697 | I26: loc_factor_825
E27: Садовый участок | F27: 0.3975 | I27: loc_factor_825
A28: ЛЭП над участком | B28: V8 | C28: 8013 | D28: ЛЭП над участком | E28: Наличие ЛЭП | F28: 0.6954 | I28: loc_factor_829
E29: Отсутствие ЛЭП | F29: 1 | I29: loc_factor_829
A30: Общая площадь | B30: V9 | C30: 8013 | D30: Площадь | E30: Количественный | F30: EXP(0,3620826966*(15,93881008-5,49662653*LN(LN(ЕСЛИ(C2<400;400;C2)))))/EXP(0,3620826966*(15,93881008-5,49662653*LN(LN(1000)))) | G30: 1.3274 | H30: 0.2048 | I30: loc_factor_807
A31: Расстояние до Екатеринбурга | B31: V10 | C31: 8013 | D31: Расстояние до центра Екатеринбурга | E31: Количественный | F31: EXP(4,118629221*(EXP(1)^(1,71093948-0,01799629*LN(ЕСЛИ(M2="";ВПР(O2;Расстояния!A:B;2;0);M2)))))/EXP(4,118629221*(EXP(1)^(1,71093948-0,01799629*LN(100)))) | G31: 1.3013 | H31: 0.5048 | I31: loc_factor_816
A32: Расстояние до центра муниципального образования | B32: V11 | C32: 8013 | D32: Расстояние до административного центра МО | E32: Количественный | F32: EXP(0,4276469859*(5,64644498-0,48211057*LN(ЕСЛИ(H2="";ВПР(O2;Расстояния!A:C;3;0);ЕСЛИ(H2<1;1;H2)))+0,10557587*LN(ЕСЛИ(H2="";ВПР(O2;Расстояния!A:C;3;0);ЕСЛИ(H2<1;1;H2)))^2+0,00096428*LN(ЕСЛИ(H2="";ВПР(O2;Расстояния!A:C;3;0);ЕСЛИ(H2<1;1;H2)))^3-0,00414511*LN(ЕСЛИ(H2="";ВПР(O2;Расстояния!A:C;3;0);ЕСЛИ(H2<1;1;H2)))^4))/EXP(0,4276469859*(5,64644498-0,48211057*LN(5)+0,10557587*LN(5)^2+0,00096428*LN(5)^3-0,00414511*LN(5)^4)) | G32: 1.2524 | H32: 0.3872 | I32: loc_factor_812
A33: Локальные центры (отрицательные и положительные зоны влияния) | B33: V12 | C33: 8013 | D33: Локальные центры (отрицательные и положительные зоны влияния) | E33: Расположен в зоне влияния отрицательных локальных центров | F33: 0.7807 | I33: loc_factor_815
E34: Не находится в зоне влияния локальных центров | F34: 1 | I34: loc_factor_815
E35: Расположен в зоне влияния положительных локальных центров | F35: 1.2103 | I35: loc_factor_815
A36: Уторгование | B36: V13 | C36: 8013 | E36: Наличие уторгования | F36: 0.91 | I36: loc_factor_827
E37: Отсутствие уторгования | F37: 1 | I37: loc_factor_827
